Workbook

Sheet Revenue driver
B4: (In Millions) | C4: 43921 | D4: =EOMONTH(C4,12) -> 44286 | E4: =EOMONTH(D4,12) -> 44651 | F4: =EOMONTH(E4,12) -> 45016 | G4: =EOMONTH(F4,12) -> 45382 | H4: =EOMONTH(G4,12) -> 45747 | I4: =EOMONTH(H4,12) -> 46112 | K4: =EOMONTH(I4,12) -> 46477 | L4: =EOMONTH(K4,12) -> 46843 | M4: =EOMONTH(L4,12) -> 47208 | N4: =EOMONTH(M4,12) -> 47573 | O4: =EOMONTH(N4,12) -> 47938 | P4: =EOMONTH(O4,12) -> 48304 | Q4: =EOMONTH(P4,12) -> 48669 | R4: =EOMONTH(Q4,12) -> 49034 | S4: =EOMONTH(R4,12) -> 49399 | T4: =EOMONTH(S4,12) -> 49765
B5: Revenue driver:
B6: Revenue | C6: 248702 | D6: 241430.6 | E6: 309762.7 | F6: 428395.6 | G6: 507888.3 | H6: 593580.5 | I6: 688207.4 | K6: =AVERAGE(I9:K9)*K13 -> 914969.92 | L6: =AVERAGE(K9:L9)*L13 -> 1167507.9 | M6: =AVERAGE(L9:M9)*M13 -> 1467607.8 | N6: =AVERAGE(M9:N9)*N13 -> 1812809.9 | O6: =AVERAGE(N9:O9)*O13 -> 2203289.8 | P6: =AVERAGE(O9:P9)*P13 -> 2637618 | Q6: =AVERAGE(P9:Q9)*Q13 -> 3112542.8 | R6: =AVERAGE(Q9:R9)*R13 -> 3639457.9 | S6: =AVERAGE(R9:S9)*S13 -> 4219042.7 | T6: =AVERAGE(S9:T9)*T13 -> 4851117.8
B7: No. of stores | C7: 214 | D7: 234 | E7: 284 | F7: 324 | G7: 365 | H7: 415 | I7: 500 | K7: =I7+K8 -> 550 | L7: =K7+L8 -> 600 | M7: =L7+M8 -> 650 | N7: =M7+N8 -> 700 | O7: =N7+O8 -> 750 | P7: =O7+P8 -> 800 | Q7: =P7+Q8 -> 850 | R7: =Q7+R8 -> 900 | S7: =R7+S8 -> 950 | T7: =S7+T8 -> 1000
B8: Additions to the stores | C8: 0 | D8: =D7-C7 -> 20 | E8: =E7-D7 -> 50 | F8: =F7-E7 -> 40 | G8: =G7-F7 -> 41 | H8: =H7-G7 -> 50 | I8: 85 | K8: 50 | L8: 50 | M8: 50 | N8: 50 | O8: 50 | P8: 50 | Q8: 50 | R8: 50 | S8: 50 | T8: 50
B9: Retail sales area | C9: 7.8 | D9: 8.8 | E9: 11.5 | F9: 13.4 | G9: 15.1 | H9: 17.2 | I9: 20.6 | K9: =I9+K10 -> 23.1 | L9: =K9+L10 -> 25.6 | M9: =L9+M10 -> 28.1 | N9: =M9+N10 -> 30.6 | O9: =N9+O10 -> 33.1 | P9: =O9+P10 -> 35.6 | Q9: =P9+Q10 -> 38.1 | R9: =Q9+R10 -> 40.6 | S9: =R9+S10 -> 43.1 | T9: =S9+T10 -> 45.6
B10: Additions to retail sales area (sq.ft) | C10: 0 | D10: =D9-C9 -> 1 | E10: =E9-D9 -> 2.7 | F10: =F9-E9 -> 1.9 | G10: =G9-F9 -> 1.7 | H10: =H9-G9 -> 2.1 | I10: =I9-H9 -> 3.4 | K10: 2.5 | L10: 2.5 | M10: 2.5 | N10: 2.5 | O10: 2.5 | P10: 2.5 | Q10: 2.5 | R10: 2.5 | S10: 2.5 | T10: 2.5
B11: Average retail sales area per store | C11: 0 | D11: =D10*10^6/D8 -> 50000 | E11: =E10*10^6/E8 -> 54000 | F11: =F10*10^6/F8 -> 47500 | G11: =G10*10^6/G8 -> 41463.415 | H11: =H10*10^6/H8 -> 42000 | I11: =I10*10^6/I8 -> 40000 | K11: 44000 | L11: 44000 | M11: 44000 | N11: 44000 | O11: 44000 | P11: 44000 | Q11: 44000 | R11: 44000 | S11: 44000 | T11: 44000
B12: Revenue from sales from per retail sales area sq.ft | C12: 32879 | D12: 27306 | E12: 27454 | F12: 31096 | G12: 32941 | H12: 33869 | I12: 33422 | K12: 0 | L12: 0 | M12: 0 | N12: 0 | O12: 0 | P12: 0 | Q12: 0 | R12: 0 | S12: 0 | T12: 0
B13: Revenue per area sq.ft as calculated | C13: 0 | D13: =D6/AVERAGE(C9:D9) -> 29088.024 | E13: =E6/AVERAGE(D9:E9) -> 30518.493 | F13: =F6/AVERAGE(E9:F9) -> 34409.285 | G13: =G6/AVERAGE(F9:G9) -> 35641.284 | H13: =H6/AVERAGE(G9:H9) -> 36754.211 | I13: =I6/AVERAGE(H9:I9) -> 36413.09 | K13: =I13*(1+K14) -> 41875.053 | L13: =K13*(1+L14) -> 47946.936 | M13: =L13*(1+M14) -> 54659.507 | N13: =M13*(1+N14) -> 61765.243 | O13: =N13*(1+O14) -> 69177.072 | P13: =O13*(1+P14) -> 76786.55 | Q13: =P13*(1+Q14) -> 84465.205 | R13: =Q13*(1+R14) -> 92489.4 | S13: =R13*(1+S14) -> 100813.45 | T13: =S13*(1+T14) -> 109382.59
B14: Growth rate | C14: 0 | D14: 0 | E14: =E13/D13-1 -> 0.049177232 | F14: =F13/E13-1 -> 0.12748967 | G14: =G13/F13-1 -> 0.035804262 | H14: =H13/G13-1 -> 0.031225764 | I14: =I13/H13-1 -> -0.0092811293 | K14: =INDEX($K$18:$T$20,MATCH('P & L'!$D$5,$B$18:$B$20,0), MATCH(K$4,$K$4:$T$4,0)) -> 0.15 | L14: =INDEX($K$18:$T$20,MATCH('P & L'!$D$5,$B$18:$B$20,0), MATCH(L$4,$K$4:$T$4,0)) -> 0.145 | M14: =INDEX($K$18:$T$20,MATCH('P & L'!$D$5,$B$18:$B$20,0), MATCH(M$4,$K$4:$T$4,0)) -> 0.14 | N14: =INDEX($K$18:$T$20,MATCH('P & L'!$D$5,$B$18:$B$20,0), MATCH(N$4,$K$4:$T$4,0)) -> 0.13 | O14: =INDEX($K$18:$T$20,MATCH('P & L'!$D$5,$B$18:$B$20,0), MATCH(O$4,$K$4:$T$4,0)) -> 0.12 | P14: =INDEX($K$18:$T$20,MATCH('P & L'!$D$5,$B$18:$B$20,0), MATCH(P$4,$K$4:$T$4,0)) -> 0.11 | Q14: =INDEX($K$18:$T$20,MATCH('P & L'!$D$5,$B$18:$B$20,0), MATCH(Q$4,$K$4:$T$4,0)) -> 0.1 | R14: =INDEX($K$18:$T$20,MATCH('P & L'!$D$5,$B$18:$B$20,0), MATCH(R$4,$K$4:$T$4,0)) -> 0.095 | ... T14: =INDEX($K$18:$T$20,MATCH('P & L'!$D$5,$B$18:$B$20,0), MATCH(T$4,$K$4:$T$4,0)) -> 0.085
B15: Like for Like growth (24 months) | C15: 0.109 | D15: -0.131 | E15: 0.167 | F15: 0.242 | G15: 0.099 | H15: 0.084 | I15: 0.081 | K15: 0 | L15: 0 | M15: 0 | N15: 0 | O15: 0 | P15: 0 | Q15: 0 | R15: 0 | S15: 0 | T15: 0
B17: Growth rate:
B18: High | K18: 0.18 | L18: 0.175 | M18: 0.17 | N18: 0.16 | O18: 0.15 | P18: 0.14 | Q18: 0.13 | R18: 0.12 | S18: 0.11 | T18: 0.1
B19: Base | K19: 0.15 | L19: 0.145 | M19: 0.14 | N19: 0.13 | O19: 0.12 | P19: 0.11 | Q19: 0.1 | R19: 0.095 | S19: 0.09 | T19: 0.085
B20: Low | K20: 0.12 | L20: 0.11 | M20: 0.105 | N20: 0.1 | O20: 0.095 | P20: 0.09 | Q20: 0.085 | R20: 0.08 | S20: 0.075 | T20: 0.07

Sheet Working Capital
C3: =D4-C4 -> 365 | D3: =E4-D4 -> 365 | E3: =F4-E4 -> 365 | F3: =G4-F4 -> 366 | G3: =H4-G4 -> 365 | H3: =I4-H4 -> 365 | I3: =K4-I4 -> 365 | K3: =L4-K4 -> 366 | L3: =M4-L4 -> 365 | M3: =N4-M4 -> 365 | N3: =O4-N4 -> 365 | O3: =P4-O4 -> 366 | P3: 366 | Q3: 366 | R3: 366 | S3: 366 | T3: 366
B4: (In Millions) | C4: 43921 | D4: =EOMONTH(C4,12) -> 44286 | E4: =EOMONTH(D4,12) -> 44651 | F4: =EOMONTH(E4,12) -> 45016 | G4: =EOMONTH(F4,12) -> 45382 | H4: =EOMONTH(G4,12) -> 45747 | I4: =EOMONTH(H4,12) -> 46112 | K4: =EOMONTH(I4,12) -> 46477 | L4: =EOMONTH(K4,12) -> 46843 | M4: =EOMONTH(L4,12) -> 47208 | N4: =EOMONTH(M4,12) -> 47573 | O4: =EOMONTH(N4,12) -> 47938 | P4: =EOMONTH(O4,12) -> 48304 | Q4: =EOMONTH(P4,12) -> 48669 | R4: =EOMONTH(Q4,12) -> 49034 | S4: =EOMONTH(R4,12) -> 49399 | T4: =EOMONTH(S4,12) -> 49765
B5: Working Capital Schedule:
B6: Inventory:
B7: Average inventories | C7: 0 | D7: =AVERAGE(BS!C24:D24) -> 20978.4 | E7: =AVERAGE(BS!D24:E24) -> 24954.7 | F7: =AVERAGE(BS!E24:F24) -> 29930.7 | G7: =AVERAGE(BS!F24:G24) -> 35853.95 | H7: =AVERAGE(BS!G24:H24) -> 44858.4 | I7: =AVERAGE(BS!H24:I24) -> 54725.05 | K7: =K10/K3*K8 -> 70358.056 | L7: =L10/L3*L8 -> 90023.328 | M7: =M10/M3*M8 -> 113163.21 | N7: =N10/N3*N8 -> 139780.79 | O7: =O10/O3*O8 -> 169425.44 | P7: =P10/P3*P8 -> 202823.8 | Q7: =Q10/Q3*Q8 -> 239343.89 | R7: =R10/R3*R8 -> 279861.86 | ... T7: =T10/T3*T8 -> 373034.36
B8: Total COGS | C8: 0 | D8: =-'P & L'!D11 -> 205546.8 | E8: =-'P & L'!E11 -> 263973.9 | F8: =-'P & L'!F11 -> 363839.5 | G8: =-'P & L'!G11 -> 432745.4 | H8: =-'P & L'!H11 -> 505517 | I8: =-'P & L'!I11 -> 584597.3 | K8: =-'P & L'!K11 -> 777724.43 | L8: =-'P & L'!L11 -> 992381.71 | M8: =-'P & L'!M11 -> 1247466.6 | N8: =-'P & L'!N11 -> 1540888.4 | O8: =-'P & L'!O11 -> 1872796.3 | P8: =-'P & L'!P11 -> 2241975.3 | Q8: =-'P & L'!Q11 -> 2645661.4 | R8: =-'P & L'!R11 -> 3093539.2 | ... T8: =-'P & L'!T11 -> 4123450.1
B9: Inventry turn-over ratio | C9: 0 | D9: =D8/D7 -> 9.7980208 | E9: =E8/E7 -> 10.578124 | F9: =F8/F7 -> 12.156064 | G9: =G8/G7 -> 12.069672 | H9: =H8/H7 -> 11.269171 | I9: =I8/I7 -> 10.682444 | K9: =AVERAGE($D$9:$I$9) -> 11.092249 | L9: =AVERAGE($D$9:$I$9) -> 11.092249 | M9: =AVERAGE($D$9:$I$9) -> 11.092249 | N9: =AVERAGE($D$9:$I$9) -> 11.092249 | O9: =AVERAGE($D$9:$I$9) -> 11.092249 | P9: =AVERAGE($D$9:$I$9) -> 11.092249 | Q9: =AVERAGE($D$9:$I$9) -> 11.092249 | R9: =AVERAGE($D$9:$I$9) -> 11.092249 | ... T9: =AVERAGE($D$9:$I$9) -> 11.092249
B10: No.of days in inventory | C10: 0 | D10: =D3/D9 -> 37.252421 | E10: =E3/E9 -> 34.505175 | F10: =F3/F9 -> 30.10843 | G10: =G3/G9 -> 30.241088 | H10: =H3/H9 -> 32.389249 | I10: =I3/I9 -> 34.16821 | K10: =AVERAGE($D$10:$I$10) -> 33.110762 | L10: =AVERAGE($D$10:$I$10) -> 33.110762 | M10: =AVERAGE($D$10:$I$10) -> 33.110762 | N10: =AVERAGE($D$10:$I$10) -> 33.110762 | O10: =AVERAGE($D$10:$I$10) -> 33.110762 | P10: =AVERAGE($D$10:$I$10) -> 33.110762 | Q10: =AVERAGE($D$10:$I$10) -> 33.110762 | R10: =AVERAGE($D$10:$I$10) -> 33.110762 | ... T10: =AVERAGE($D$10:$I$10) -> 33.110762
B12: Receivables:
B13: Average trade receivables | C13: 0 | D13: =AVERAGE(BS!C27:D27) -> 315.65 | E13: =AVERAGE(BS!D27:E27) -> 552.35 | F13: =AVERAGE(BS!E27:F27) -> 645.25 | G13: =AVERAGE(BS!F27:G27) -> 1142.65 | H13: =AVERAGE(BS!G27:H27) -> 1600.8 | I13: =AVERAGE(BS!H27:I27) -> 1515.65 | K13: =K16*K14/K3 -> 1786.8988 | L13: =L16*L14/L3 -> 2286.3419 | M13: =M16*M14/M3 -> 2874.0304 | N13: =N16*N14/N3 -> 3550.043 | O13: =O16*O14/O3 -> 4302.9346 | P13: =P16*P14/P3 -> 5151.1599 | Q13: =Q16*Q14/Q3 -> 6078.6686 | R13: =R16*R14/R3 -> 7107.7121 | ... T13: =T16*T14/T3 -> 9474.0343
B14: Revenue from operations | C14: 0 | D14: ='P & L'!D8 -> 241430.6 | E14: ='P & L'!E8 -> 309762.7 | F14: ='P & L'!F8 -> 428395.6 | G14: ='P & L'!G8 -> 507888.3 | H14: ='P & L'!H8 -> 593580.5 | I14: ='P & L'!I8 -> 688207.4 | K14: ='P & L'!K8 -> 914969.92 | L14: ='P & L'!L8 -> 1167507.9 | M14: ='P & L'!M8 -> 1467607.8 | N14: ='P & L'!N8 -> 1812809.9 | O14: ='P & L'!O8 -> 2203289.8 | P14: ='P & L'!P8 -> 2637618 | Q14: ='P & L'!Q8 -> 3112542.8 | R14: ='P & L'!R8 -> 3639457.9 | ... T14: ='P & L'!T8 -> 4851117.8
B15: Receivables turn-over ratio | C15: 0 | D15: =D14/D13 -> 764.86805 | E15: =E14/E13 -> 560.80873 | F15: =F14/F13 -> 663.92189 | G15: =G14/G13 -> 444.48283 | H15: =H14/H13 -> 370.80241 | I15: =I14/I13 -> 454.0675 | K15: =AVERAGE($D$15:$I$15) -> 543.15857 | L15: =AVERAGE($D$15:$I$15) -> 543.15857 | M15: =AVERAGE($D$15:$I$15) -> 543.15857 | N15: =AVERAGE($D$15:$I$15) -> 543.15857 | O15: =AVERAGE($D$15:$I$15) -> 543.15857 | P15: =AVERAGE($D$15:$I$15) -> 543.15857 | Q15: =AVERAGE($D$15:$I$15) -> 543.15857 | R15: =AVERAGE($D$15:$I$15) -> 543.15857 | ... T15: =AVERAGE($D$15:$I$15) -> 543.15857
B16: No.of days for receivables | C16: 0 | D16: =D3/D15 -> 0.47720649 | E16: =E3/E15 -> 0.65084579 | F16: =F3/F15 -> 0.55126967 | G16: =G3/G15 -> 0.82117909 | H16: =H3/H15 -> 0.98435174 | I16: =I3/I15 -> 0.80384525 | K16: =AVERAGE($D$16:$I$16) -> 0.71478301 | L16: =AVERAGE($D$16:$I$16) -> 0.71478301 | M16: =AVERAGE($D$16:$I$16) -> 0.71478301 | N16: =AVERAGE($D$16:$I$16) -> 0.71478301 | O16: =AVERAGE($D$16:$I$16) -> 0.71478301 | P16: =AVERAGE($D$16:$I$16) -> 0.71478301 | Q16: =AVERAGE($D$16:$I$16) -> 0.71478301 | R16: =AVERAGE($D$16:$I$16) -> 0.71478301 | ... T16: =AVERAGE($D$16:$I$16) -> 0.71478301
B18: Payables:
B19: Micro and small enterprises | C19: =BS!C56 -> 174.7 | D19: =BS!D56 -> 219.5 | E19: =BS!E56 -> 323.9 | F19: =BS!F56 -> 762.9 | G19: =BS!G56 -> 2306 | H19: =BS!H56 -> 2895.3 | I19: =BS!I56 -> 3934.7 | K19: =K21*K22 -> 4344.1019 | L19: =L21*L22 -> 5558.2904 | M19: =M21*M22 -> 6987.0107 | N19: =N21*N22 -> 8630.4545 | O19: =O21*O22 -> 10460.798 | P19: =P21*P22 -> 12522.905 | Q19: =Q21*Q22 -> 14777.757 | R19: =R21*R22 -> 17279.449 | ... T19: =T21*T22 -> 23032.178
B20: Other than micro and small enterprises | C20: =BS!C57 -> 4159.8 | D20: =BS!D57 -> 5561.8 | E20: =BS!E57 -> 5568.1 | F20: =BS!F57 -> 6775 | G20: =BS!G57 -> 7542.1 | H20: =BS!H57 -> 7812.8 | I20: =BS!I57 -> 9447.6 | K20: =K21-K19 -> 11975.581 | L20: =L21-L19 -> 15322.789 | M20: =M21-M19 -> 19261.407 | N20: =N21-N19 -> 23791.963 | O20: =O21-O19 -> 28837.752 | P20: =P21-P19 -> 34522.456 | Q20: =Q21-Q19 -> 40738.508 | R20: =R21-R19 -> 47635.034 | ... T20: =T21-T19 -> 63493.842
B21: Total Payables: | C21: =SUM(C19:C20) -> 4334.5 | D21: =SUM(D19:D20) -> 5781.3 | E21: =SUM(E19:E20) -> 5892 | F21: =SUM(F19:F20) -> 7537.9 | G21: =SUM(G19:G20) -> 9848.1 | H21: =SUM(H19:H20) -> 10708.1 | I21: =SUM(I19:I20) -> 13382.3 | K21: =K24 -> 16319.683 | L21: =L24 -> 20881.08 | M21: =M24 -> 26248.418 | N21: =N24 -> 32422.417 | O21: =O24 -> 39298.549 | P21: =P24 -> 47045.361 | Q21: =Q24 -> 55516.265 | R21: =R24 -> 64914.483 | ... T21: =T24 -> 86526.02
B22: Micro and small as a percentage of total | C22: =C19/C21 -> 0.040304533 | D22: =D19/D21 -> 0.037967239 | E22: =E19/E21 -> 0.054972845 | F22: =F19/F21 -> 0.10120856 | G22: =G19/G21 -> 0.23415684 | H22: =H19/H21 -> 0.2703841 | I22: =I19/I21 -> 0.2940227 | K22: =AVERAGE($G$22:$I$22) -> 0.26618788 | L22: =AVERAGE($G$22:$I$22) -> 0.26618788 | M22: =AVERAGE($G$22:$I$22) -> 0.26618788 | N22: =AVERAGE($G$22:$I$22) -> 0.26618788 | O22: =AVERAGE($G$22:$I$22) -> 0.26618788 | P22: =AVERAGE($G$22:$I$22) -> 0.26618788 | Q22: =AVERAGE($G$22:$I$22) -> 0.26618788 | R22: =AVERAGE($G$22:$I$22) -> 0.26618788 | ... T22: =AVERAGE($G$22:$I$22) -> 0.26618788
B24: Average trade payables | C24: 0 | D24: =AVERAGE(C21:D21) -> 5057.9 | E24: =AVERAGE(D21:E21) -> 5836.65 | F24: =AVERAGE(E21:F21) -> 6714.95 | G24: =AVERAGE(F21:G21) -> 8693 | H24: =AVERAGE(G21:H21) -> 10278.1 | I24: =AVERAGE(H21:I21) -> 12045.2 | K24: =K25/K26 -> 16319.683 | L24: =L25/L26 -> 20881.08 | M24: =M25/M26 -> 26248.418 | N24: =N25/N26 -> 32422.417 | O24: =O25/O26 -> 39298.549 | P24: =P25/P26 -> 47045.361 | Q24: =Q25/Q26 -> 55516.265 | R24: =R25/R26 -> 64914.483 | ... T24: =T25/T26 -> 86526.02
B25: Total COGS | C25: 0 | D25: =-'P & L'!D11 -> 205546.8 | E25: =-'P & L'!E11 -> 263973.9 | F25: =-'P & L'!F11 -> 363839.5 | G25: =-'P & L'!G11 -> 432745.4 | H25: =-'P & L'!H11 -> 505517 | I25: =-'P & L'!I11 -> 584597.3 | J25: =-'P & L'!J11 -> 0 | K25: =-'P & L'!K11 -> 777724.43 | ... T25: =-'P & L'!T11 -> 4123450.1
B26: Payables turn-over ratio | C26: 0 | D26: =D25/D24 -> 40.638763 | E26: =E25/E24 -> 45.226954 | F26: =F25/F24 -> 54.183501 | G26: =G25/G24 -> 49.780904 | H26: =H25/H24 -> 49.183896 | I26: =I25/I24 -> 48.533632 | K26: =K3/K27 -> 47.655609 | L26: =L3/L27 -> 47.525402 | M26: =M3/M27 -> 47.525402 | N26: =N3/N27 -> 47.525402 | O26: =O3/O27 -> 47.655609 | P26: =P3/P27 -> 47.655609 | Q26: =Q3/Q27 -> 47.655609 | R26: =R3/R27 -> 47.655609 | ... T26: =T3/T27 -> 47.655609
B27: No.of days for payables | C27: 0 | D27: =D3/D26 -> 8.9815726 | E27: =E3/E26 -> 8.0704087 | F27: =F3/F26 -> 6.7548238 | G27: =G3/G26 -> 7.3321288 | H27: =H3/H26 -> 7.4211283 | I27: =I3/I26 -> 7.5205582 | K27: =AVERAGE($D$27:$I$27) -> 7.6801034 | L27: =AVERAGE($D$27:$I$27) -> 7.6801034 | M27: =AVERAGE($D$27:$I$27) -> 7.6801034 | N27: =AVERAGE($D$27:$I$27) -> 7.6801034 | O27: =AVERAGE($D$27:$I$27) -> 7.6801034 | P27: =AVERAGE($D$27:$I$27) -> 7.6801034 | Q27: =AVERAGE($D$27:$I$27) -> 7.6801034 | R27: =AVERAGE($D$27:$I$27) -> 7.6801034 | ... T27: =AVERAGE($D$27:$I$27) -> 7.6801034
B29: Current Liabilitiess:
B30: Current Tax Liabilities:
B31: Current Tax Liabilities (Net) | C31: =BS!C61 -> 151.8 | D31: =BS!D61 -> 237.7 | E31: =BS!E61 -> 364.4 | F31: =BS!F61 -> 853.9 | G31: =BS!G61 -> 2547.8 | H31: =BS!H61 -> 2411.2 | I31: =BS!I61 -> 2715.3 | K31: =K32*K33 -> 4037.1598 | L31: =L32*L33 -> 5324.4069 | M31: =M32*M33 -> 6837.5954 | N31: =N32*N33 -> 8585.5569 | O31: =O32*O33 -> 10571.168 | P31: =P32*P33 -> 12786.69 | Q31: =Q32*Q33 -> 15214.678 | R31: =R32*R33 -> 17915.854 | ... T31: =T32*T33 -> 24147.517
B32: Total Tax | C32: =-'P & L'!C30 -> 4437.9 | D32: =-'P & L'!D30 -> 3840.2 | E32: =-'P & L'!E30 -> 5717.2 | F32: =-'P & L'!F30 -> 6817.5 | G32: =-'P & L'!G30 -> 9257.2 | H32: =-'P & L'!H30 -> 9652.2 | I32: =-'P & L'!I30 -> 11110.2 | J32: =-'P & L'!J30 -> 0 | ... T32: =-'P & L'!T30 -> 107960.44
B33: Current Tax Liability as a % of total tax | C33: =C31/C32 -> 0.034205367 | D33: =D31/D32 -> 0.061897818 | E33: =E31/E32 -> 0.063737494 | F33: =F31/F32 -> 0.12525119 | G33: =G31/G32 -> 0.27522361 | H33: =H31/H32 -> 0.24980833 | I33: =I31/I32 -> 0.24439704 | K33: =AVERAGE($F$33:$I$33) -> 0.22367004 | L33: =AVERAGE($F$33:$I$33) -> 0.22367004 | M33: =AVERAGE($F$33:$I$33) -> 0.22367004 | N33: =AVERAGE($F$33:$I$33) -> 0.22367004 | O33: =AVERAGE($F$33:$I$33) -> 0.22367004 | P33: =AVERAGE($F$33:$I$33) -> 0.22367004 | Q33: =AVERAGE($F$33:$I$33) -> 0.22367004 | R33: =AVERAGE($F$33:$I$33) -> 0.22367004 | ... T33: =AVERAGE($F$33:$I$33) -> 0.22367004
B35: Other current financial liabilities:
B36: Other current financial liabilities | C36: =BS!C58 -> 1779.4 | D36: =BS!D58 -> 2697.8 | E36: =BS!E58 -> 2829.2 | F36: =BS!F58 -> 2894.6 | G36: =BS!G58 -> 3898.5 | H36: =BS!H58 -> 4486.4 | I36: =BS!I58 -> 6371.9 | K36: =K37*Schedules!K8 -> 2475.1087 | L36: =L37*Schedules!L8 -> 5016.993 | M36: =M37*Schedules!M8 -> 5673.0613 | N36: =N37*Schedules!N8 -> 6139.0628 | O36: =O37*Schedules!O8 -> 6613.8169 | P36: =P37*Schedules!P8 -> 7097.4523 | Q36: =Q37*Schedules!Q8 -> 7590.099 | R36: =R37*Schedules!R8 -> 8091.8889 | ... T36: =T37*Schedules!T8 -> 9123.4344
B37: Other current financial liabilities as a % of capex | C37: =C36/Schedules!C8 -> 0.11955361 | D37: =D36/Schedules!D8 -> 0.23687977 | E37: =E36/Schedules!E8 -> 0.13152585 | F37: =F36/Schedules!F8 -> 0.11949405 | G37: =G36/Schedules!G8 -> 0.15117966 | H37: =H36/Schedules!H8 -> 0.13867715 | I37: =I36/Schedules!I8 -> 0.15882856 | K37: =AVERAGE($C$37:$I$37) -> 0.15087695 | L37: =AVERAGE($C$37:$I$37) -> 0.15087695 | M37: =AVERAGE($C$37:$I$37) -> 0.15087695 | N37: =AVERAGE($C$37:$I$37) -> 0.15087695 | O37: =AVERAGE($C$37:$I$37) -> 0.15087695 | P37: =AVERAGE($C$37:$I$37) -> 0.15087695 | Q37: =AVERAGE($C$37:$I$37) -> 0.15087695 | R37: =AVERAGE($C$37:$I$37) -> 0.15087695 | ... T37: =AVERAGE($C$37:$I$37) -> 0.15087695
B39: Provisions:
B40: Closing balance of provision | C40: =BS!C60 -> 207 | D40: =BS!D60 -> 407.3 | E40: =BS!E60 -> 583.7 | F40: =BS!F60 -> 508.7 | G40: =BS!G60 -> 610.4 | H40: =BS!H60 -> 491.4 | I40: =BS!I60 -> 1114.2 | K40: =K41*K42 -> 1198.6249 | L40: =L41*L42 -> 1529.4536 | M40: =M41*M42 -> 1922.5891 | N40: =N41*N42 -> 2374.8093 | O40: =O41*O42 -> 2886.3441 | P40: =P41*P42 -> 3455.3209 | Q40: =Q41*Q42 -> 4077.4798 | R40: =R41*R42 -> 4767.7468 | ... T40: =T41*T42 -> 6355.0402
B41: Employee benefit during the year | C41: =-'P & L'!C14 -> 4561 | D41: =-'P & L'!D14 -> 5365.7 | E41: =-'P & L'!E14 -> 6162.1 | F41: =-'P & L'!F14 -> 7469.7 | G41: =-'P & L'!G14 -> 9061.2 | H41: =-'P & L'!H14 -> 11659 | I41: =-'P & L'!I14 -> 15414.8 | K41: =-'P & L'!K14 -> 18008.5 | L41: =-'P & L'!L14 -> 22978.97 | M41: =-'P & L'!M14 -> 28885.556 | N41: =-'P & L'!N14 -> 35679.847 | O41: =-'P & L'!O14 -> 43365.299 | P41: =-'P & L'!P14 -> 51913.777 | Q41: =-'P & L'!Q14 -> 61261.279 | R41: =-'P & L'!R14 -> 71632.057 | ... T41: =-'P & L'!T14 -> 95480.03
B42: Provision as a % of employee benefit | C42: =C40/C41 -> 0.045384784 | D42: =D40/D41 -> 0.075908083 | E42: =E40/E41 -> 0.094724201 | F42: =F40/F41 -> 0.068101798 | G42: =G40/G41 -> 0.067364146 | H42: =H40/H41 -> 0.042147697 | I42: =I40/I41 -> 0.072281184 | K42: =AVERAGE($C$42:$I$42) -> 0.066558842 | L42: =AVERAGE($C$42:$I$42) -> 0.066558842 | M42: =AVERAGE($C$42:$I$42) -> 0.066558842 | N42: =AVERAGE($C$42:$I$42) -> 0.066558842 | O42: =AVERAGE($C$42:$I$42) -> 0.066558842 | P42: =AVERAGE($C$42:$I$42) -> 0.066558842 | Q42: =AVERAGE($C$42:$I$42) -> 0.066558842 | R42: =AVERAGE($C$42:$I$42) -> 0.066558842 | ... T42: =AVERAGE($C$42:$I$42) -> 0.066558842
B44: Other current liabilities:
B45: Statutary dues | C45: 181.6 | D45: 371.2 | E45: 469.8 | F45: 954.6 | G45: 679 | H45: 959.6 | I45: 786.2 | K45: =K50*'P & L'!K8 -> 1321.2922 | L45: =L50*'P & L'!L8 -> 1685.9779 | M45: =M50*'P & L'!M8 -> 2119.3469 | N45: =N50*'P & L'!N8 -> 2617.8472 | O45: =O50*'P & L'!O8 -> 3181.7324 | P45: =P50*'P & L'!P8 -> 3808.9383 | Q45: =Q50*'P & L'!Q8 -> 4494.769 | R45: =R50*'P & L'!R8 -> 5255.6779 | ... T45: =T50*'P & L'!T8 -> 7005.4149
B46: Others payable | C46: 25.4 | D46: 36.1 | E46: 92.3 | F46: 183.4 | G46: 205.9 | H46: 233.2 | I46: 280 | K46: =K51*'P & L'!K8 -> 285.32198 | L46: =L51*'P & L'!L8 -> 364.07281 | M46: =M51*'P & L'!M8 -> 457.65522 | N46: =N51*'P & L'!N8 -> 565.3022 | O46: =O51*'P & L'!O8 -> 687.06849 | P46: =P51*'P & L'!P8 -> 822.50835 | Q46: =Q51*'P & L'!Q8 -> 970.60774 | R46: =R51*'P & L'!R8 -> 1134.9196 | ... T46: =T51*'P & L'!T8 -> 1512.7607
B47: Corporate Social Responsibility (CSR) | C47: 0 | D47: 0 | E47: 21.6 | F47: 73.8 | G47: 72.5 | H47: 193.4 | I47: 348.2 | K47: =K52*'P & L'!K32 -> 572.02077 | L47: =L52*'P & L'!L32 -> 754.40941 | M47: =M52*'P & L'!M32 -> 968.81144 | N47: =N52*'P & L'!N32 -> 1216.4782 | O47: =O52*'P & L'!O32 -> 1497.8174 | P47: =P52*'P & L'!P32 -> 1811.7322 | Q47: =Q52*'P & L'!Q32 -> 2155.7512 | R47: =R52*'P & L'!R32 -> 2538.4778 | ... T47: =T52*'P & L'!T32 -> 3421.4354
B48: Oter current liabilities total | C48: =SUM(C45:C47) -> 207 | D48: =SUM(D45:D47) -> 407.3 | E48: =SUM(E45:E47) -> 583.7 | F48: =SUM(F45:F47) -> 1211.8 | G48: =SUM(G45:G47) -> 957.4 | H48: =SUM(H45:H47) -> 1386.2 | I48: =SUM(I45:I47) -> 1414.4 | K48: =SUM(K45:K47) -> 2178.6349 | L48: =SUM(L45:L47) -> 2804.4601 | M48: =SUM(M45:M47) -> 3545.8135 | N48: =SUM(N45:N47) -> 4399.6276 | O48: =SUM(O45:O47) -> 5366.6183 | P48: =SUM(P45:P47) -> 6443.1789 | Q48: =SUM(Q45:Q47) -> 7621.1279 | R48: =SUM(R45:R47) -> 8929.0753 | ... T48: =SUM(T45:T47) -> 11939.611
B50: Statutary dues as a % of revenue | C50: =C45/'P & L'!C8 -> 0.00073019115 | D50: =D45/'P & L'!D8 -> 0.0015375019 | E50: =E45/'P & L'!E8 -> 0.0015166448 | F50: =F45/'P & L'!F8 -> 0.0022283142 | G50: =G45/'P & L'!G8 -> 0.0013369081 | H50: =H45/'P & L'!H8 -> 0.0016166299 | I50: =I45/'P & L'!I8 -> 0.0011423882 | K50: =AVERAGE($C$50:$I$50) -> 0.0014440826 | L50: =AVERAGE($C$50:$I$50) -> 0.0014440826 | M50: =AVERAGE($C$50:$I$50) -> 0.0014440826 | N50: =AVERAGE($C$50:$I$50) -> 0.0014440826 | O50: =AVERAGE($C$50:$I$50) -> 0.0014440826 | P50: =AVERAGE($C$50:$I$50) -> 0.0014440826 | Q50: =AVERAGE($C$50:$I$50) -> 0.0014440826 | R50: =AVERAGE($C$50:$I$50) -> 0.0014440826 | ... T50: =AVERAGE($C$50:$I$50) -> 0.0014440826
B51: Others payable as a % of revenue | C51: =C46/'P & L'!C8 -> 0.00010213026 | D51: =D46/'P & L'!D8 -> 0.00014952537 | E51: =E46/'P & L'!E8 -> 0.00029797003 | F51: =F46/'P & L'!F8 -> 0.00042810897 | G51: =G46/'P & L'!G8 -> 0.0004054041 | H51: =H46/'P & L'!H8 -> 0.00039287005 | I51: =I46/'P & L'!I8 -> 0.0004068541 | K51: =AVERAGE($C$51:$I$51) -> 0.00031183755 | L51: =AVERAGE($C$51:$I$51) -> 0.00031183755 | M51: =AVERAGE($C$51:$I$51) -> 0.00031183755 | N51: =AVERAGE($C$51:$I$51) -> 0.00031183755 | O51: =AVERAGE($C$51:$I$51) -> 0.00031183755 | P51: =AVERAGE($C$51:$I$51) -> 0.00031183755 | Q51: =AVERAGE($C$51:$I$51) -> 0.00031183755 | R51: =AVERAGE($C$51:$I$51) -> 0.00031183755 | ... T51: =AVERAGE($C$51:$I$51) -> 0.00031183755
B52: CSR as a % of Net profit | C52: =C47/'P & L'!C32 -> 0 | D52: =D47/'P & L'!D32 -> 0 | E52: =E47/'P & L'!E32 -> 0.0014473332 | F52: =F47/'P & L'!F32 -> 0.0031030046 | G52: =G47/'P & L'!G32 -> 0.0028592725 | H52: =H47/'P & L'!H32 -> 0.0071432529 | I52: =I47/'P & L'!I32 -> 0.011721538 | K52: =I52 -> 0.011721538 | L52: =K52 -> 0.011721538 | M52: =L52 -> 0.011721538 | N52: =M52 -> 0.011721538 | O52: =N52 -> 0.011721538 | P52: =O52 -> 0.011721538 | Q52: =P52 -> 0.011721538 | R52: =Q52 -> 0.011721538 | S52: =R52 -> 0.011721538 | T52: =S52 -> 0.011721538
B54: Current Assets:
B55: Other Current Assets:
B56: Other current assets | C56: =BS!C31 -> 1491 | D56: =BS!D31 -> 1528.3 | E56: =BS!E31 -> 2013.3 | F56: =BS!F31 -> 2154.6 | G56: =BS!G31 -> 2350.2 | H56: =BS!H31 -> 3062.3 | I56: =BS!I31 -> 3954.2 | K56: =K57*'P & L'!K8 -> 5148.1884 | L56: =L57*'P & L'!L8 -> 6569.1237 | M56: =M57*'P & L'!M8 -> 8257.6718 | N56: =N57*'P & L'!N8 -> 10199.993 | O56: =O57*'P & L'!O8 -> 12397.075 | P56: =P57*'P & L'!P8 -> 14840.875 | Q56: =Q57*'P & L'!Q8 -> 17513.097 | R56: =R57*'P & L'!R8 -> 20477.848 | ... T56: =T57*'P & L'!T8 -> 27295.398
B57: Other current assets % | C57: =C56/'P & L'!C8 -> 0.0059951267 | D57: =D56/'P & L'!D8 -> 0.0063301835 | E57: =E56/'P & L'!E8 -> 0.0064994914 | F57: =F56/'P & L'!F8 -> 0.0050294634 | G57: =G56/'P & L'!G8 -> 0.0046273954 | H57: =H56/'P & L'!H8 -> 0.0051590307 | I57: =I56/'P & L'!I8 -> 0.0057456517 | K57: =AVERAGE($C$57:$I$57) -> 0.0056266204 | L57: =AVERAGE($C$57:$I$57) -> 0.0056266204 | M57: =AVERAGE($C$57:$I$57) -> 0.0056266204 | N57: =AVERAGE($C$57:$I$57) -> 0.0056266204 | O57: =AVERAGE($C$57:$I$57) -> 0.0056266204 | P57: =AVERAGE($C$57:$I$57) -> 0.0056266204 | Q57: =AVERAGE($C$57:$I$57) -> 0.0056266204 | R57: =AVERAGE($C$57:$I$57) -> 0.0056266204 | ... T57: =AVERAGE($C$57:$I$57) -> 0.0056266204

Sheet Schedules
B4: (In Millions) | C4: 43921 | D4: =EOMONTH(C4,12) -> 44286 | E4: =EOMONTH(D4,12) -> 44651 | F4: =EOMONTH(E4,12) -> 45016 | G4: =EOMONTH(F4,12) -> 45382 | H4: =EOMONTH(G4,12) -> 45747 | I4: =EOMONTH(H4,12) -> 46112 | K4: =EOMONTH(I4,12) -> 46477 | L4: =EOMONTH(K4,12) -> 46843 | M4: =EOMONTH(L4,12) -> 47208 | N4: =EOMONTH(M4,12) -> 47573 | O4: =EOMONTH(N4,12) -> 47938 | P4: =EOMONTH(O4,12) -> 48304 | Q4: =EOMONTH(P4,12) -> 48669 | R4: =EOMONTH(Q4,12) -> 49034 | S4: =EOMONTH(R4,12) -> 49399 | T4: =EOMONTH(S4,12) -> 49765
B5: Depreciation Schedule:
B6: PPE:
B7: Opening balance | C7: =48575.5-5835.2 -> 42740.3 | D7: =C11 -> 51073.6 | E7: =D11 -> 59385 | F7: =E11 -> 77704.6 | G7: =F11 -> 97256.1 | H7: =G11 -> 117591.9 | I7: =H11 -> 143498.3 | K7: =I11 -> 175869.5 | L7: =K11 -> 183070.72 | M7: =L11 -> 206338.1 | N7: =M11 -> 232681.76 | O7: =N11 -> 260719.64 | P7: =O11 -> 290423.6 | Q7: =P11 -> 321767.72 | R7: =Q11 -> 354728.22 | S7: =R11 -> 389283.37 | T7: =S11 -> 425413.39
B8: Additions | C8: 14883.7 | D8: 11388.9 | E8: 21510.6 | F8: 24223.8 | G8: 25787.2 | H8: 32351.4 | I8: 40118.1 | K8: =-K28 -> 16404.817 | L8: =-L28 -> 33252.217 | M8: =-M28 -> 37600.583 | N8: =-N28 -> 40689.203 | O8: =-O28 -> 43835.834 | P8: =-P28 -> 47041.33 | Q8: =-Q28 -> 50306.551 | R8: =-R28 -> 53632.373 | ... T8: =-T28 -> 60469.372
B9: Depreciation | C9: -2618.7 | D9: -2892.3 | E9: -3399.8 | F9: -4595.9 | G9: -5336.5 | H9: -6327.3 | I9: -7659.7 | K9: =K15*(K7+K8/2) -> -9203.5954 | L9: =L15*(L7+L8/2) -> -9984.8415 | M9: =M15*(M7+M8/2) -> -11256.919 | N9: =N15*(N7+N8/2) -> -12651.318 | O9: =O15*(O7+O8/2) -> -14131.878 | P9: =P15*(P7+P8/2) -> -15697.213 | Q9: =Q15*(Q7+Q8/2) -> -17346.05 | R9: =R15*(R7+R8/2) -> -19077.22 | ... T9: =T15*(T7+T8/2) -> -22782.404
B10: Others | C10: =C11-SUM(C7:C9) -> -3931.7 | D10: =D11-SUM(D7:D9) -> -185.2 | E10: =E11-SUM(E7:E9) -> 208.8 | F10: =F11-SUM(F7:F9) -> -76.4 | G10: =G11-SUM(G7:G9) -> -114.9 | H10: =H11-SUM(H7:H9) -> -117.7 | I10: =I11-SUM(I7:I9) -> -87.2 | K10: 0 | L10: 0 | M10: 0 | N10: 0 | O10: 0 | P10: 0 | Q10: 0 | R10: 0 | S10: 0 | T10: 0
B11: Closing balance | C11: 51073.6 | D11: 59385 | E11: 77704.6 | F11: 97256.1 | G11: 117591.9 | H11: 143498.3 | I11: 175869.5 | K11: =SUM(K7:K10) -> 183070.72 | L11: =SUM(L7:L10) -> 206338.1 | M11: =SUM(M7:M10) -> 232681.76 | N11: =SUM(N7:N10) -> 260719.64 | O11: =SUM(O7:O10) -> 290423.6 | P11: =SUM(P7:P10) -> 321767.72 | Q11: =SUM(Q7:Q10) -> 354728.22 | R11: =SUM(R7:R10) -> 389283.37 | ... T11: =SUM(T7:T10) -> 463100.36
B13: Additional stores per year | C13: ='Revenue driver'!C8 -> 0 | D13: ='Revenue driver'!D8 -> 20 | E13: ='Revenue driver'!E8 -> 50 | F13: ='Revenue driver'!F8 -> 40 | G13: ='Revenue driver'!G8 -> 41 | H13: ='Revenue driver'!H8 -> 50 | I13: ='Revenue driver'!I8 -> 85 | K13: ='Revenue driver'!K8 -> 50 | L13: ='Revenue driver'!L8 -> 50 | M13: ='Revenue driver'!M8 -> 50 | N13: ='Revenue driver'!N8 -> 50 | O13: ='Revenue driver'!O8 -> 50 | P13: ='Revenue driver'!P8 -> 50 | Q13: ='Revenue driver'!Q8 -> 50 | R13: ='Revenue driver'!R8 -> 50 | ... T13: ='Revenue driver'!T8 -> 50
B14: Cost per new store | C14: 0 | D14: =D8/D13 -> 569.445 | E14: =E8/E13 -> 430.212 | F14: =F8/F13 -> 605.595 | G14: =G8/G13 -> 628.9561 | H14: =H8/H13 -> 647.028 | I14: =I8/I13 -> 471.97765 | K14: 650 | L14: =K14+L13 -> 700 | M14: =L14+M13 -> 750 | N14: =M14+N13 -> 800 | O14: =N14+O13 -> 850 | P14: =O14+P13 -> 900 | Q14: =P14+Q13 -> 950 | R14: =Q14+R13 -> 1000 | S14: =R14+S13 -> 1050 | T14: =S14+T13 -> 1100
B15: Depreciation rate | C15: =C9/(C8/2+C7) -> -0.052183894 | D15: =D9/(D8/2+D7) -> -0.050949434 | E15: =E9/(E8/2+E7) -> -0.048471421 | F15: =F9/(F8/2+F7) -> -0.051169885 | G15: =G9/(G8/2+G7) -> -0.048447703 | H15: =H9/(H8/2+H7) -> -0.047300692 | I15: =I9/(I8/2+I7) -> -0.046831891 | K15: -0.05 | L15: -0.05 | M15: -0.05 | N15: -0.05 | O15: -0.05 | P15: -0.05 | Q15: -0.05 | R15: -0.05 | S15: -0.05 | T15: -0.05
B17: Right of use:
B18: Opening balance | D18: 7173.3 | E18: 9602.4 | F18: 13886.5 | G18: 15048.8 | H18: 15391 | I18: 17417.3 | K18: =I22 -> 23814.1 | L18: =K22 -> 25316.728 | M18: =L22 -> 26646.555 | N18: =M22 -> 27823.451 | O18: =N22 -> 28865.004 | P18: =O22 -> 29786.779 | Q18: =P22 -> 30602.549 | R18: =Q22 -> 31325.448 | S18: =R22 -> 31966.157 | T18: =S22 -> 32534.126
B19: Additions | D19: 3313.7 | E19: 6185.4 | F19: 3262.7 | G19: 2945.9 | H19: 4663.5 | I19: 9151.4 | K19: 4500 | L19: 4500 | M19: 4500 | N19: 4500 | O19: 4500 | P19: 4500 | Q19: 4501 | R19: 4502 | S19: 4503 | T19: 4504
B20: Ammortizarion | D20: -1097 | E20: -1427 | F20: -1777.9 | G20: -1954.1 | H20: 2352 | I20: 2663 | K20: =(K18+(K19/2))*K23 -> -2997.3715 | L20: =(L18+(L19/2))*L23 -> -3170.1738 | M20: =(M18+(M19/2))*M23 -> -3323.1038 | N20: =(N18+(N19/2))*N23 -> -3458.4469 | O20: =(O18+(O19/2))*O23 -> -3578.2255 | P20: =(P18+(P19/2))*P23 -> -3684.2295 | Q20: =(Q18+(Q19/2))*Q23 -> -3778.1006 | R20: =(R18+(R19/2))*R23 -> -3861.2916 | ... T20: =(T18+(T19/2))*T23 -> -4000.4045
B21: Others | D21: 212.4 | E21: -474.29 | F21: -322.5 | G21: -649.6 | H21: -4989.2 | I21: -5417.6 | K21: 0 | L21: 0 | M21: 0
B22: Closing balance | C22: =BS!C12 -> 7173.3 | D22: =BS!D12 -> 9602.4 | E22: =BS!E12 -> 13886.5 | F22: =BS!F12 -> 15048.8 | G22: =BS!G12 -> 15391 | H22: =BS!H12 -> 17417.3 | I22: =BS!I12 -> 23814.1 | K22: =SUM(K18:K21) -> 25316.728 | L22: =SUM(L18:L21) -> 26646.555 | M22: =SUM(M18:M21) -> 27823.451 | N22: =SUM(N18:N21) -> 28865.004 | O22: =SUM(O18:O21) -> 29786.779 | P22: =SUM(P18:P21) -> 30602.549 | Q22: =SUM(Q18:Q21) -> 31325.448 | R22: =SUM(R18:R21) -> 31966.157 | ... T22: =SUM(T18:T21) -> 33037.722
B23: Amortization rate | D23: =D20/((D19/2)+D18) -> -0.12423345 | E23: =E20/((E19/2)+E18) -> -0.11240557 | F23: =F20/((F19/2)+F18) -> -0.11457128 | G23: =G20/((G19/2)+G18) -> -0.1182744 | H23: =H20/((H19/2)+H18) -> 0.13271078 | I23: =I20/((I19/2)+I18) -> 0.12108398 | K23: -0.115 | L23: -0.115 | M23: -0.115 | N23: -0.115 | O23: -0.115 | P23: -0.115 | Q23: -0.115 | R23: -0.115 | S23: -0.115 | T23: -0.115
B25: Capital work in progress:
B26: Opening Balance | C26: 3768.4 | D26: 3644 | E26: 10195.9 | F26: 11293.4 | G26: 8291.6 | H26: 9352.2 | I26: 10995.5 | K26: =I29 -> 12999.6 | L26: =K29 -> 29094.783 | M26: =L29 -> 30842.567 | N26: =M29 -> 30741.984 | O26: =N29 -> 30052.781 | P26: =O29 -> 28716.946 | Q26: =P29 -> 26675.617 | R26: =Q29 -> 23869.065 | S26: =R29 -> 20236.692 | T26: =S29 -> 15717.011
B27: Additions during the year | C27: 7291.2 | D27: 11006.7 | E27: 12853.8 | F27: 10890.6 | G27: 11434.6 | H27: 12972.4 | I27: 16835.4 | K27: =K13*K14 -> 32500 | L27: =L13*L14 -> 35000 | M27: =M13*M14 -> 37500 | N27: =N13*N14 -> 40000 | O27: =O13*O14 -> 42500 | P27: =P13*P14 -> 45000 | Q27: =Q13*Q14 -> 47500 | R27: =R13*R14 -> 50000 | ... T27: =T13*T14 -> 55000
B28: Transfer / Adjustment during the year | C28: -7415.6 | D28: -4454.8 | E28: -11756.3 | F28: -13892.4 | G28: -10374 | H28: -11331.1 | I28: -14829.3 | K28: =-I27*K30 -> -16404.817 | L28: =-K27*L30 -> -33252.217 | M28: =-L27*M30 -> -37600.583 | N28: =-M27*N30 -> -40689.203 | O28: =-N27*O30 -> -43835.834 | P28: =-O27*P30 -> -47041.33 | Q28: =-P27*Q30 -> -50306.551 | R28: =-Q27*R30 -> -53632.373 | S28: =-R27*S30 -> -57019.681 | T28: =-S27*T30 -> -60469.372
B29: Closing Balance | C29: 3644 | D29: 10195.9 | E29: 11293.4 | F29: 8291.6 | G29: 9352.2 | H29: 10993.5 | I29: 12999.6 | K29: =SUM(K26:K28) -> 29094.783 | L29: =SUM(L26:L28) -> 30842.567 | M29: =SUM(M26:M28) -> 30741.984 | N29: =SUM(N26:N28) -> 30052.781 | O29: =SUM(O26:O28) -> 28716.946 | P29: =SUM(P26:P28) -> 26675.617 | Q29: =SUM(Q26:Q28) -> 23869.065 | R29: =SUM(R26:R28) -> 20236.692 | ... T29: =SUM(T26:T28) -> 10247.639
B30: Transfer of CWIP as percentage of previosu year's additions | C30: 0 | D30: =-D28/C27 -> 0.6109831 | E30: =-E28/D27 -> 1.068104 | F30: =-F28/E27 -> 1.080801 | G30: =-G28/F27 -> 0.9525646 | H30: =-H28/G27 -> 0.99094852 | I30: =-I28/H27 -> 1.1431424 | K30: =INDEX($K$73:$P$75,MATCH(BS!$D$5,$B$73:$B$75,0),MATCH(K$4,$K$4:$P$4,0)) -> 0.97442393 | L30: =INDEX($K$73:$P$75,MATCH(BS!$D$5,$B$73:$B$75,0),MATCH(L$4,$K$4:$P$4,0)) -> 1.0231451 | M30: =INDEX($K$73:$P$75,MATCH(BS!$D$5,$B$73:$B$75,0),MATCH(M$4,$K$4:$P$4,0)) -> 1.0743024 | N30: =INDEX($K$73:$P$75,MATCH(BS!$D$5,$B$73:$B$75,0),MATCH(N$4,$K$4:$P$4,0)) -> 1.0850454 | O30: =INDEX($K$73:$P$75,MATCH(BS!$D$5,$B$73:$B$75,0),MATCH(O$4,$K$4:$P$4,0)) -> 1.0958959 | P30: =INDEX($K$73:$P$75,MATCH(BS!$D$5,$B$73:$B$75,0),MATCH(P$4,$K$4:$P$4,0)) -> 1.1068548 | Q30: =INDEX($K$73:$T$75,MATCH(BS!$D$5,$B$73:$B$75,0),MATCH(Q$4,$K$4:$T$4,0)) -> 1.1179234 | R30: =INDEX($K$73:$T$75,MATCH(BS!$D$5,$B$73:$B$75,0),MATCH(R$4,$K$4:$T$4,0)) -> 1.1291026 | S30: =INDEX($K$73:$T$75,MATCH(BS!$D$5,$B$73:$B$75,0),MATCH(S$4,$K$4:$T$4,0)) -> 1.1403936 | T30: =INDEX($K$73:$T$75,MATCH(BS!$D$5,$B$73:$B$75,0),MATCH(T$4,$K$4:$T$4,0)) -> 1.1517976
B32: Lease Liabilities:
B33: Current lease | C33: =BS!C54 -> 743.5 | D33: =BS!D54 -> 807 | E33: =BS!E54 -> 1397.9 | F33: =BS!F54 -> 1663.2 | G33: =BS!G54 -> 1929.2 | H33: =BS!H54 -> 2638.3 | I33: =BS!I54 -> 3171.8 | K33: =K36*K35 -> 4087.9538 | L33: =L36*L35 -> 4193.7236 | M33: =M36*M35 -> 4272.3429 | N33: =N36*N35 -> 4330.7811 | O33: =O36*O35 -> 4374.2186 | P33: =P36*P35 -> 4406.5059 | Q33: =Q36*Q35 -> 4430.762 | R33: =R36*R35 -> 4449.0483 | ... T33: =T36*T35 -> 4473.4482
B34: Non-current lease | C34: =BS!C46 -> 2211.1 | D34: =BS!D46 -> 3120.1 | E34: =BS!E46 -> 5071.5 | F34: =BS!F46 -> 4766.6 | G34: =BS!G46 -> 3992.4 | H34: =BS!H46 -> 5557.9 | I34: =BS!I46 -> 11425.4 | K34: =K35-K33 -> 11837.446 | L34: =L35-L33 -> 12143.723 | M34: =M35-M33 -> 12371.38 | N34: =N35-N33 -> 12540.599 | O34: =O35-O33 -> 12666.38 | P34: =P35-P33 -> 12759.874 | Q34: =Q35-Q33 -> 12830.112 | R34: =R35-R33 -> 12883.064 | ... T34: =T35-T33 -> 12953.718
B35: Total | C35: =SUM(C33:C34) -> 2954.6 | D35: =SUM(D33:D34) -> 3927.1 | E35: =SUM(E33:E34) -> 6469.4 | F35: =SUM(F33:F34) -> 6429.8 | G35: =SUM(G33:G34) -> 5921.6 | H35: =SUM(H33:H34) -> 8196.2 | I35: =SUM(I33:I34) -> 14597.2 | K35: =K41 -> 15925.4 | L35: =L41 -> 16337.446 | M35: =M41 -> 16643.723 | N35: =N41 -> 16871.38 | O35: =O41 -> 17040.599 | P35: =P41 -> 17166.38 | Q35: =Q41 -> 17260.874 | R35: =R41 -> 17332.112 | ... T35: =T41 -> 17427.167
B36: Current lease as a % of total | C36: =C33/C35 -> 0.25164151 | D36: =D33/D35 -> 0.20549515 | E36: =E33/E35 -> 0.21607877 | F36: =F33/F35 -> 0.25867057 | G36: =G33/G35 -> 0.32579033 | H36: =H33/H35 -> 0.32189307 | I36: =I33/I35 -> 0.21728825 | K36: =AVERAGE($C$36:$I$36) -> 0.25669395 | L36: =AVERAGE($C$36:$I$36) -> 0.25669395 | M36: =AVERAGE($C$36:$I$36) -> 0.25669395 | N36: =AVERAGE($C$36:$I$36) -> 0.25669395 | O36: =AVERAGE($C$36:$I$36) -> 0.25669395 | P36: =AVERAGE($C$36:$I$36) -> 0.25669395 | Q36: =AVERAGE($C$36:$I$36) -> 0.25669395 | R36: =AVERAGE($C$36:$I$36) -> 0.25669395 | ... T36: =AVERAGE($C$36:$I$36) -> 0.25669395
B38: Opening balance | K38: =I41 -> 14597.2 | L38: =K41 -> 15925.4 | M38: =L41 -> 16337.446 | N38: =M41 -> 16643.723 | O38: =N41 -> 16871.38 | P38: =O41 -> 17040.599 | Q38: =P41 -> 17166.38 | R38: =Q41 -> 17260.874 | S38: =R41 -> 17332.112 | T38: =S41 -> 17386.064
B39: Additions | K39: =K19 -> 4500 | L39: =L19 -> 4500 | M39: =M19 -> 4500 | N39: =N19 -> 4500 | O39: =O19 -> 4500 | P39: =P19 -> 4500 | Q39: =Q19 -> 4501 | R39: =R19 -> 4502 | ... T39: =T19 -> 4504
B40: Repayments | K40: =-I33 -> -3171.8 | L40: =-K33 -> -4087.9538 | M40: =-L33 -> -4193.7236 | N40: =-M33 -> -4272.3429 | O40: =-N33 -> -4330.7811 | P40: =-O33 -> -4374.2186 | Q40: =-P33 -> -4406.5059 | R40: =-Q33 -> -4430.762 | S40: =-R33 -> -4449.0483 | T40: =-S33 -> -4462.8974
B41: Closing balance | I41: =I35 -> 14597.2 | K41: =SUM(K38:K40) -> 15925.4 | L41: =SUM(L38:L40) -> 16337.446 | M41: =SUM(M38:M40) -> 16643.723 | N41: =SUM(N38:N40) -> 16871.38 | O41: =SUM(O38:O40) -> 17040.599 | P41: =SUM(P38:P40) -> 17166.38 | Q41: =SUM(Q38:Q40) -> 17260.874 | R41: =SUM(R38:R40) -> 17332.112 | ... T41: =SUM(T38:T40) -> 17427.167
B43: Deferred tax liability on account of:
B44: Depreciation | C44: 555 | D44: 656.5 | E44: 826.7 | F44: 1036.9 | G44: 1297.9 | H44: 1537.4 | I44: 1871.8 | K44: =K58*BS!K10 -> 1977.5917 | L44: =L58*BS!L10 -> 2228.9338 | M44: =M58*BS!M10 -> 2513.5069 | N44: =N58*BS!N10 -> 2816.3816 | O44: =O58*BS!O10 -> 3137.2538 | P44: =P58*BS!P10 -> 3475.8435 | Q44: =Q58*BS!Q10 -> 3831.8939 | R44: =R58*BS!R10 -> 4205.1704 | ... T44: =T58*BS!T10 -> 5002.5664
B45: Employee benefits | C45: 0 | D45: 0 | E45: 0 | F45: 0 | G45: 0 | H45: 0 | I45: 0 | K45: 0 | L45: 0 | M45: 0 | N45: 0 | O45: 0 | P45: 0 | Q45: 0 | R45: 0 | S45: 0 | T45: 0
B46: Right-of-use asset | C46: 0 | D46: 0 | E46: 0 | F46: 0 | G46: 996.6 | H46: 1550.2 | I46: 3023.2 | K46: 0 | L46: 0 | M46: 0 | N46: 0 | O46: 0 | P46: 0 | Q46: 0 | R46: 0 | S46: 0 | T46: 0
B47: Unrealised profit on cosolidation | C47: 0 | D47: 0 | E47: 0 | F47: 0 | G47: 0 | H47: 0 | I47: 0 | K47: 0 | L47: 0 | M47: 0 | N47: 0 | O47: 0 | P47: 0 | Q47: 0 | R47: 0 | S47: 0 | T47: 0
B48: Fair value gain on financial instruments at Fair value through statement of profit and loss | C48: 1.4 | D48: 0 | E48: 0 | F48: 0 | G48: 0 | H48: 0 | I48: 0 | K48: 0 | L48: 0 | M48: 0 | N48: 0 | O48: 0 | P48: 0 | Q48: 0 | R48: 0 | S48: 0 | T48: 0
B49: Others | C49: 0 | D49: 0 | E49: 0 | F49: 8 | G49: 0.9 | H49: 0 | I49: 0 | K49: 0 | L49: 0 | M49: 0 | N49: 0 | O49: 0 | P49: 0 | Q49: 0 | R49: 0 | S49: 0 | T49: 0
B50: Deferred tax assets on account of:
B51: Depreciation | C51: 0 | D51: 0 | E51: 0 | F51: 0 | G51: 0 | H51: 0 | I51: 0 | K51: 0 | L51: 0 | M51: 0 | N51: 0 | O51: 0 | P51: 0 | Q51: 0 | R51: 0 | S51: 0 | T51: 0
B52: Employee benefits | C52: 39.4 | D52: 55.8 | E52: 65.7 | F52: 77 | G52: 84.1 | H52: 120 | I52: 274.8 | K52: =-K59*'P & L'!K14 -> 199.14556 | L52: =-L59*'P & L'!L14 -> 254.1111 | M52: =-M59*'P & L'!M14 -> 319.42861 | N52: =-N59*'P & L'!N14 -> 394.56274 | O52: =-O59*'P & L'!O14 -> 479.55168 | P52: =-P59*'P & L'!P14 -> 574.08435 | Q52: =-Q59*'P & L'!Q14 -> 677.45295 | R52: =-R59*'P & L'!R14 -> 792.13737 | ... T52: =-T59*'P & L'!T14 -> 1055.8583
B53: Right-of-use asset | C53: 34.4 | D53: 81.7 | E53: 112.5 | F53: 148.8 | G53: 1167.2 | H53: 1711.9 | I53: 3233 | K53: =K60*BS!K12 -> 218.70491 | L53: =L60*BS!L12 -> 230.19295 | M53: =M60*BS!M12 -> 240.35986 | N53: =N60*BS!N12 -> 249.35758 | O53: =O60*BS!O12 -> 257.32056 | P53: =P60*BS!P12 -> 264.3678 | Q53: =Q60*BS!Q12 -> 270.61274 | R53: =R60*BS!R12 -> 276.14766 | ... T53: =T60*BS!T12 -> 285.40465
B54: Unrealised profit on cosolidation | C54: 8.7 | D54: 7.1 | E54: 8.2 | F54: 0 | G54: 0 | H54: 0 | I54: 0 | K54: 0 | L54: 0 | M54: 0 | N54: 0 | O54: 0 | P54: 0 | Q54: 1 | R54: 2 | S54: 3 | T54: 4
B55: Others | C55: 0 | D55: 0 | E55: 0 | F55: 34.1 | G55: 103.7 | H55: 104.1 | I55: 168.6 | K55: =I55 -> 168.6 | L55: =K55 -> 168.6 | M55: =L55 -> 168.6 | N55: =M55 -> 168.6 | O55: =N55 -> 168.6 | P55: =O55 -> 168.6 | Q55: =P55 -> 168.6 | R55: =Q55 -> 168.6 | S55: =R55 -> 168.6 | T55: =S55 -> 168.6
B56: Deferred tax liabilities (net) | C56: 473.9 | D56: 511.9 | E56: 640.3 | F56: 785 | G56: 940.4 | H56: 1151.6 | I56: 1218.6 | K56: =K44-K52-K53-K55 -> 1391.1412 | L56: =L44-L52-L53-L55 -> 1576.0297 | M56: =M44-M52-M53-M55 -> 1785.1184 | N56: =N44-N52-N53-N55 -> 2003.8613 | O56: =O44-O52-O53-O55 -> 2231.7815 | P56: =P44-P52-P53-P55 -> 2468.7913 | Q56: =Q44-Q52-Q53-Q55 -> 2715.2282 | R56: =R44-R52-R53-R55 -> 2968.2853 | ... T56: =T44-T52-T53-T55 -> 3492.7035
B58: Depreciation as a % | C58: =C44/BS!C10 -> 0.010866671 | D58: =D44/BS!D10 -> 0.01105498 | E58: =E44/BS!E10 -> 0.01063901 | F58: =F44/BS!F10 -> 0.010661542 | G58: =G44/BS!G10 -> 0.011037325 | H58: =H44/BS!H10 -> 0.010713716 | I58: =I44/BS!I10 -> 0.010643119 | K58: =AVERAGE($C58:$I58) -> 0.010802337 | L58: =AVERAGE($C58:$I58) -> 0.010802337 | M58: =AVERAGE($C58:$I58) -> 0.010802337 | N58: =AVERAGE($C58:$I58) -> 0.010802337 | O58: =AVERAGE($C58:$I58) -> 0.010802337 | P58: =AVERAGE($C58:$I58) -> 0.010802337 | Q58: =AVERAGE($C58:$I58) -> 0.010802337 | R58: =AVERAGE($C58:$I58) -> 0.010802337 | ... T58: =AVERAGE($C58:$I58) -> 0.010802337
B59: Employee benefits as a % | C59: =C52/-'P & L'!C14 -> 0.0086384565 | D59: =D52/-'P & L'!D14 -> 0.010399389 | E59: =E52/-'P & L'!E14 -> 0.01066195 | F59: =F52/-'P & L'!F14 -> 0.010308312 | G59: =G52/-'P & L'!G14 -> 0.0092813314 | H59: =H52/-'P & L'!H14 -> 0.010292478 | I59: =I52/-'P & L'!I14 -> 0.017827023 | K59: =AVERAGE($C59:$I59) -> 0.01105842 | L59: =AVERAGE($C59:$I59) -> 0.01105842 | M59: =AVERAGE($C59:$I59) -> 0.01105842 | N59: =AVERAGE($C59:$I59) -> 0.01105842 | O59: =AVERAGE($C59:$I59) -> 0.01105842 | P59: =AVERAGE($C59:$I59) -> 0.01105842 | Q59: =AVERAGE($C59:$I59) -> 0.01105842 | R59: =AVERAGE($C59:$I59) -> 0.01105842 | ... T59: =AVERAGE($C59:$I59) -> 0.01105842
B60: Right-of-use asset as a % | C60: =(C53-C45)/BS!C12 -> 0.0047955613 | D60: =(D53-D45)/BS!D12 -> 0.0085082896 | E60: =(E53-E45)/BS!E12 -> 0.0081013934 | F60: =(F53-F45)/BS!F12 -> 0.0098878316 | G60: =(G53-G46)/BS!G12 -> 0.0110844 | H60: =(H53-H46)/BS!H12 -> 0.0092838729 | I60: =(I53-I46)/BS!I12 -> 0.0088099067 | K60: =AVERAGE($C60:$I60) -> 0.0086387508 | L60: =AVERAGE($C60:$I60) -> 0.0086387508 | M60: =AVERAGE($C60:$I60) -> 0.0086387508 | N60: =AVERAGE($C60:$I60) -> 0.0086387508 | O60: =AVERAGE($C60:$I60) -> 0.0086387508 | P60: =AVERAGE($C60:$I60) -> 0.0086387508 | Q60: =AVERAGE($C60:$I60) -> 0.0086387508 | R60: =AVERAGE($C60:$I60) -> 0.0086387508 | ... T60: =AVERAGE($C60:$I60) -> 0.0086387508
B62: Finance Costs:
B63: Interest on term loans from banks | C63: 122.2 | D63: 0 | E63: 0 | F63: 0 | G63: 0 | H63: 0 | I63: 0 | K63: 0 | L63: 0 | M63: 0 | N63: 0 | O63: 0 | P63: 0 | Q63: 0 | R63: 0 | S63: 0 | T63: 0
B64: Interest on non convertible debentures | C64: 247.6 | D64: 12.3 | E64: 0 | F64: 0 | G64: 0 | H64: 0 | I64: 0 | K64: 0 | L64: 0 | M64: 0 | N64: 0 | O64: 0 | P64: 0 | Q64: 0 | R64: 0 | S64: 0 | T64: 0
B65: Interest expenses on lease liability | C65: 0 | D65: 0 | E65: 0 | F65: 663.7 | G65: 569.6 | H65: 672.9 | I65: 1207.6 | K65: =K35*K70 -> 1578.3068 | L65: =L35*L70 -> 1619.1432 | M65: =M35*M70 -> 1649.4971 | N65: =N35*N70 -> 1672.0593 | O65: =O35*O70 -> 1688.83 | P65: =P35*P70 -> 1701.2957 | Q65: =Q35*Q70 -> 1710.6606 | R65: =R35*R70 -> 1717.7208 | ... T65: =T35*T70 -> 1727.1413
B66: Interest Others | C66: 616.1 | D66: 414 | E66: 536.1 | F66: 7.2 | G66: 9.8 | H66: 18.4 | I66: 210.1 | K66: =AVERAGE($D$66:$I$66) -> 199.26667 | L66: =AVERAGE($D$66:$I$66) -> 199.26667 | M66: =AVERAGE($D$66:$I$66) -> 199.26667 | N66: =AVERAGE($D$66:$I$66) -> 199.26667 | O66: =AVERAGE($D$66:$I$66) -> 199.26667 | P66: =AVERAGE($D$66:$I$66) -> 199.26667 | Q66: =AVERAGE($D$66:$I$66) -> 199.26667 | R66: =AVERAGE($D$66:$I$66) -> 199.26667 | ... T66: =AVERAGE($D$66:$I$66) -> 199.26667
B67: Finance charges | C67: 11.5 | D67: 2.5 | E67: 1.8 | F67: 3.2 | G67: 1.9 | H67: 3.2 | I67: 2.8 | K67: =I67 -> 2.8 | L67: =K67 -> 2.8 | M67: =L67 -> 2.8 | N67: =M67 -> 2.8 | O67: =N67 -> 2.8 | P67: =O67 -> 2.8 | Q67: =P67 -> 2.8 | R67: =Q67 -> 2.8 | S67: =R67 -> 2.8 | T67: =S67 -> 2.8
B68: Total Finance Cost | C68: =SUM(C63:C67) -> 997.4 | D68: =SUM(D63:D67) -> 428.8 | E68: =SUM(E63:E67) -> 537.9 | F68: =SUM(F63:F67) -> 674.1 | G68: =SUM(G63:G67) -> 581.3 | H68: =SUM(H63:H67) -> 694.5 | I68: =SUM(I63:I67) -> 1420.5 | K68: =SUM(K65:K67) -> 1780.3735 | L68: =SUM(L65:L67) -> 1821.2098 | M68: =SUM(M65:M67) -> 1851.5637 | N68: =SUM(N65:N67) -> 1874.126 | O68: =SUM(O65:O67) -> 1890.8966 | P68: =SUM(P65:P67) -> 1903.3624 | Q68: =SUM(Q65:Q67) -> 1912.7273 | R68: =SUM(R65:R67) -> 1919.7874 | ... T68: =SUM(T65:T67) -> 1929.2079
B70: Implied interest rate | C70: 0 | D70: 0 | E70: 0 | F70: =F65/AVERAGE(Schedules!E35:F35) -> 0.10290561 | G70: =G65/AVERAGE(Schedules!F35:G35) -> 0.092232459 | H70: =H65/AVERAGE(Schedules!G35:H35) -> 0.095326467 | I70: =I65/AVERAGE(Schedules!H35:I35) -> 0.1059605 | K70: =AVERAGE($F$70:$I$70) -> 0.099106258 | L70: =AVERAGE($F$70:$I$70) -> 0.099106258 | M70: =AVERAGE($F$70:$I$70) -> 0.099106258 | N70: =AVERAGE($F$70:$I$70) -> 0.099106258 | O70: =AVERAGE($F$70:$I$70) -> 0.099106258 | P70: =AVERAGE($F$70:$I$70) -> 0.099106258 | Q70: =AVERAGE($F$70:$I$70) -> 0.099106258 | R70: =AVERAGE($F$70:$I$70) -> 0.099106258 | ... T70: =AVERAGE($F$70:$I$70) -> 0.099106258
B72: Transfer of CWIP as percentage of previosu year's additions: | K72: 0.05 | L72: 0.05 | M72: 0.05 | N72: 0.02 | O72: 0.02 | P72: 0.02 | Q72: 0.01 | R72: 0.01 | S72: 0.01 | T72: 0.01
B73: High | K73: =AVERAGE($D$30:$I$30)*1.03 -> 1.0036566 | L73: =K73*1.03 -> 1.0337663 | M73: =L73*1.05 -> 1.0854547 | N73: =M73*1.01 -> 1.0963092 | O73: =N73*1.01 -> 1.1072723 | P73: =O73*1.01 -> 1.118345 | Q73: =P73*1.01 -> 1.1295285 | R73: =Q73*1.01 -> 1.1408238 | S73: =R73*1.01 -> 1.152232 | T73: =S73*1.01 -> 1.1637543
B74: Average | K74: =AVERAGE($D$30:$I$30) -> 0.97442393 | L74: =K74*1.05 -> 1.0231451 | M74: =L74*1.05 -> 1.0743024 | N74: =M74*1.01 -> 1.0850454 | O74: =N74*1.01 -> 1.0958959 | P74: =O74*1.01 -> 1.1068548 | Q74: =P74*1.01 -> 1.1179234 | R74: =Q74*1.01 -> 1.1291026 | S74: =R74*1.01 -> 1.1403936 | T74: =S74*1.01 -> 1.1517976
B75: Lower | K75: =AVERAGE($D$30:$I$30)*0.9 -> 0.87698154 | L75: =K75*1.05 -> 0.92083061 | M75: =L75*1.05 -> 0.96687214 | N75: =M75*1.05 -> 1.0152157 | O75: =N75*1.05 -> 1.0659765 | P75: =O75*1.02 -> 1.0872961 | Q75: =P75*1.02 -> 1.109042 | R75: =Q75 -> 1.109042 | S75: =R75 -> 1.109042 | T75: =S75*1.02 -> 1.1312228

Sheet Data_Sheet
A1: Date | B1: Price | C1: Open | D1: High | E1: Low | F1: Vol. | G1: Change % | H1: Year | I1: Quarter | J1: Month | P1: 2020-21 | Q1: 2021-22 | R1: 2022-23 | S1: 2023-24 | T1: 2024-25 | U1: 2025-26
A2: 43922 | B2: 2082.7 | C2: 2218 | D2: 2230 | E2: 2078.15 | F2: 272200 | G2: -0.0479 | H2: =YEAR(AVEU_Historical_Data__2[[#This Row],[Date]]) -> 2020 | I2: =ROUNDUP((MOD(MONTH(AVEU_Historical_Data__2[[#This Row],[Date]])+8,12)+1)/3,0) -> 1 | J2: =MONTH(AVEU_Historical_Data__2[[#This Row],[Date]]) -> 4 | O2: Revenue growth (Y-o-Y) | P2: -0.029237401 | Q2: 0.28302999 | R2: 0.38297994 | S2: 0.1855591 | T2: 0.16872253 | U2: 0.15941713
A3: 43924 | B3: 2066.95 | C3: 2101.5 | D3: 2119 | E3: 2020 | F3: 303210 | G3: -0.0076 | H3: =YEAR(AVEU_Historical_Data__2[[#This Row],[Date]]) -> 2020 | I3: =ROUNDUP((MOD(MONTH(AVEU_Historical_Data__2[[#This Row],[Date]])+8,12)+1)/3,0) -> 1 | J3: =MONTH(AVEU_Historical_Data__2[[#This Row],[Date]]) -> 4 | L3: Row Labels | M3: Average of Price
A4: 43928 | B4: 2170.25 | C4: 2090.1 | D4: 2170.25 | E4: 2090.1 | F4: 219470 | G4: 0.05 | H4: =YEAR(AVEU_Historical_Data__2[[#This Row],[Date]]) -> 2020 | I4: =ROUNDUP((MOD(MONTH(AVEU_Historical_Data__2[[#This Row],[Date]])+8,12)+1)/3,0) -> 1 | J4: =MONTH(AVEU_Historical_Data__2[[#This Row],[Date]]) -> 4 | L4: 2020 | M4: 2280.6283 | P4: 2020-21 | Q4: 2021-22 | R4: 2022-23 | S4: 2023-24 | T4: 2024-25 | U4: 2025-26
A5: 43929 | B5: 2278.75 | C5: 2222 | D5: 2278.75 | E5: 2201.05 | F5: 153350 | G5: 0.05 | H5: =YEAR(AVEU_Historical_Data__2[[#This Row],[Date]]) -> 2020 | I5: =ROUNDUP((MOD(MONTH(AVEU_Historical_Data__2[[#This Row],[Date]])+8,12)+1)/3,0) -> 1 | J5: =MONTH(AVEU_Historical_Data__2[[#This Row],[Date]]) -> 4 | L5: 2021 | M5: 3620.9115 | O5: Revenue from sales from per retail sales area sq.ft | P5: 27306 | Q5: 27454 | R5: 31096 | S5: 32941 | T5: 33869 | U5: 33422
A6: 43930 | B6: 2392.65 | C6: 2392.65 | D6: 2392.65 | E6: 2392.65 | F6: 231680 | G6: 0.05 | H6: =YEAR(AVEU_Historical_Data__2[[#This Row],[Date]]) -> 2020 | I6: =ROUNDUP((MOD(MONTH(AVEU_Historical_Data__2[[#This Row],[Date]])+8,12)+1)/3,0) -> 1 | J6: =MONTH(AVEU_Historical_Data__2[[#This Row],[Date]]) -> 4 | L6: 2022 | M6: 4077.6554
A7: 43934 | B7: 2273.05 | C7: 2320 | D7: 2320 | E7: 2273.05 | F7: 272320 | G7: -0.05 | H7: =YEAR(AVEU_Historical_Data__2[[#This Row],[Date]]) -> 2020 | I7: =ROUNDUP((MOD(MONTH(AVEU_Historical_Data__2[[#This Row],[Date]])+8,12)+1)/3,0) -> 1 | J7: =MONTH(AVEU_Historical_Data__2[[#This Row],[Date]]) -> 4 | L7: 2023 | M7: 3673.7089 | P7: 2020-21 | Q7: 2021-22 | R7: 2022-23 | S7: 2023-24 | T7: 2024-25 | U7: 2025-26
A8: 43936 | B8: 2180.9 | C8: 2161 | D8: 2320 | E8: 2159.4 | F8: 634860 | G8: -0.0405 | H8: =YEAR(AVEU_Historical_Data__2[[#This Row],[Date]]) -> 2020 | I8: =ROUNDUP((MOD(MONTH(AVEU_Historical_Data__2[[#This Row],[Date]])+8,12)+1)/3,0) -> 1 | J8: =MONTH(AVEU_Historical_Data__2[[#This Row],[Date]]) -> 4 | L8: 2024 | M8: 4383.2404 | O8: Retail sales area | P8: 8.8 | Q8: 11.5 | R8: 13.4 | S8: 15.1 | T8: 17.2 | U8: 20.6
A9: 43937 | B9: 2137.85 | C9: 2151 | D9: 2210 | E9: 2104.9 | F9: 393230 | G9: -0.0197 | H9: =YEAR(AVEU_Historical_Data__2[[#This Row],[Date]]) -> 2020 | I9: =ROUNDUP((MOD(MONTH(AVEU_Historical_Data__2[[#This Row],[Date]])+8,12)+1)/3,0) -> 1 | J9: =MONTH(AVEU_Historical_Data__2[[#This Row],[Date]]) -> 4 | L9: 2025 | M9: 4083.3016
A10: 43938 | B10: 2212.1 | C10: 2214 | D10: 2230 | E10: 2200 | F10: 292020 | G10: 0.0347 | H10: =YEAR(AVEU_Historical_Data__2[[#This Row],[Date]]) -> 2020 | I10: =ROUNDUP((MOD(MONTH(AVEU_Historical_Data__2[[#This Row],[Date]])+8,12)+1)/3,0) -> 1 | J10: =MONTH(AVEU_Historical_Data__2[[#This Row],[Date]]) -> 4 | L10: 2026 | M10: 4041.9933 | P10: 2020-21 | Q10: 2021-22 | R10: 2022-23 | S10: 2023-24 | T10: 2024-25 | U10: 2025-26
A11: 43941 | B11: 2256.25 | C11: 2229.95 | D11: 2285 | E11: 2150.05 | F11: 274760 | G11: 0.02 | H11: =YEAR(AVEU_Historical_Data__2[[#This Row],[Date]]) -> 2020 | I11: =ROUNDUP((MOD(MONTH(AVEU_Historical_Data__2[[#This Row],[Date]])+8,12)+1)/3,0) -> 1 | J11: =MONTH(AVEU_Historical_Data__2[[#This Row],[Date]]) -> 4 | L11: Grand Total | M11: 3777.9851 | O11: Revenue from operations | P11: 241430.6 | Q11: 309762.7 | R11: 428395.6 | S11: 507888.3 | T11: 593580.5 | U11: 688207.4
A12: 43942 | B12: 2238.2 | C12: 2200 | D12: 2288.5 | E12: 2199.45 | F12: 205880 | G12: -0.008 | H12: =YEAR(AVEU_Historical_Data__2[[#This Row],[Date]]) -> 2020 | I12: =ROUNDUP((MOD(MONTH(AVEU_Historical_Data__2[[#This Row],[Date]])+8,12)+1)/3,0) -> 1 | J12: =MONTH(AVEU_Historical_Data__2[[#This Row],[Date]]) -> 4
A13: 43943 | B13: 2290.05 | C13: 2235 | D13: 2320 | E13: 2225 | F13: 232000 | G13: 0.0232 | H13: =YEAR(AVEU_Historical_Data__2[[#This Row],[Date]]) -> 2020 | I13: =ROUNDUP((MOD(MONTH(AVEU_Historical_Data__2[[#This Row],[Date]])+8,12)+1)/3,0) -> 1 | J13: =MONTH(AVEU_Historical_Data__2[[#This Row],[Date]]) -> 4 | P13: 2020-21 | Q13: 2021-22 | R13: 2022-23 | S13: 2023-24 | T13: 2024-25 | U13: 2025-26
A14: 43944 | B14: 2303.5 | C14: 2290.05 | D14: 2350 | E14: 2290.05 | F14: 182400 | G14: 0.0059 | H14: =YEAR(AVEU_Historical_Data__2[[#This Row],[Date]]) -> 2020 | I14: =ROUNDUP((MOD(MONTH(AVEU_Historical_Data__2[[#This Row],[Date]])+8,12)+1)/3,0) -> 1 | J14: =MONTH(AVEU_Historical_Data__2[[#This Row],[Date]]) -> 4 | L14: Row Labels | M14: Sum of Volume | O14: EBIT | P14: 13288.9 | Q14: 20004.2 | R14: 29981.6 | S14: 33730.1 | T14: 36178.1 | U14: 41495.7
A15: 43945 | B15: 2310.5 | C15: 2299.45 | D15: 2346.5 | E15: 2269.45 | F15: 586420 | G15: 0.003 | H15: =YEAR(AVEU_Historical_Data__2[[#This Row],[Date]]) -> 2020 | I15: =ROUNDUP((MOD(MONTH(AVEU_Historical_Data__2[[#This Row],[Date]])+8,12)+1)/3,0) -> 1 | J15: =MONTH(AVEU_Historical_Data__2[[#This Row],[Date]]) -> 4 | L15: 2020 | M15: 119713620 | O15: EBIT margin | P15: 0.055042319 | Q15: 0.064579112 | R15: 0.069985779 | S15: 0.066412438 | T15: 0.060948936 | U15: 0.060295341
A16: 43948 | B16: 2323.95 | C16: 2300 | D16: 2350 | E16: 2274 | F16: 198320 | G16: 0.0058 | H16: =YEAR(AVEU_Historical_Data__2[[#This Row],[Date]]) -> 2020 | I16: =ROUNDUP((MOD(MONTH(AVEU_Historical_Data__2[[#This Row],[Date]])+8,12)+1)/3,0) -> 1 | J16: =MONTH(AVEU_Historical_Data__2[[#This Row],[Date]]) -> 4 | L16: 2021 | M16: 116165280
A17: 43949 | B17: 2305.8 | C17: 2339 | D17: 2340 | E17: 2285 | F17: 858550 | G17: -0.0078 | H17: =YEAR(AVEU_Historical_Data__2[[#This Row],[Date]]) -> 2020 | I17: =ROUNDUP((MOD(MONTH(AVEU_Historical_Data__2[[#This Row],[Date]])+8,12)+1)/3,0) -> 1 | J17: =MONTH(AVEU_Historical_Data__2[[#This Row],[Date]]) -> 4 | L17: 2022 | M17: 102609300 | P17: 2020-21 | Q17: 2021-22 | R17: 2022-23 | S17: 2023-24 | T17: 2024-25 | U17: 2025-26
A18: 43950 | B18: 2344.35 | C18: 2310 | D18: 2350 | E18: 2305.8 | F18: 120880 | G18: 0.0167 | H18: =YEAR(AVEU_Historical_Data__2[[#This Row],[Date]]) -> 2020 | I18: =ROUNDUP((MOD(MONTH(AVEU_Historical_Data__2[[#This Row],[Date]])+8,12)+1)/3,0) -> 1 | J18: =MONTH(AVEU_Historical_Data__2[[#This Row],[Date]]) -> 4 | L18: 2023 | M18: 85452980 | O18: Net Profit | P18: 10994.3 | Q18: 14924 | R18: 23783.4 | S18: 25356.1 | T18: 27074.5 | U18: 29706
A19: 43951 | B19: 2383.65 | C19: 2349 | D19: 2389.75 | E19: 2325 | F19: 619340 | G19: 0.0168 | H19: =YEAR(AVEU_Historical_Data__2[[#This Row],[Date]]) -> 2020 | I19: =ROUNDUP((MOD(MONTH(AVEU_Historical_Data__2[[#This Row],[Date]])+8,12)+1)/3,0) -> 1 | J19: =MONTH(AVEU_Historical_Data__2[[#This Row],[Date]]) -> 4 | L19: 2024 | M19: 138939140 | O19: Net profit margin | P19: 0.045538138 | Q19: 0.048178816 | R19: 0.055517377 | S19: 0.04992456 | T19: 0.045612179 | U19: 0.043164314
A20: 43955 | B20: 2281.3 | C20: 2310.2 | D20: 2345 | E20: 2269.95 | F20: 234630 | G20: -0.0429 | H20: =YEAR(AVEU_Historical_Data__2[[#This Row],[Date]]) -> 2020 | I20: =ROUNDUP((MOD(MONTH(AVEU_Historical_Data__2[[#This Row],[Date]])+8,12)+1)/3,0) -> 1 | J20: =MONTH(AVEU_Historical_Data__2[[#This Row],[Date]]) -> 5 | L20: 2025 | M20: 145453260
A21: 43956 | B21: 2198.95 | C21: 2320 | D21: 2329.95 | E21: 2185.3 | F21: 183050 | G21: -0.0361 | H21: =YEAR(AVEU_Historical_Data__2[[#This Row],[Date]]) -> 2020 | I21: =ROUNDUP((MOD(MONTH(AVEU_Historical_Data__2[[#This Row],[Date]])+8,12)+1)/3,0) -> 1 | J21: =MONTH(AVEU_Historical_Data__2[[#This Row],[Date]]) -> 5 | L21: 2026 | M21: 93491040 | P21: 2020-21 | Q21: 2021-22 | R21: 2022-23 | S21: 2023-24 | T21: 2024-25 | U21: 2025-26
A22: 43957 | B22: 2175.6 | C22: 2200 | D22: 2249 | E22: 2126.55 | F22: 292520 | G22: -0.0106 | H22: =YEAR(AVEU_Historical_Data__2[[#This Row],[Date]]) -> 2020 | I22: =ROUNDUP((MOD(MONTH(AVEU_Historical_Data__2[[#This Row],[Date]])+8,12)+1)/3,0) -> 1 | J22: =MONTH(AVEU_Historical_Data__2[[#This Row],[Date]]) -> 5 | L22: Grand Total | M22: 801824620 | O22: Net cash flow from operating activities | P22: 13751.4 | Q22: 13723.5 | R22: 26302.7 | S22: 27458.4 | T22: 24629.7 | U22: 34667.4
A23: 43958 | B23: 2182.1 | C23: 2180 | D23: 2210.3 | E23: 2144 | F23: 287440 | G23: 0.003 | H23: =YEAR(AVEU_Historical_Data__2[[#This Row],[Date]]) -> 2020 | I23: =ROUNDUP((MOD(MONTH(AVEU_Historical_Data__2[[#This Row],[Date]])+8,12)+1)/3,0) -> 1 | J23: =MONTH(AVEU_Historical_Data__2[[#This Row],[Date]]) -> 5
A24: 43959 | B24: 2255 | C24: 2190 | D24: 2284 | E24: 2185 | F24: 247820 | G24: 0.0334 | H24: =YEAR(AVEU_Historical_Data__2[[#This Row],[Date]]) -> 2020 | I24: =ROUNDUP((MOD(MONTH(AVEU_Historical_Data__2[[#This Row],[Date]])+8,12)+1)/3,0) -> 1 | J24: =MONTH(AVEU_Historical_Data__2[[#This Row],[Date]]) -> 5 | P24: 2020-21 | Q24: 2021-22 | R24: 2022-23 | S24: 2023-24 | T24: 2024-25 | U24: 2025-26
A25: 43962 | B25: 2313.55 | C25: 2280 | D25: 2358 | E25: 2270 | F25: 279520 | G25: 0.026 | H25: =YEAR(AVEU_Historical_Data__2[[#This Row],[Date]]) -> 2020 | I25: =ROUNDUP((MOD(MONTH(AVEU_Historical_Data__2[[#This Row],[Date]])+8,12)+1)/3,0) -> 1 | J25: =MONTH(AVEU_Historical_Data__2[[#This Row],[Date]]) -> 5 | L25: Top shareholders | M25: Shareholding % | O25: No.of days in inventory | P25: 37.252421 | Q25: 34.505175 | R25: 30.10843 | S25: 30.241088 | T25: 32.389249 | U25: 34.16821
A26: 43963 | B26: 2303.35 | C26: 2320.55 | D26: 2347 | E26: 2286.9 | F26: 277810 | G26: -0.0044 | H26: =YEAR(AVEU_Historical_Data__2[[#This Row],[Date]]) -> 2020 | I26: =ROUNDUP((MOD(MONTH(AVEU_Historical_Data__2[[#This Row],[Date]])+8,12)+1)/3,0) -> 1 | J26: =MONTH(AVEU_Historical_Data__2[[#This Row],[Date]]) -> 5 | L26: Promoter | M26: 0.7452 | O26: No.of days for receivables | P26: 0.47720649 | Q26: 0.65084579 | R26: 0.55126967 | S26: 0.82117909 | T26: 0.98435174 | U26: 0.80384525
A27: 43964 | B27: 2352.15 | C27: 2353 | D27: 2379.95 | E27: 2305 | F27: 373230 | G27: 0.0212 | H27: =YEAR(AVEU_Historical_Data__2[[#This Row],[Date]]) -> 2020 | I27: =ROUNDUP((MOD(MONTH(AVEU_Historical_Data__2[[#This Row],[Date]])+8,12)+1)/3,0) -> 1 | J27: =MONTH(AVEU_Historical_Data__2[[#This Row],[Date]]) -> 5 | L27: Mutual Funds | M27: 0.0677 | O27: No.of days for payables | P27: 8.9815726 | Q27: 8.0704087 | R27: 6.7548238 | S27: 7.3321288 | T27: 7.4211283 | U27: 7.5205582
A28: 43965 | B28: 2324.4 | C28: 2344.35 | D28: 2358 | E28: 2304 | F28: 344410 | G28: -0.0118 | H28: =YEAR(AVEU_Historical_Data__2[[#This Row],[Date]]) -> 2020 | I28: =ROUNDUP((MOD(MONTH(AVEU_Historical_Data__2[[#This Row],[Date]])+8,12)+1)/3,0) -> 1 | J28: =MONTH(AVEU_Historical_Data__2[[#This Row],[Date]]) -> 5 | L28: Foreign Portfolio Investor | M28: 0.09 | O28: Cash Conversion Cycle | P28: =P25+P26-P27 -> 28.748055 | Q28: =Q25+Q26-Q27 -> 27.085612 | R28: =R25+R26-R27 -> 23.904876 | S28: =S25+S26-S27 -> 23.730138 | T28: =T25+T26-T27 -> 25.952472 | U28: =U25+U26-U27 -> 27.451497
A29: 43966 | B29: 2333.8 | C29: 2320 | D29: 2340 | E29: 2290.25 | F29: 181710 | G29: 0.004 | H29: =YEAR(AVEU_Historical_Data__2[[#This Row],[Date]]) -> 2020 | I29: =ROUNDUP((MOD(MONTH(AVEU_Historical_Data__2[[#This Row],[Date]])+8,12)+1)/3,0) -> 1 | J29: =MONTH(AVEU_Historical_Data__2[[#This Row],[Date]]) -> 5 | L29: Provident Funds/Pension Funds | M29: 0.0146
A30: 43969 | B30: 2306.55 | C30: 2333 | D30: 2370.8 | E30: 2275 | F30: 293740 | G30: -0.0117 | H30: =YEAR(AVEU_Historical_Data__2[[#This Row],[Date]]) -> 2020 | I30: =ROUNDUP((MOD(MONTH(AVEU_Historical_Data__2[[#This Row],[Date]])+8,12)+1)/3,0) -> 1 | J30: =MONTH(AVEU_Historical_Data__2[[#This Row],[Date]]) -> 5 | L30: Individuals | M30: 0.0719 | P30: 2020-21 | Q30: 2021-22 | R30: 2022-23 | S30: 2023-24 | T30: 2024-25 | U30: 2025-26
A31: 43970 | B31: 2337.5 | C31: 2341.95 | D31: 2355.6 | E31: 2306 | F31: 254060 | G31: 0.0134 | H31: =YEAR(AVEU_Historical_Data__2[[#This Row],[Date]]) -> 2020 | I31: =ROUNDUP((MOD(MONTH(AVEU_Historical_Data__2[[#This Row],[Date]])+8,12)+1)/3,0) -> 1 | J31: =MONTH(AVEU_Historical_Data__2[[#This Row],[Date]]) -> 5 | L31: Minority Shareholders | M31: 0.0106 | O31: Equity | P31: 121841.1 | Q31: 136778.9 | R31: 160787.8 | S31: 186973.4 | T31: 214267 | U31: 244623.6
A32: 43971 | B32: 2454.35 | C32: 2335 | D32: 2454.35 | E32: 2318 | F32: 374840 | G32: 0.05 | H32: =YEAR(AVEU_Historical_Data__2[[#This Row],[Date]]) -> 2020 | I32: =ROUNDUP((MOD(MONTH(AVEU_Historical_Data__2[[#This Row],[Date]])+8,12)+1)/3,0) -> 1 | J32: =MONTH(AVEU_Historical_Data__2[[#This Row],[Date]]) -> 5 | L32: Total (A+B) | M32: =SUM(M26:M31) -> 1 | O32: Debt | P32: =SUM(BS!D46:D47,BS!D53:D54,BS!D56:D58,BS!D59) -> 13537.2 | Q32: =SUM(BS!E46:E47,BS!E53:E54,BS!E56:E58,BS!E59) -> 16310.4 | R32: =SUM(BS!F46:F47,BS!F53:F54,BS!F56:F58,BS!F59) -> 18078.8 | S32: =SUM(BS!G46:G47,BS!G53:G54,BS!G56:G58,BS!G59) -> 20629.3 | T32: =SUM(BS!H46:H47,BS!H53:H54,BS!H56:H58,BS!H59) -> 24781.8 | U32: =SUM(BS!I46:I47,BS!I53:I54,BS!I56:I58,BS!I59) -> 45423.9
A33: 43972 | B33: 2470.25 | C33: 2452 | D33: 2519.95 | E33: 2375 | F33: 359120 | G33: 0.0065 | H33: =YEAR(AVEU_Historical_Data__2[[#This Row],[Date]]) -> 2020 | I33: =ROUNDUP((MOD(MONTH(AVEU_Historical_Data__2[[#This Row],[Date]])+8,12)+1)/3,0) -> 1 | J33: =MONTH(AVEU_Historical_Data__2[[#This Row],[Date]]) -> 5 | O33: Debt to equity ratio | P33: =P32/P31 -> 0.11110537 | Q33: =Q32/Q31 -> 0.11924646 | R33: =R32/R31 -> 0.11243888 | S33: =S32/S31 -> 0.11033281 | T33: =T32/T31 -> 0.1156585 | U33: =U32/U31 -> 0.18568895
A34: 43973 | B34: 2398.3 | C34: 2484.8 | D34: 2518 | E34: 2381.5 | F34: 388440 | G34: -0.0291 | H34: =YEAR(AVEU_Historical_Data__2[[#This Row],[Date]]) -> 2020 | I34: =ROUNDUP((MOD(MONTH(AVEU_Historical_Data__2[[#This Row],[Date]])+8,12)+1)/3,0) -> 1 | J34: =MONTH(AVEU_Historical_Data__2[[#This Row],[Date]]) -> 5
A35: 43977 | B35: 2283.25 | C35: 2339 | D35: 2340 | E35: 2278.4 | F35: 773060 | G35: -0.048 | H35: =YEAR(AVEU_Historical_Data__2[[#This Row],[Date]]) -> 2020 | I35: =ROUNDUP((MOD(MONTH(AVEU_Historical_Data__2[[#This Row],[Date]])+8,12)+1)/3,0) -> 1 | J35: =MONTH(AVEU_Historical_Data__2[[#This Row],[Date]]) -> 5 | P35: 2020-21 | Q35: 2021-22 | R35: 2022-23 | S35: 2023-24 | T35: 2024-25 | U35: 2025-26
A36: 43978 | B36: 2200.2 | C36: 2222.2 | D36: 2275 | E36: 2176 | F36: 751860 | G36: -0.0364 | H36: =YEAR(AVEU_Historical_Data__2[[#This Row],[Date]]) -> 2020 | I36: =ROUNDUP((MOD(MONTH(AVEU_Historical_Data__2[[#This Row],[Date]])+8,12)+1)/3,0) -> 1 | J36: =MONTH(AVEU_Historical_Data__2[[#This Row],[Date]]) -> 5 | O36: Net profit after tax | P36: ='P & L'!D32 -> 10994.3 | Q36: ='P & L'!E32 -> 14924 | R36: ='P & L'!F32 -> 23783.4 | S36: ='P & L'!G32 -> 25356.1 | T36: ='P & L'!H32 -> 27074.5 | U36: ='P & L'!I32 -> 29706
A37: 43979 | B37: 2308.45 | C37: 2210 | D37: 2310.2 | E37: 2205 | F37: 927240 | G37: 0.0492 | H37: =YEAR(AVEU_Historical_Data__2[[#This Row],[Date]]) -> 2020 | I37: =ROUNDUP((MOD(MONTH(AVEU_Historical_Data__2[[#This Row],[Date]])+8,12)+1)/3,0) -> 1 | J37: =MONTH(AVEU_Historical_Data__2[[#This Row],[Date]]) -> 5 | O37: Average net worth | P37: =AVERAGE(BS!C34:D34)-SUM(AVERAGE(BS!C50:D50),AVERAGE(BS!C62:D62)) -> 116321.55 | Q37: =AVERAGE(BS!D34:E34)-SUM(AVERAGE(BS!D50:E50),AVERAGE(BS!D62:E62)) -> 129310 | R37: =AVERAGE(BS!E34:F34)-SUM(AVERAGE(BS!E50:F50),AVERAGE(BS!E62:F62)) -> 148783.35 | S37: =AVERAGE(BS!F34:G34)-SUM(AVERAGE(BS!F50:G50),AVERAGE(BS!F62:G62)) -> 173880.6 | T37: =AVERAGE(BS!G34:H34)-SUM(AVERAGE(BS!G50:H50),AVERAGE(BS!G62:H62)) -> 200620.2 | U37: =AVERAGE(BS!H34:I34)-SUM(AVERAGE(BS!H50:I50),AVERAGE(BS!H62:I62)) -> 229445.3
A38: 43980 | B38: 2269.35 | C38: 2330 | D38: 2358 | E38: 2229 | F38: 3800000 | G38: -0.0169 | H38: =YEAR(AVEU_Historical_Data__2[[#This Row],[Date]]) -> 2020 | I38: =ROUNDUP((MOD(MONTH(AVEU_Historical_Data__2[[#This Row],[Date]])+8,12)+1)/3,0) -> 1 | J38: =MONTH(AVEU_Historical_Data__2[[#This Row],[Date]]) -> 5 | O38: Capital employed | P38: =AVERAGE(P32:P32)+AVERAGE(P31:P31)-AVERAGE(BS!C28:D28)-AVERAGE(BS!C26:D26) -> 133803.3 | Q38: =AVERAGE(P32:Q32)+AVERAGE(P31:Q31)-AVERAGE(BS!D28:E28)-AVERAGE(BS!D26:E26) -> 142756.3 | R38: =AVERAGE(Q32:R32)+AVERAGE(Q31:R31)-AVERAGE(BS!E28:F28)-AVERAGE(BS!E26:F26) -> 163426 | S38: =AVERAGE(R32:S32)+AVERAGE(R31:S31)-AVERAGE(BS!F28:G28)-AVERAGE(BS!F26:G26) -> 188969.05 | T38: =AVERAGE(S32:T32)+AVERAGE(S31:T31)-AVERAGE(BS!G28:H28)-AVERAGE(BS!G26:H26) -> 219323.2 | U38: =AVERAGE(T32:U32)+AVERAGE(T31:U31)-AVERAGE(BS!H28:I28)-AVERAGE(BS!H26:I26) -> 261335.95
A39: 43983 | B39: 2305.5 | C39: 2320.1 | D39: 2328.55 | E39: 2282.65 | F39: 448580 | G39: 0.0159 | H39: =YEAR(AVEU_Historical_Data__2[[#This Row],[Date]]) -> 2020 | I39: =ROUNDUP((MOD(MONTH(AVEU_Historical_Data__2[[#This Row],[Date]])+8,12)+1)/3,0) -> 1 | J39: =MONTH(AVEU_Historical_Data__2[[#This Row],[Date]]) -> 6 | O39: Return on Net Worth | P39: =P$36/P37 -> 0.09451645 | Q39: =Q$36/Q37 -> 0.11541257 | R39: =R$36/R37 -> 0.15985256 | S39: =S$36/S37 -> 0.14582478 | T39: =T$36/T37 -> 0.13495401 | U39: =U$36/U37 -> 0.12946877
A40: 43984 | B40: 2381.7 | C40: 2309.1 | D40: 2389 | E40: 2290.05 | F40: 503210 | G40: 0.0331 | H40: =YEAR(AVEU_Historical_Data__2[[#This Row],[Date]]) -> 2020 | I40: =ROUNDUP((MOD(MONTH(AVEU_Historical_Data__2[[#This Row],[Date]])+8,12)+1)/3,0) -> 1 | J40: =MONTH(AVEU_Historical_Data__2[[#This Row],[Date]]) -> 6 | O40: Return on Capital Employed | P40: =P$36/P38 -> 0.08216763 | Q40: =Q$36/Q38 -> 0.1045418 | R40: =R$36/R38 -> 0.14553009 | S40: =S$36/S38 -> 0.13418123 | T40: =T$36/T38 -> 0.12344567 | U40: =U$36/U38 -> 0.11366978
A41: 43985 | B41: 2349.3 | C41: 2390 | D41: 2450 | E41: 2330 | F41: 425480 | G41: -0.0136 | H41: =YEAR(AVEU_Historical_Data__2[[#This Row],[Date]]) -> 2020 | I41: =ROUNDUP((MOD(MONTH(AVEU_Historical_Data__2[[#This Row],[Date]])+8,12)+1)/3,0) -> 1 | J41: =MONTH(AVEU_Historical_Data__2[[#This Row],[Date]]) -> 6
A42: 43986 | B42: 2414.2 | C42: 2362 | D42: 2434 | E42: 2311.3 | F42: 363350 | G42: 0.0276 | H42: =YEAR(AVEU_Historical_Data__2[[#This Row],[Date]]) -> 2020 | I42: =ROUNDUP((MOD(MONTH(AVEU_Historical_Data__2[[#This Row],[Date]])+8,12)+1)/3,0) -> 1 | J42: =MONTH(AVEU_Historical_Data__2[[#This Row],[Date]]) -> 6
A43: 43987 | B43: 2499 | C43: 2438 | D43: 2524 | E43: 2434.15 | F43: 668800 | G43: 0.0351 | H43: =YEAR(AVEU_Historical_Data__2[[#This Row],[Date]]) -> 2020 | I43: =ROUNDUP((MOD(MONTH(AVEU_Historical_Data__2[[#This Row],[Date]])+8,12)+1)/3,0) -> 1 | J43: =MONTH(AVEU_Historical_Data__2[[#This Row],[Date]]) -> 6
A44: 43990 | B44: 2459.5 | C44: 2520 | D44: 2527 | E44: 2414.2 | F44: 322710 | G44: -0.0158 | H44: =YEAR(AVEU_Historical_Data__2[[#This Row],[Date]]) -> 2020 | I44: =ROUNDUP((MOD(MONTH(AVEU_Historical_Data__2[[#This Row],[Date]])+8,12)+1)/3,0) -> 1 | J44: =MONTH(AVEU_Historical_Data__2[[#This Row],[Date]]) -> 6
A45: 43991 | B45: 2390.1 | C45: 2461 | D45: 2468.8 | E45: 2370 | F45: 376330 | G45: -0.0282 | H45: =YEAR(AVEU_Historical_Data__2[[#This Row],[Date]]) -> 2020 | I45: =ROUNDUP((MOD(MONTH(AVEU_Historical_Data__2[[#This Row],[Date]])+8,12)+1)/3,0) -> 1 | J45: =MONTH(AVEU_Historical_Data__2[[#This Row],[Date]]) -> 6
A46: 43992 | B46: 2388.35 | C46: 2400 | D46: 2429.95 | E46: 2360 | F46: 215500 | G46: -0.0007 | H46: =YEAR(AVEU_Historical_Data__2[[#This Row],[Date]]) -> 2020 | I46: =ROUNDUP((MOD(MONTH(AVEU_Historical_Data__2[[#This Row],[Date]])+8,12)+1)/3,0) -> 1 | J46: =MONTH(AVEU_Historical_Data__2[[#This Row],[Date]]) -> 6
A47: 43993 | B47: 2406.5 | C47: 2390 | D47: 2422.8 | E47: 2365 | F47: 325840 | G47: 0.0076 | H47: =YEAR(AVEU_Historical_Data__2[[#This Row],[Date]]) -> 2020 | I47: =ROUNDUP((MOD(MONTH(AVEU_Historical_Data__2[[#This Row],[Date]])+8,12)+1)/3,0) -> 1 | J47: =MONTH(AVEU_Historical_Data__2[[#This Row],[Date]]) -> 6
A48: 43994 | B48: 2397.8 | C48: 2312 | D48: 2438 | E48: 2312 | F48: 415420 | G48: -0.0036 | H48: =YEAR(AVEU_Historical_Data__2[[#This Row],[Date]]) -> 2020 | I48: =ROUNDUP((MOD(MONTH(AVEU_Historical_Data__2[[#This Row],[Date]])+8,12)+1)/3,0) -> 1 | J48: =MONTH(AVEU_Historical_Data__2[[#This Row],[Date]]) -> 6
A49: 43997 | B49: 2365.3 | C49: 2373 | D49: 2422 | E49: 2337.05 | F49: 354820 | G49: -0.0136 | H49: =YEAR(AVEU_Historical_Data__2[[#This Row],[Date]]) -> 2020 | I49: =ROUNDUP((MOD(MONTH(AVEU_Historical_Data__2[[#This Row],[Date]])+8,12)+1)/3,0) -> 1 | J49: =MONTH(AVEU_Historical_Data__2[[#This Row],[Date]]) -> 6
A50: 43998 | B50: 2403.55 | C50: 2399 | D50: 2434 | E50: 2356.6 | F50: 321260 | G50: 0.0162 | H50: =YEAR(AVEU_Historical_Data__2[[#This Row],[Date]]) -> 2020 | I50: =ROUNDUP((MOD(MONTH(AVEU_Historical_Data__2[[#This Row],[Date]])+8,12)+1)/3,0) -> 1 | J50: =MONTH(AVEU_Historical_Data__2[[#This Row],[Date]]) -> 6
A51: 43999 | B51: 2340.4 | C51: 2390 | D51: 2404 | E51: 2325 | F51: 563670 | G51: -0.0263 | H51: =YEAR(AVEU_Historical_Data__2[[#This Row],[Date]]) -> 2020 | I51: =ROUNDUP((MOD(MONTH(AVEU_Historical_Data__2[[#This Row],[Date]])+8,12)+1)/3,0) -> 1 | J51: =MONTH(AVEU_Historical_Data__2[[#This Row],[Date]]) -> 6
A52: 44000 | B52: 2350.85 | C52: 2331 | D52: 2365 | E52: 2320.3 | F52: 199700 | G52: 0.0045 | H52: =YEAR(AVEU_Historical_Data__2[[#This Row],[Date]]) -> 2020 | I52: =ROUNDUP((MOD(MONTH(AVEU_Historical_Data__2[[#This Row],[Date]])+8,12)+1)/3,0) -> 1 | J52: =MONTH(AVEU_Historical_Data__2[[#This Row],[Date]]) -> 6
... A1024: 45429 | B1024: 4682.9 | C1024: 4680 | D1024: 4710 | E1024: 4665.05 | F1024: 203110 | G1024: 0.0025 | H1024: =YEAR(AVEU_Historical_Data__2[[#This Row],[Date]]) -> 2024 | I1024: =ROUNDUP((MOD(MONTH(AVEU_Historical_Data__2[[#This Row],[Date]])+8,12)+1)/3,0) -> 1 | J1024: =MONTH(AVEU_Historical_Data__2[[#This Row],[Date]]) -> 5
A1025: 45430 | B1025: 4670.65 | C1025: 4670.65 | D1025: 4670.65 | E1025: 4670.65 | G1025: -0.0026 | H1025: =YEAR(AVEU_Historical_Data__2[[#This Row],[Date]]) -> 2024 | I1025: =ROUNDUP((MOD(MONTH(AVEU_Historical_Data__2[[#This Row],[Date]])+8,12)+1)/3,0) -> 1 | J1025: =MONTH(AVEU_Historical_Data__2[[#This Row],[Date]]) -> 5
A1026: 45433 | B1026: 4705.9 | C1026: 4670 | D1026: 4737.45 | E1026: 4605.45 | F1026: 179170 | G1026: 0.0075 | H1026: =YEAR(AVEU_Historical_Data__2[[#This Row],[Date]]) -> 2024 | I1026: =ROUNDUP((MOD(MONTH(AVEU_Historical_Data__2[[#This Row],[Date]])+8,12)+1)/3,0) -> 1 | J1026: =MONTH(AVEU_Historical_Data__2[[#This Row],[Date]]) -> 5
A1027: 45434 | B1027: 4798.8 | C1027: 4763.15 | D1027: 4924.2 | E1027: 4737.15 | F1027: 716980 | G1027: 0.0197 | H1027: =YEAR(AVEU_Historical_Data__2[[#This Row],[Date]]) -> 2024 | I1027: =ROUNDUP((MOD(MONTH(AVEU_Historical_Data__2[[#This Row],[Date]])+8,12)+1)/3,0) -> 1 | J1027: =MONTH(AVEU_Historical_Data__2[[#This Row],[Date]]) -> 5
A1028: 45435 | B1028: 4793.55 | C1028: 4794.5 | D1028: 4812 | E1028: 4755.8 | F1028: 151030 | G1028: -0.0011 | H1028: =YEAR(AVEU_Historical_Data__2[[#This Row],[Date]]) -> 2024 | I1028: =ROUNDUP((MOD(MONTH(AVEU_Historical_Data__2[[#This Row],[Date]])+8,12)+1)/3,0) -> 1 | J1028: =MONTH(AVEU_Historical_Data__2[[#This Row],[Date]]) -> 5
A1029: 45436 | B1029: 4684.5 | C1029: 4797.9 | D1029: 4841.4 | E1029: 4674.1 | F1029: 307320 | G1029: -0.0227 | H1029: =YEAR(AVEU_Historical_Data__2[[#This Row],[Date]]) -> 2024 | I1029: =ROUNDUP((MOD(MONTH(AVEU_Historical_Data__2[[#This Row],[Date]])+8,12)+1)/3,0) -> 1 | J1029: =MONTH(AVEU_Historical_Data__2[[#This Row],[Date]]) -> 5
A1030: 45439 | B1030: 4537.35 | C1030: 4651.55 | D1030: 4669 | E1030: 4508 | F1030: 392850 | G1030: -0.0314 | H1030: =YEAR(AVEU_Historical_Data__2[[#This Row],[Date]]) -> 2024 | I1030: =ROUNDUP((MOD(MONTH(AVEU_Historical_Data__2[[#This Row],[Date]])+8,12)+1)/3,0) -> 1 | J1030: =MONTH(AVEU_Historical_Data__2[[#This Row],[Date]]) -> 5
A1031: 45440 | B1031: 4474.45 | C1031: 4551.9 | D1031: 4588.85 | E1031: 4440.2 | F1031: 224690 | G1031: -0.0139 | H1031: =YEAR(AVEU_Historical_Data__2[[#This Row],[Date]]) -> 2024 | I1031: =ROUNDUP((MOD(MONTH(AVEU_Historical_Data__2[[#This Row],[Date]])+8,12)+1)/3,0) -> 1 | J1031: =MONTH(AVEU_Historical_Data__2[[#This Row],[Date]]) -> 5
A1032: 45441 | B1032: 4476.85 | C1032: 4474 | D1032: 4564.85 | E1032: 4435.1 | F1032: 234520 | G1032: 0.0005 | H1032: =YEAR(AVEU_Historical_Data__2[[#This Row],[Date]]) -> 2024 | I1032: =ROUNDUP((MOD(MONTH(AVEU_Historical_Data__2[[#This Row],[Date]])+8,12)+1)/3,0) -> 1 | J1032: =MONTH(AVEU_Historical_Data__2[[#This Row],[Date]]) -> 5
A1033: 45442 | B1033: 4444.95 | C1033: 4475.9 | D1033: 4497.25 | E1033: 4410 | F1033: 141710 | G1033: -0.0071 | H1033: =YEAR(AVEU_Historical_Data__2[[#This Row],[Date]]) -> 2024 | I1033: =ROUNDUP((MOD(MONTH(AVEU_Historical_Data__2[[#This Row],[Date]])+8,12)+1)/3,0) -> 1 | J1033: =MONTH(AVEU_Historical_Data__2[[#This Row],[Date]]) -> 5
A1034: 45443 | B1034: 4302.15 | C1034: 4440 | D1034: 4450 | E1034: 4250.4 | F1034: 866440 | G1034: -0.0321 | H1034: =YEAR(AVEU_Historical_Data__2[[#This Row],[Date]]) -> 2024 | I1034: =ROUNDUP((MOD(MONTH(AVEU_Historical_Data__2[[#This Row],[Date]])+8,12)+1)/3,0) -> 1 | J1034: =MONTH(AVEU_Historical_Data__2[[#This Row],[Date]]) -> 5
A1035: 45446 | B1035: 4349.35 | C1035: 4392.95 | D1035: 4400 | E1035: 4301 | F1035: 279800 | G1035: 0.011 | H1035: =YEAR(AVEU_Historical_Data__2[[#This Row],[Date]]) -> 2024 | I1035: =ROUNDUP((MOD(MONTH(AVEU_Historical_Data__2[[#This Row],[Date]])+8,12)+1)/3,0) -> 1 | J1035: =MONTH(AVEU_Historical_Data__2[[#This Row],[Date]]) -> 6
A1036: 45447 | B1036: 4548.75 | C1036: 4399 | D1036: 4590 | E1036: 4355.65 | F1036: 1090000 | G1036: 0.0458 | H1036: =YEAR(AVEU_Historical_Data__2[[#This Row],[Date]]) -> 2024 | I1036: =ROUNDUP((MOD(MONTH(AVEU_Historical_Data__2[[#This Row],[Date]])+8,12)+1)/3,0) -> 1 | J1036: =MONTH(AVEU_Historical_Data__2[[#This Row],[Date]]) -> 6
A1037: 45448 | B1037: 4862.25 | C1037: 4590 | D1037: 4900 | E1037: 4562.2 | F1037: 1500000 | G1037: 0.0689 | H1037: =YEAR(AVEU_Historical_Data__2[[#This Row],[Date]]) -> 2024 | I1037: =ROUNDUP((MOD(MONTH(AVEU_Historical_Data__2[[#This Row],[Date]])+8,12)+1)/3,0) -> 1 | J1037: =MONTH(AVEU_Historical_Data__2[[#This Row],[Date]]) -> 6
... A1566: 46227 | B1566: 4018.8 | C1566: 4010 | D1566: 4074.8 | E1566: 3990 | F1566: 332480 | G1566: -0.004 | H1566: =YEAR(AVEU_Historical_Data__2[[#This Row],[Date]]) -> 2026 | I1566: =ROUNDUP((MOD(MONTH(AVEU_Historical_Data__2[[#This Row],[Date]])+8,12)+1)/3,0) -> 2 | J1566: =MONTH(AVEU_Historical_Data__2[[#This Row],[Date]]) -> 7
A1567: 46230 | B1567: 4027.7 | C1567: 4030 | D1567: 4074.1 | E1567: 4013 | F1567: 384730 | G1567: 0.0022 | H1567: =YEAR(AVEU_Historical_Data__2[[#This Row],[Date]]) -> 2026 | I1567: =ROUNDUP((MOD(MONTH(AVEU_Historical_Data__2[[#This Row],[Date]])+8,12)+1)/3,0) -> 2 | J1567: =MONTH(AVEU_Historical_Data__2[[#This Row],[Date]]) -> 7 | N1567: 1000
A1568: 46231 | B1568: 3846.6 | C1568: 4027.7 | D1568: 4094.2 | E1568: 3755.1 | F1568: 2410000 | G1568: -0.045 | H1568: =YEAR(AVEU_Historical_Data__2[[#This Row],[Date]]) -> 2026 | I1568: =ROUNDUP((MOD(MONTH(AVEU_Historical_Data__2[[#This Row],[Date]])+8,12)+1)/3,0) -> 2 | J1568: =MONTH(AVEU_Historical_Data__2[[#This Row],[Date]]) -> 7
A1569: 46232 | B1569: 3848.1 | C1569: 3859.3 | D1569: 3879.8 | E1569: 3826 | F1569: 629780 | G1569: 0.0004 | H1569: =YEAR(AVEU_Historical_Data__2[[#This Row],[Date]]) -> 2026 | I1569: =ROUNDUP((MOD(MONTH(AVEU_Historical_Data__2[[#This Row],[Date]])+8,12)+1)/3,0) -> 2 | J1569: =MONTH(AVEU_Historical_Data__2[[#This Row],[Date]]) -> 7
A1570: 46233 | B1570: 3874 | C1570: 3849 | D1570: 3967.2 | E1570: 3837.1 | F1570: 1040000 | G1570: 0.0067 | H1570: =YEAR(AVEU_Historical_Data__2[[#This Row],[Date]]) -> 2026 | I1570: =ROUNDUP((MOD(MONTH(AVEU_Historical_Data__2[[#This Row],[Date]])+8,12)+1)/3,0) -> 2 | J1570: =MONTH(AVEU_Historical_Data__2[[#This Row],[Date]]) -> 7
A1571: 46234 | B1571: 3921 | C1571: 3900.1 | D1571: 3946.5 | E1571: 3889.7 | F1571: 551950 | G1571: 0.0121 | H1571: =YEAR(AVEU_Historical_Data__2[[#This Row],[Date]]) -> 2026 | I1571: =ROUNDUP((MOD(MONTH(AVEU_Historical_Data__2[[#This Row],[Date]])+8,12)+1)/3,0) -> 2 | J1571: =MONTH(AVEU_Historical_Data__2[[#This Row],[Date]]) -> 7
A1572: 46237 | B1572: 4015 | C1572: 3945.1 | D1572: 4017 | E1572: 3912.1 | F1572: 497300 | G1572: 0.024 | H1572: =YEAR(AVEU_Historical_Data__2[[#This Row],[Date]]) -> 2026 | I1572: =ROUNDUP((MOD(MONTH(AVEU_Historical_Data__2[[#This Row],[Date]])+8,12)+1)/3,0) -> 2 | J1572: =MONTH(AVEU_Historical_Data__2[[#This Row],[Date]]) -> 8
A1573: 46238 | B1573: 4023 | C1573: 4023 | D1573: 4023 | E1573: 3969.7 | F1573: 448870 | G1573: 0.002 | H1573: =YEAR(AVEU_Historical_Data__2[[#This Row],[Date]]) -> 2026 | I1573: =ROUNDUP((MOD(MONTH(AVEU_Historical_Data__2[[#This Row],[Date]])+8,12)+1)/3,0) -> 2 | J1573: =MONTH(AVEU_Historical_Data__2[[#This Row],[Date]]) -> 8
A1574: 46239 | B1574: 3946 | C1574: 4018 | D1574: 4018.5 | E1574: 3946 | F1574: 347770 | G1574: -0.0191 | H1574: =YEAR(AVEU_Historical_Data__2[[#This Row],[Date]]) -> 2026 | I1574: =ROUNDUP((MOD(MONTH(AVEU_Historical_Data__2[[#This Row],[Date]])+8,12)+1)/3,0) -> 2 | J1574: =MONTH(AVEU_Historical_Data__2[[#This Row],[Date]]) -> 8
A1575: 46240 | B1575: 3931.2 | C1575: 3988.9 | D1575: 3988.9 | E1575: 3927.6 | F1575: 250190 | G1575: -0.0038 | H1575: =YEAR(AVEU_Historical_Data__2[[#This Row],[Date]]) -> 2026 | I1575: =ROUNDUP((MOD(MONTH(AVEU_Historical_Data__2[[#This Row],[Date]])+8,12)+1)/3,0) -> 2 | J1575: =MONTH(AVEU_Historical_Data__2[[#This Row],[Date]]) -> 8
A1576: 46241 | B1576: 3900 | C1576: 3945 | D1576: 3948.4 | E1576: 3885.5 | F1576: 374240 | G1576: -0.0079 | H1576: =YEAR(AVEU_Historical_Data__2[[#This Row],[Date]]) -> 2026 | I1576: =ROUNDUP((MOD(MONTH(AVEU_Historical_Data__2[[#This Row],[Date]])+8,12)+1)/3,0) -> 2 | J1576: =MONTH(AVEU_Historical_Data__2[[#This Row],[Date]]) -> 8
A1577: 46244 | B1577: 4054 | C1577: 3910 | D1577: 4059.8 | E1577: 3897 | F1577: 552730 | G1577: 0.0395 | H1577: =YEAR(AVEU_Historical_Data__2[[#This Row],[Date]]) -> 2026 | I1577: =ROUNDUP((MOD(MONTH(AVEU_Historical_Data__2[[#This Row],[Date]])+8,12)+1)/3,0) -> 2 | J1577: =MONTH(AVEU_Historical_Data__2[[#This Row],[Date]]) -> 8
A1578: 46245 | B1578: 4054.9 | C1578: 4054 | D1578: 4085 | E1578: 4003.2 | F1578: 413760 | G1578: 0.0002 | H1578: =YEAR(AVEU_Historical_Data__2[[#This Row],[Date]]) -> 2026 | I1578: =ROUNDUP((MOD(MONTH(AVEU_Historical_Data__2[[#This Row],[Date]])+8,12)+1)/3,0) -> 2 | J1578: =MONTH(AVEU_Historical_Data__2[[#This Row],[Date]]) -> 8
A1579: 46246 | B1579: 4040 | C1579: 4035 | D1579: 4068.9 | E1579: 4020 | F1579: 336890 | G1579: -0.0037 | H1579: =YEAR(AVEU_Historical_Data__2[[#This Row],[Date]]) -> 2026 | I1579: =ROUNDUP((MOD(MONTH(AVEU_Historical_Data__2[[#This Row],[Date]])+8,12)+1)/3,0) -> 2 | J1579: =MONTH(AVEU_Historical_Data__2[[#This Row],[Date]]) -> 8
... A1593: 46266 | B1593: 3784.4 | C1593: 3850 | D1593: 3850 | E1593: 3766.2 | F1593: 209190 | G1593: -0.0296 | H1593: =YEAR(AVEU_Historical_Data__2[[#This Row],[Date]]) -> 2026 | I1593: =ROUNDUP((MOD(MONTH(AVEU_Historical_Data__2[[#This Row],[Date]])+8,12)+1)/3,0) -> 2 | J1593: =MONTH(AVEU_Historical_Data__2[[#This Row],[Date]]) -> 9

Sheet Front Page
B19: Equity Research Report & Valuation Model
E37: 2026
I42: Prepared by:
J44: Pranesh MK

Sheet Index
B20: TABLE OF CONTENTS
B24: S.No | D24: Titles
B29: 1 | D29: Introduction
B32: 2 | D32: Operating & Financial Summary
B35: 3 | D35: Ratio Analysis
B38: 4 | D38: Profit & Loss Statement
B41: 5 | D41: Profit & Loss Statement
B44: 6 | D44: Balance Sheet
B47: 7 | D47: Cash Flow Statement
B50: 8 | D50: DCF Valuation

Sheet Introduction
B2: Avenue Supermarts Limited - A One Page Financial Profile
F5: Avenue Supermarts Limited is an Indian retail company that operates a chain of supermarkets under the DMart brand. DMart follows a value-retail business model, focusing on offering everyday products at competitive prices while maintaining relatively disciplined operating costs. The company's core business is the retailing of food, FMCG, general merchandise and apparel products through its network of physical stores. DMart's business model is based largely on the Everyday Low Cost/Everyday Low Price philosophy.
B14: Key Financial Metrics:
C17: Key Financial Metrics | D17: 43921 | E17: =EOMONTH(D17,12) -> 44286 | F17: =EOMONTH(E17,12) -> 44651 | G17: =EOMONTH(F17,12) -> 45016 | H17: =EOMONTH(G17,12) -> 45382 | I17: =EOMONTH(H17,12) -> 45747 | J17: =EOMONTH(I17,12) -> 46112
C18: Revenue from operations | D18: ='P & L'!C8 -> 248702 | E18: ='P & L'!D8 -> 241430.6 | F18: ='P & L'!E8 -> 309762.7 | G18: ='P & L'!F8 -> 428395.6 | H18: ='P & L'!G8 -> 507888.3 | I18: ='P & L'!H8 -> 593580.5 | J18: ='P & L'!I8 -> 688207.4
C19: Revenue growth (Y-o-Y) | D19: 0.24322903 | E19: =(E18/D18)-1 -> -0.029237401 | F19: =(F18/E18)-1 -> 0.28302999 | G19: =(G18/F18)-1 -> 0.38297994 | H19: =(H18/G18)-1 -> 0.1855591 | I19: =(I18/H18)-1 -> 0.16872253 | J19: =(J18/I18)-1 -> 0.15941713
C20: Gross profit margin (%) | D20: ='P & L'!C13 -> 0.15147727 | E20: ='P & L'!D13 -> 0.14862988 | F20: ='P & L'!E13 -> 0.14781896 | G20: ='P & L'!F13 -> 0.15069272 | H20: ='P & L'!G13 -> 0.14795163 | I20: ='P & L'!H13 -> 0.14835983 | J20: ='P & L'!I13 -> 0.15055069
C21: EBITDA margin | D21: ='P & L'!C18 -> 0.085576714 | E21: ='P & L'!D18 -> 0.072196731 | F21: ='P & L'!E18 -> 0.080658517 | G21: ='P & L'!F18 -> 0.084898865 | H21: ='P & L'!G18 -> 0.080800641 | I21: ='P & L'!H18 -> 0.075597665 | J21: ='P & L'!I18 -> 0.075363764
C22: EBIT margin | D22: ='P & L'!C21 -> 0.070522151 | E22: ='P & L'!D21 -> 0.055042319 | F22: ='P & L'!E21 -> 0.064579112 | G22: ='P & L'!F21 -> 0.069985779 | H22: ='P & L'!G21 -> 0.066412438 | I22: ='P & L'!H21 -> 0.060948936 | J22: ='P & L'!I21 -> 0.060295341
C23: EBT margin | D23: ='P & L'!C26 -> 0.070155045 | E23: ='P & L'!D26 -> 0.061444158 | F23: ='P & L'!E26 -> 0.066635525 | G23: ='P & L'!F26 -> 0.071431406 | H23: ='P & L'!G26 -> 0.068151403 | I23: ='P & L'!H26 -> 0.061873158 | J23: ='P & L'!I26 -> 0.059307993
C24: Net profit margin | D24: ='P & L'!C33 -> 0.052310798 | E24: ='P & L'!D33 -> 0.045538138 | F24: ='P & L'!E33 -> 0.048178816 | G24: ='P & L'!F33 -> 0.055517377 | H24: ='P & L'!G33 -> 0.04992456 | I24: ='P & L'!H33 -> 0.045612179 | J24: ='P & L'!I33 -> 0.043164314
C25: Earnings Per Share (EPS) | D25: ='P & L'!C36 -> 20.71 | E25: ='P & L'!D36 -> 16.97 | F25: ='P & L'!E36 -> 23.04 | G25: ='P & L'!F36 -> 36.72 | H25: ='P & L'!G36 -> 38.99 | I25: ='P & L'!H36 -> 41.61 | J25: ='P & L'!I36 -> 45.65
C26: EPS Growth rate Y-o-Y | D26: 0 | E26: =(E25/D25)-1 -> -0.18058909 | F26: =(F25/E25)-1 -> 0.35769004 | G26: =(G25/F25)-1 -> 0.59375 | H26: =(H25/G25)-1 -> 0.061819172 | I26: =(I25/H25)-1 -> 0.067196717 | J26: =(J25/I25)-1 -> 0.097092045
C27: Market price | D27: 2218 | E27: 2885 | F27: 4013 | G27: 341305 | H27: 4570 | I27: 4109.75 | J27: 4075
C28: Price-to-Earnings | D28: =2218/'P & L'!C36 -> 107.09802 | E28: =2885/'P & L'!D36 -> 170.00589 | F28: =4013/'P & L'!E36 -> 174.17535 | G28: =3413.05/'P & L'!F36 -> 92.947985 | H28: =4570/'P & L'!G36 -> 117.20954 | I28: =4109.75/'P & L'!H36 -> 98.768325 | J28: =4075/'P & L'!I36 -> 89.266156
C29: Price to book value | D29: =D27/10 -> 221.8 | E29: =E27/10 -> 288.5 | F29: =F27/10 -> 401.3 | G29: =G27/10 -> 34130.5 | H29: =H27/10 -> 457 | I29: =I27/10 -> 410.975 | J29: =J27/10 -> 407.5
C30: Return on equity | D30: =D25/D27 -> 0.0093372408 | E30: =E25/E27 -> 0.005882149 | F30: =F25/F27 -> 0.0057413406 | G30: =G25/G27 -> 0.00010758706 | H30: =H25/H27 -> 0.0085317287 | I30: =I25/I27 -> 0.010124703 | J30: =J25/J27 -> 0.011202454
C32: Top shareholders | D32: No.of shares | E32: Shareholding % | G32: Market value | I32: Capital structure (in millions)
C33: A. PROMOTERS: | D33: 485747156 | E33: 0.7452 | G33: =E33*'DCF Valuation'!$C$42 -> 1834274.7 | I33: Share price | J33: ='DCF Valuation'!C40 -> 3781
C34: B. PUBLIC SHAREHOLDING: | I34: Outstanding shares | J34: ='DCF Valuation'!C41 -> 651.00578
C35: Central Government | D35: 15248 | E35: 0 | G35: =E35*'DCF Valuation'!$C$42 -> 0 | I35: Market capitalization | J35: =J33*J34 -> 2461452.9
C36: Mutual Funds | D36: 49677262 | E36: 0.0677 | G36: =E36*'DCF Valuation'!$C$42 -> 166640.36 | I36: Less: Cash | J36: ='DCF Valuation'!C45 -> -965.6
C37: Banks | D37: 6187 | E37: 0 | G37: =E37*'DCF Valuation'!$C$42 -> 0 | I37: Add: Debt | J37: ='DCF Valuation'!C44 -> 14597.2
C38: Insurance Companies | D38: 3915195 | E38: 0.0047 | G38: =E38*'DCF Valuation'!$C$42 -> 11568.828 | I38: Enterprise Value | J38: =SUM(J35:J37) -> 2475084.5
C39: Foreign Portfolio Investor | D39: 53208934 | E39: 0.09 | G39: =E39*'DCF Valuation'!$C$42 -> 221530.76
C40: Alternate Investment Funds | D40: 239444 | E40: 0.0007 | G40: =E40*'DCF Valuation'!$C$42 -> 1723.017
C41: Provident Funds/Pension Funds | D41: 5261246 | E41: 0.0146 | G41: =E41*'DCF Valuation'!$C$42 -> 35937.212
C42: Sovereign Wealth Funds | D42: 430903 | E42: 0.0007 | G42: =E42*'DCF Valuation'!$C$42 -> 1723.017
C43: Individuals | D43: 49969654 | E43: 0.0719 | G43: =E43*'DCF Valuation'!$C$42 -> 176978.46
C44: NBFCs | D44: 863 | E44: 0 | G44: =E44*'DCF Valuation'!$C$42 -> 0
C45: Trust | D45: 2297 | E45: 0 | G45: =E45*'DCF Valuation'!$C$42 -> 0
C46: Hindu Undivided Family | D46: 517942 | E46: 0.0007 | G46: =E46*'DCF Valuation'!$C$42 -> 1723.017
C47: Non-Resident Indians | D47: 714736 | E47: 0.0011 | G47: =E47*'DCF Valuation'!$C$42 -> 2707.5981
C48: Clearing Member | D48: 11811 | E48: 0.0012 | G48: =E48*'DCF Valuation'!$C$42 -> 2953.7434
C49: Bodies Corporate | D49: 971836 | E49: 0.0014 | G49: =E49*'DCF Valuation'!$C$42 -> 3446.034
C50: Body Corporate - Ltd Liability Partnership | D50: 42354 | E50: 0.0001 | G50: =E50*'DCF Valuation'!$C$42 -> 246.14529
C51: Total (A+B) | D51: 650733068 | E51: =SUM(E33:F50) -> 1 | G51: =SUM(G33:G50) -> 2461452.9
B67: Key Highlights:
C70: Leadership transition: - Neville (Ignatius) Noronha stepped down as MD & CEO after 21 years, handing over to Anshul Asawa, who now leads the company and set out his early priorities in his first shareholder letter. Milestone year for scale: - DMart crossed 500 stores (opening its 500th at Avadi, Chennai, on the final day of the fiscal year) after adding 85 new stores in FY 2025-26 — retail business area grew to 20.6 million sq. ft., up from 17.2 million the year before. Growth strategy going forward: - Doubling down on the EDLC/EDLP (Everyday Low Cost/Everyday Low Price) model as the core competitive moat, with management flagging that losing this pricing edge is one of the company's biggest listed risks. - Plans to simplify and automate execution processes to improve efficiency and service quality.

Sheet Operating and Financial Summary
B2: Operating and Financial Summary
A47: Sources: | B47: Sources:
C50: Dmart official website | E50: https://www.dmartindia.com/investor-relations/investor-updates/2026-2027
C51: Screener | E51: https://www.screener.in/company/DMART/consolidated/
C52: Yahoo finance | E52: https://finance.yahoo.com/quote/DMART.NS/history/?period1=1775001600&period2=1777507200
C53: Investing.com | E53: https://in.investing.com/equities/avenue-supermarts-ltd-historical-data

Sheet Common Size Statements
B2: Common Size Income Statement
C5: 43921 | D5: =EOMONTH(C5,12) -> 44286 | E5: =EOMONTH(D5,12) -> 44651 | F5: =EOMONTH(E5,12) -> 45016 | G5: =EOMONTH(F5,12) -> 45382 | H5: =EOMONTH(G5,12) -> 45747 | I5: =EOMONTH(H5,12) -> 46112
B6: Revenue from operations | C6: ='P & L'!C8/'P & L'!C$8 -> 1 | D6: ='P & L'!D8/'P & L'!D$8 -> 1 | E6: ='P & L'!E8/'P & L'!E$8 -> 1 | F6: ='P & L'!F8/'P & L'!F$8 -> 1 | G6: ='P & L'!G8/'P & L'!G$8 -> 1 | H6: ='P & L'!H8/'P & L'!H$8 -> 1 | I6: ='P & L'!I8/'P & L'!I$8 -> 1
B7: Purchase of stock-in-trade | C7: ='P & L'!C9/'P & L'!C$8 -> -0.86214345 | D7: ='P & L'!D9/'P & L'!D$8 -> -0.86383251 | E7: ='P & L'!E9/'P & L'!E$8 -> -0.868141 | F7: ='P & L'!F9/'P & L'!F$8 -> -0.86099787 | G7: ='P & L'!G9/'P & L'!G$8 -> -0.86551137 | H7: ='P & L'!H9/'P & L'!H$8 -> -0.87045919 | I7: ='P & L'!I9/'P & L'!I$8 -> -0.8618912
B8: Changes in stock-in-trade | C8: ='P & L'!C10/'P & L'!C$8 -> 0.013620719 | D8: ='P & L'!D10/'P & L'!D$8 -> 0.01246238 | E8: ='P & L'!E10/'P & L'!E$8 -> 0.015959959 | F8: ='P & L'!F10/'P & L'!F$8 -> 0.011690596 | G8: ='P & L'!G10/'P & L'!G$8 -> 0.013463 | H8: ='P & L'!H10/'P & L'!H$8 -> 0.018819014 | I8: ='P & L'!I10/'P & L'!I$8 -> 0.012441889
B9: Total COGS | C9: ='P & L'!C11/'P & L'!C$8 -> -0.84852273 | D9: ='P & L'!D11/'P & L'!D$8 -> -0.85137012 | E9: ='P & L'!E11/'P & L'!E$8 -> -0.85218104 | F9: ='P & L'!F11/'P & L'!F$8 -> -0.84930728 | G9: ='P & L'!G11/'P & L'!G$8 -> -0.85204837 | H9: ='P & L'!H11/'P & L'!H$8 -> -0.85164017 | I9: ='P & L'!I11/'P & L'!I$8 -> -0.84944931
B10: Gross profit | C10: =C9+C6 -> 0.15147727 | D10: =D9+D6 -> 0.14862988 | E10: =E9+E6 -> 0.14781896 | F10: =F9+F6 -> 0.15069272 | G10: =G9+G6 -> 0.14795163 | H10: =H9+H6 -> 0.14835983 | I10: =I9+I6 -> 0.15055069
B11: Employee benefits expenses | C11: ='P & L'!C14/'P & L'!C$8 -> -0.018339217 | D11: ='P & L'!D14/'P & L'!D$8 -> -0.022224606 | E11: ='P & L'!E14/'P & L'!E$8 -> -0.01989297 | F11: ='P & L'!F14/'P & L'!F$8 -> -0.017436454 | G11: ='P & L'!G14/'P & L'!G$8 -> -0.017840931 | H11: ='P & L'!H14/'P & L'!H$8 -> -0.019641818 | I11: ='P & L'!I14/'P & L'!I$8 -> -0.02239848
B12: Other expenses | C12: ='P & L'!C15/'P & L'!C$8 -> -0.047561338 | D12: ='P & L'!D15/'P & L'!D$8 -> -0.054208539 | E12: ='P & L'!E15/'P & L'!E$8 -> -0.047267473 | F12: ='P & L'!F15/'P & L'!F$8 -> -0.048357406 | G12: ='P & L'!G15/'P & L'!G$8 -> -0.049310055 | H12: ='P & L'!H15/'P & L'!H$8 -> -0.053120343 | I12: ='P & L'!I15/'P & L'!I$8 -> -0.052788447
B13: EBITDA | C13: =C10+C11+C12 -> 0.085576714 | D13: =D10+D11+D12 -> 0.072196731 | E13: =E10+E11+E12 -> 0.080658517 | F13: =F10+F11+F12 -> 0.084898865 | G13: =G10+G11+G12 -> 0.080800641 | H13: =H10+H11+H12 -> 0.075597665 | I13: =I10+I11+I12 -> 0.075363764
B14: Depreciation and Amortization | C14: ='P & L'!C19/'P & L'!C$8 -> -0.015054563 | D14: ='P & L'!D19/'P & L'!D$8 -> -0.017154412 | E14: ='P & L'!E19/'P & L'!E$8 -> -0.016079405 | F14: ='P & L'!F19/'P & L'!F$8 -> -0.014913085 | G14: ='P & L'!G19/'P & L'!G$8 -> -0.014388203 | H14: ='P & L'!H19/'P & L'!H$8 -> -0.014648729 | I14: ='P & L'!I19/'P & L'!I$8 -> -0.015068423
B15: EBIT | C15: =C14+C13 -> 0.070522151 | D15: =D14+D13 -> 0.055042319 | E15: =E14+E13 -> 0.064579112 | F15: =F14+F13 -> 0.069985779 | G15: =G14+G13 -> 0.066412438 | H15: =H14+H13 -> 0.060948936 | I15: =I14+I13 -> 0.060295341
B16: Finance Costs | C16: ='P & L'!C22/'P & L'!C$8 -> -0.0027792298 | D16: ='P & L'!D22/'P & L'!D$8 -> -0.0017251334 | E16: ='P & L'!E22/'P & L'!E$8 -> -0.0017364905 | F16: ='P & L'!F22/'P & L'!F$8 -> -0.0015735456 | G16: ='P & L'!G22/'P & L'!G$8 -> -0.001144543 | H16: ='P & L'!H22/'P & L'!H$8 -> -0.0011700182 | I16: ='P & L'!I22/'P & L'!I$8 -> -0.002064058
B17: Other Incomes | C17: ='P & L'!C23/'P & L'!C$8 -> 0.0024121237 | D17: ='P & L'!D23/'P & L'!D$8 -> 0.0081269731 | E17: ='P & L'!E23/'P & L'!E$8 -> 0.0037929034 | F17: ='P & L'!F23/'P & L'!F$8 -> 0.003019172 | G17: ='P & L'!G23/'P & L'!G$8 -> 0.002883508 | H17: ='P & L'!H23/'P & L'!H$8 -> 0.00209424 | I17: ='P & L'!I23/'P & L'!I$8 -> 0.0010767103
B18: EBT | C18: =C15+C16+C17 -> 0.070155045 | D18: =D15+D16+D17 -> 0.061444158 | E18: =E15+E16+E17 -> 0.066635525 | F18: =F15+F16+F17 -> 0.071431406 | G18: =G15+G16+G17 -> 0.068151403 | H18: =H15+H16+H17 -> 0.061873158 | I18: =I15+I16+I17 -> 0.059307993
B19: Current tax | C19: ='P & L'!C27/'P & L'!C$8 -> -0.018485577 | D19: ='P & L'!D27/'P & L'!D$8 -> -0.016347969 | E19: ='P & L'!E27/'P & L'!E$8 -> -0.017637049 | F19: ='P & L'!F27/'P & L'!F$8 -> -0.018854069 | G19: ='P & L'!G27/'P & L'!G$8 -> -0.017978166 | H19: ='P & L'!H27/'P & L'!H$8 -> -0.016568435 | I19: ='P & L'!I27/'P & L'!I$8 -> -0.016001426
B20: Deferred tax charge/(credit) | C20: ='P & L'!C28/'P & L'!C$8 -> 0.00064213396 | D20: ='P & L'!D28/'P & L'!D$8 -> -0.00013130067 | E20: ='P & L'!E28/'P & L'!E$8 -> -0.0003906216 | F20: ='P & L'!F28/'P & L'!F$8 -> -0.00029925611 | G20: ='P & L'!G28/'P & L'!G$8 -> -0.00023666621 | H20: ='P & L'!H28/'P & L'!H$8 -> -0.0002992012 | I20: ='P & L'!I28/'P & L'!I$8 -> -0.00014762992
B21: Adjustment of tax related to earlier years | C21: ='P & L'!C29/'P & L'!C$8 -> -8.0417528e-07 | D21: ='P & L'!D29/'P & L'!D$8 -> 0.00057324962 | E21: ='P & L'!E29/'P & L'!E$8 -> -0.0004290381 | F21: ='P & L'!F29/'P & L'!F$8 -> 0.0032392956 | G21: ='P & L'!G29/'P & L'!G$8 -> -1.2010515e-05 | H21: ='P & L'!H29/'P & L'!H$8 -> 0.0006066574 | I21: ='P & L'!I29/'P & L'!I$8 -> 5.3762863e-06
B22: Total Tax | C22: ='P & L'!C30/'P & L'!C$8 -> -0.017844247 | D22: ='P & L'!D30/'P & L'!D$8 -> -0.01590602 | E22: ='P & L'!E30/'P & L'!E$8 -> -0.018456709 | F22: ='P & L'!F30/'P & L'!F$8 -> -0.015914029 | G22: ='P & L'!G30/'P & L'!G$8 -> -0.018226842 | H22: ='P & L'!H30/'P & L'!H$8 -> -0.016260979 | I22: ='P & L'!I30/'P & L'!I$8 -> -0.01614368
B23: PAT | C23: =C22+C18 -> 0.052310798 | D23: =D22+D18 -> 0.045538138 | E23: =E22+E18 -> 0.048178816 | F23: =F22+F18 -> 0.055517377 | G23: =G22+G18 -> 0.04992456 | H23: =H22+H18 -> 0.045612179 | I23: =I22+I18 -> 0.043164314
B25: Common Size Balance Sheet
C28: 43921 | D28: =EOMONTH(C28,12) -> 44286 | E28: =EOMONTH(D28,12) -> 44651 | F28: =EOMONTH(E28,12) -> 45016 | G28: =EOMONTH(F28,12) -> 45382 | H28: =EOMONTH(G28,12) -> 45747 | I28: =EOMONTH(H28,12) -> 46112
B29: Assets
B30: Non-current assets
B31: Property, plant and equipment | C31: =BS!C10/BS!C$34 -> 0.42291899 | D31: =BS!D10/BS!D$34 -> 0.43486475 | E31: =BS!E10/BS!E$34 -> 0.50220648 | F31: =BS!F10/BS!F$34 -> 0.53713986 | G31: =BS!G10/BS!G$34 -> 0.55527596 | H31: =BS!H10/BS!H$34 -> 0.59003532 | I31: =BS!I10/BS!I$34 -> 0.59567793
B32: Capital work-in-progress | C32: =BS!C11/BS!C$34 -> 0.03017443 | D32: =BS!D11/BS!D$34 -> 0.074662583 | E32: =BS!E11/BS!E$34 -> 0.072989483 | F32: =BS!F11/BS!F$34 -> 0.045794031 | G32: =BS!G11/BS!G$34 -> 0.044161646 | H32: =BS!H11/BS!H$34 -> 0.045202997 | I32: =BS!I11/BS!I$34 -> 0.044030231
B33: Right-of-use assets | C33: =BS!C12/BS!C$34 -> 0.059399078 | D33: =BS!D12/BS!D$34 -> 0.070316499 | E33: =BS!E12/BS!E$34 -> 0.089748744 | F33: =BS!F12/BS!F$34 -> 0.083113658 | G33: =BS!G12/BS!G$34 -> 0.072677219 | H33: =BS!H12/BS!H$34 -> 0.071616334 | I33: =BS!I12/BS!I$34 -> 0.080659431
B34: Investment properties | C34: =BS!C13/BS!C$34 -> 0.0013687797 | D34: =BS!D13/BS!D$34 -> 0.0007007924 | E34: =BS!E13/BS!E$34 -> 0.00058361081 | F34: =BS!F13/BS!F$34 -> 0.0004716593 | G34: =BS!G13/BS!G$34 -> 0.00038201462 | H34: =BS!H13/BS!H$34 -> 0.00031455217 | I34: =BS!I13/BS!I$34 -> 0.00024589947
B35: Goodwill | C35: =BS!C14/BS!C$34 -> 0.0064812093 | D35: =BS!D14/BS!D$34 -> 0.0057315592 | E35: =BS!E14/BS!E$34 -> 0.0050586067 | F35: =BS!F14/BS!F$34 -> 0.0043228072 | G35: =BS!G14/BS!G$34 -> 0.003695956 | H35: =BS!H14/BS!H$34 -> 0.0032183004 | I35: =BS!I14/BS!I$34 -> 0.0026510402
B36: Intangible asset | C36: =BS!C15/BS!C$34 -> 0.0023632773 | D36: =BS!D15/BS!D$34 -> 0.0016271272 | E36: =BS!E15/BS!E$34 -> 0.00087961718 | F36: =BS!F15/BS!F$34 -> 0.0012802181 | G36: =BS!G15/BS!G$34 -> 0.0014331451 | H36: =BS!H15/BS!H$34 -> 0.0011915976 | I36: =BS!I15/BS!I$34 -> 0.0012335618
B37: Financial assets | C37: 0.25857516 | D37: 0.081230407 | E37: 0.081609215 | F37: 0.0059957065 | G37: 0.011085979 | H37: 0.0069953936 | I37: 0.006730736
B38: Income tax assets (net) | C38: =BS!C19/BS!C$34 -> 0.00068314778 | D38: =BS!D19/BS!D$34 -> 0.00011936172 | E38: =BS!E19/BS!E$34 -> 0.00014735688 | F38: =BS!F19/BS!F$34 -> 0.00096651495 | G38: =BS!G19/BS!G$34 -> 0.00082919366 | H38: =BS!H19/BS!H$34 -> 0.00074793516 | I38: =BS!I19/BS!I$34 -> 0.00056902358
B39: Deferred tax assets (net) | C39: =BS!C20/BS!C$34 -> 2.401368e-05 | D39: =BS!D20/BS!D$34 -> 6.7369802e-05 | E39: =BS!E20/BS!E$34 -> 0.00010728615 | F39: =BS!F20/BS!F$34 -> 9.7756084e-05 | G39: =BS!G20/BS!G$34 -> 0.00022288121 | H39: =BS!H20/BS!H$34 -> 0.00030879566 | I39: =BS!I20/BS!I$34 -> 0.00022727073
B40: Other non-current assets | C40: =BS!C21/BS!C$34 -> 0.023611243 | D40: =BS!D21/BS!D$34 -> 0.033290934 | E40: =BS!E21/BS!E$34 -> 0.024157481 | F40: =BS!F21/BS!F$34 -> 0.019906342 | G40: =BS!G21/BS!G$34 -> 0.017372457 | H40: =BS!H21/BS!H$34 -> 0.017534742 | I40: =BS!I21/BS!I$34 -> 0.014699098
B41: Total non-current assets | C41: =BS!C22/BS!C$34 -> 0.80559933 | D41: =BS!D22/BS!D$34 -> 0.70261139 | E41: =BS!E22/BS!E$34 -> 0.77748788 | F41: =BS!F22/BS!F$34 -> 0.69908855 | G41: =BS!G22/BS!G$34 -> 0.70713645 | H41: =BS!H22/BS!H$34 -> 0.73716596 | I41: =BS!I22/BS!I$34 -> 0.74672422
B42: Current assets
B43: Inventories | C43: =BS!C24/BS!C$34 -> 0.161256 | D43: =BS!D24/BS!D$34 -> 0.16463715 | E43: =BS!E24/BS!E$34 -> 0.1772587 | F43: =BS!F24/BS!F$34 -> 0.17913554 | G43: =BS!G24/BS!G$34 -> 0.18544992 | H43: =BS!H24/BS!H$34 -> 0.20741406 | I43: =BS!I24/BS!I$34 -> 0.19985734
B44: Financial assets | C44: 0.020798331 | D44: 0.12156002 | E44: 0.032241427 | F44: 0.10987618 | G44: 0.096315849 | H44: 0.042828437 | I44: 0.040025389
B45: Other current assets | C45: =BS!C31/BS!C$34 -> 0.012346344 | D45: =BS!D31/BS!D$34 -> 0.011191442 | E45: =BS!E31/BS!E$34 -> 0.013012001 | F45: =BS!F31/BS!F$34 -> 0.011899732 | G45: =BS!G31/BS!G$34 -> 0.011097784 | H45: =BS!H31/BS!H$34 -> 0.012591544 | I45: =BS!I31/BS!I$34 -> 0.013393054
B46: Total current assets | C46: =BS!C32/BS!C$34 -> 0.19440067 | D46: =BS!D32/BS!D$34 -> 0.29738861 | E46: =BS!E32/BS!E$34 -> 0.22251212 | F46: =BS!F32/BS!F$34 -> 0.30091145 | G46: =BS!G32/BS!G$34 -> 0.29286355 | H46: =BS!H32/BS!H$34 -> 0.26283404 | I46: =BS!I32/BS!I$34 -> 0.25327578
B48: Total assets | C48: =BS!C34/BS!C$34 -> 1 | D48: =BS!D34/BS!D$34 -> 1 | E48: =BS!E34/BS!E$34 -> 1 | F48: =BS!F34/BS!F$34 -> 1 | G48: =BS!G34/BS!G$34 -> 1 | H48: =BS!H34/BS!H$34 -> 1 | I48: =BS!I34/BS!I$34 -> 1
B50: Equity and liabilities
B51: Equity:
B52: Equity share capital | C52: =BS!C38/BS!C$64 -> 0.053639108 | D52: =BS!D38/BS!D$64 -> 0.047434931 | E52: =BS!E38/BS!E$64 -> 0.041865512 | F52: =BS!F38/BS!F$64 -> 0.035803028 | G52: =BS!G38/BS!G$64 -> 0.030727858 | H52: =BS!H38/BS!H$64 -> 0.026756671 | I52: =BS!I38/BS!I$64 -> 0.022082179
B53: Other equity | C53: =BS!C39/BS!C$64 -> 0.86382753 | D53: =BS!D39/BS!D$64 -> 0.84475435 | E53: =BS!E39/BS!E$64 -> 0.84212326 | F53: =BS!F39/BS!F$64 -> 0.85221434 | G53: =BS!G39/BS!G$64 -> 0.85219434 | H53: =BS!H39/BS!H$64 -> 0.85430807 | I53: =BS!I39/BS!I$64 -> 0.80652589
B54: Equity attributable to equity holders of the Company | C54: =SUM(C52:C53) -> 0.91746664 | D54: =SUM(D52:D53) -> 0.89218928 | E54: =SUM(E52:E53) -> 0.88398877 | F54: =SUM(F52:F53) -> 0.88801737 | G54: =SUM(G52:G53) -> 0.8829222 | H54: =SUM(H52:H53) -> 0.88106474 | I54: =SUM(I52:I53) -> 0.82860807
B55: Non-controlling interest | C55: =BS!C41/BS!C$64 -> 3.8090664e-05 | D55: =BS!D41/BS!D$64 -> 2.9291218e-05 | E55: =BS!E41/BS!E$64 -> 1.6157553e-05 | F55: =BS!F41/BS!F$64 -> 4.4183541e-06 | G55: =BS!G41/BS!G$64 -> -2.2665886e-05 | H55: =BS!H41/BS!H$64 -> -4.3173827e-05 | I55: =BS!I41/BS!I$64 -> -5.6902358e-05
B56: Total equity | C56: =BS!C42/BS!C$64 -> 0.91750473 | D56: =BS!D42/BS!D$64 -> 0.89221857 | E56: =BS!E42/BS!E$64 -> 0.88400493 | F56: =BS!F42/BS!F$64 -> 0.88802179 | G56: =BS!G42/BS!G$64 -> 0.88289953 | H56: =BS!H42/BS!H$64 -> 0.88102157 | I56: =BS!I42/BS!I$64 -> 0.82855116
B57: Liabilities:
B58: Non-current liabilities:
B59: Financial liabilities | C59: 0.018348107 | D59: 0.022880103 | E59: 0.03280371 | F59: 0.026351616 | G59: 0.018869822 | H59: 0.022873083 | I59: 0.038716635
B60: Provisions | C60: =BS!C48/BS!C$64 -> 0.00012255257 | D60: =BS!D48/BS!D$64 -> 0.00017940871 | E60: =BS!E48/BS!E$64 -> 0.00031474913 | F60: =BS!F48/BS!F$64 -> 0.00035402062 | G60: =BS!G48/BS!G$64 -> 0.00043348507 | H60: =BS!H48/BS!H$64 -> 0.00052096418 | I60: =BS!I48/BS!I$64 -> 0.00049789563
B61: Deferred tax liabilities (net) | C61: =BS!C49/BS!C$64 -> 0.0039241665 | D61: =BS!D49/BS!D$64 -> 0.0037485437 | E61: =BS!E49/BS!E$64 -> 0.0041382725 | F61: =BS!F49/BS!F$64 -> 0.0042504566 | G61: =BS!G49/BS!G$64 -> 0.0043409894 | H61: =BS!H49/BS!H$64 -> 0.0046249449 | I61: =BS!I49/BS!I$64 -> 0.0041274532
B62: Total non-current liabilities | C62: =BS!C50/BS!C$64 -> 0.022394826 | D62: =BS!D50/BS!D$64 -> 0.026808055 | E62: =BS!E50/BS!E$64 -> 0.037256732 | F62: =BS!F50/BS!F$64 -> 0.030956093 | G62: =BS!G50/BS!G$64 -> 0.023644297 | H62: =BS!H50/BS!H$64 -> 0.028018992 | I62: =BS!I50/BS!I$64 -> 0.043341984
B63: Current liabilities:
B64: Financial liabilities: | C64: 0.057092109 | D64: 0.068000296 | E64: 0.065399958 | F64: 0.066803857 | G64: 0.074022061 | H64: 0.073324784 | I64: 0.11034553
B65: Other current liabilities | C65: =BS!C59/BS!C$64 -> 3.7262606e-05 | D65: =BS!D59/BS!D$64 -> 0.0082498717 | E65: =BS!E59/BS!E$64 -> 0.0072107927 | F65: =BS!F59/BS!F$64 -> 0.0066927018 | G65: =BS!G59/BS!G$64 -> 0.0045208998 | H65: =BS!H59/BS!H$64 -> 0.0056997676 | I65: =BS!I59/BS!I$64 -> 0.0047906366
B66: Provisions | C66: =BS!C60/BS!C$64 -> 0.0017140799 | D66: =BS!D60/BS!D$64 -> 0.0029825783 | E66: =BS!E60/BS!E$64 -> 0.0037724655 | F66: =BS!F60/BS!F$64 -> 0.0028095209 | G66: =BS!G60/BS!G$64 -> 0.0028823452 | H66: =BS!H60/BS!H$64 -> 0.0020205351 | I66: =BS!I60/BS!I$64 -> 0.0037738456
B67: Current Tax Liabilities (Net) | C67: =BS!C61/BS!C$64 -> 0.0012569919 | D67: =BS!D61/BS!D$64 -> 0.0017406307 | E67: =BS!E61/BS!E$64 -> 0.0023551249 | F67: =BS!F61/BS!F$64 -> 0.0047160407 | G67: =BS!G61/BS!G$64 -> 0.012030863 | H67: =BS!H61/BS!H$64 -> 0.0099143555 | I67: =BS!I61/BS!I$64 -> 0.0091968435
B68: Total current liabilities | C68: =BS!C62/BS!C$64 -> 0.060100443 | D68: =BS!D62/BS!D$64 -> 0.080973376 | E68: =BS!E62/BS!E$64 -> 0.078738341 | F68: =BS!F62/BS!F$64 -> 0.08102212 | G68: =BS!G62/BS!G$64 -> 0.09345617 | H68: =BS!H62/BS!H$64 -> 0.090959442 | I68: =BS!I62/BS!I$64 -> 0.12810685
B70: Total liabilities | C70: =SUM(C62,C68) -> 0.08249527 | D70: =SUM(D62,D68) -> 0.10778143 | E70: =SUM(E62,E68) -> 0.11599507 | F70: =SUM(F62,F68) -> 0.11197821 | G70: =SUM(G62,G68) -> 0.11710047 | H70: =SUM(H62,H68) -> 0.11897843 | I70: =SUM(I62,I68) -> 0.17144884
B71: Total equity and liabilities | C71: =BS!C64/BS!C$64 -> 1 | D71: =BS!D64/BS!D$64 -> 1 | E71: =BS!E64/BS!E$64 -> 1 | F71: =BS!F64/BS!F$64 -> 1 | G71: =BS!G64/BS!G$64 -> 1 | H71: =BS!H64/BS!H$64 -> 1 | I71: =BS!I64/BS!I$64 -> 1

Sheet Ratio Analysis
B2: Ratio Analysis - Avenue Supermarts Limited (2020 - 2026)
B5: Profitability Ratios: | C5: 43921 | D5: =EOMONTH(C5,12) -> 44286 | E5: =EOMONTH(D5,12) -> 44651 | F5: =EOMONTH(E5,12) -> 45016 | G5: =EOMONTH(F5,12) -> 45382 | H5: =EOMONTH(G5,12) -> 45747 | I5: =EOMONTH(H5,12) -> 46112 | J5: Trend
B6: Gross profit Margin | C6: 0.15147727 | D6: 0.14862988 | E6: 0.14781896 | F6: 0.15069272 | G6: 0.14795163 | H6: 0.14835983 | I6: 0.15055069
B7: EBITDA Margin | C7: 0.085576714 | D7: 0.072196731 | E7: 0.080658517 | F7: 0.084898865 | G7: 0.080800641 | H7: 0.075597665 | I7: 0.075363764
B8: EBIT Margin | C8: 0.070522151 | D8: 0.055042319 | E8: 0.064579112 | F8: 0.069985779 | G8: 0.066412438 | H8: 0.060948936 | I8: 0.060295341
B9: EBT Margin | C9: 0.070155045 | D9: 0.061444158 | E9: 0.066635525 | F9: 0.071431406 | G9: 0.068151403 | H9: 0.061873158 | I9: 0.059307993
B10: Net Profit Margin | C10: 0.052310798 | D10: 0.045538138 | E10: 0.048178816 | F10: 0.055517377 | G10: 0.04992456 | H10: 0.045612179 | I10: 0.043164314
B12: Return On Investment: | C12: 43921 | D12: =EOMONTH(C12,12) -> 44286 | E12: =EOMONTH(D12,12) -> 44651 | F12: =EOMONTH(E12,12) -> 45016 | G12: =EOMONTH(F12,12) -> 45382 | H12: =EOMONTH(G12,12) -> 45747 | I12: =EOMONTH(H12,12) -> 46112 | J12: Trend
B13: Operating Profit Return On Asset | C13: 0 | D13: ='P & L'!D16/AVERAGE(BS!C34:D34) -> 0.13547502 | E13: ='P & L'!E16/AVERAGE(BS!D34:E34) -> 0.17154955 | F13: ='P & L'!F16/AVERAGE(BS!E34:F34) -> 0.21662572 | G13: ='P & L'!G16/AVERAGE(BS!F34:G34) -> 0.20893103 | H13: ='P & L'!H16/AVERAGE(BS!G34:H34) -> 0.19725616 | I13: ='P & L'!I16/AVERAGE(BS!H34:I34) -> 0.19265051
B14: Return On Assets | C14: 0 | D14: ='P & L'!D32/AVERAGE(BS!C34:D34) -> 0.08545096 | E14: ='P & L'!E32/AVERAGE(BS!D34:E34) -> 0.1024697 | F14: ='P & L'!F32/AVERAGE(BS!E34:F34) -> 0.14165669 | G14: ='P & L'!G32/AVERAGE(BS!F34:G34) -> 0.12909291 | H14: ='P & L'!H32/AVERAGE(BS!G34:H34) -> 0.11901536 | I14: ='P & L'!I32/AVERAGE(BS!H34:I34) -> 0.11033986
B15: Return Of Capital Employed | C15: 0 | D15: 0.08216763 | E15: 0.1045418 | F15: 0.14553009 | G15: 0.13418123 | H15: 0.12344567 | I15: 0.11366978
B16: Return On Equity | C16: 0 | D16: ='P & L'!D32/AVERAGE(BS!C42:D42) -> 0.09451645 | E16: ='P & L'!E32/AVERAGE(BS!D42:E42) -> 0.11541257 | F16: ='P & L'!F32/AVERAGE(BS!E42:F42) -> 0.15985256 | G16: ='P & L'!G32/AVERAGE(BS!F42:G42) -> 0.14582478 | H16: ='P & L'!H32/AVERAGE(BS!G42:H42) -> 0.13495401 | I16: ='P & L'!I32/AVERAGE(BS!H42:I42) -> 0.12946877
B18: Liquidity Ratios: | C18: 43921 | D18: =EOMONTH(C18,12) -> 44286 | E18: =EOMONTH(D18,12) -> 44651 | F18: =EOMONTH(E18,12) -> 45016 | G18: =EOMONTH(F18,12) -> 45382 | H18: =EOMONTH(G18,12) -> 45747 | I18: =EOMONTH(H18,12) -> 46112 | J18: Trend
B19: Current Ratio | C19: =BS!C32/BS!C62 -> 3.2345963 | D19: =BS!D32/BS!D62 -> 3.6726715 | E19: =BS!E32/BS!E62 -> 2.8259692 | F19: =BS!F32/BS!F62 -> 3.713942 | G19: =BS!G32/BS!G62 -> 3.1336995 | H19: =BS!H32/BS!H62 -> 2.889574 | I19: =BS!I32/BS!I62 -> 1.9770666
B20: Quick Ratio | C20: =(BS!C32-BS!C24-BS!C31)/BS!C62 -> 0.34605952 | D20: =(BS!D32-BS!D24-BS!D31)/BS!D62 -> 1.5012344 | E20: =(BS!E32-BS!E24-BS!E31)/BS!E62 -> 0.40947558 | F20: =(BS!F32-BS!F24-BS!F31)/BS!F62 -> 1.3561257 | G20: =(BS!G32-BS!G24-BS!G31)/BS!G62 -> 1.0305991 | H20: =(BS!H32-BS!H24-BS!H31)/BS!H62 -> 0.47085202 | I20: =(BS!I32-BS!I24-BS!I31)/BS!I62 -> 0.31243754
B21: Cash Ratio | C21: =BS!C28/BS!C62 -> 0.14586663 | D21: =BS!D28/BS!D62 -> 0.17318249 | E21: =BS!E28/BS!E62 -> 0.078076648 | F21: =BS!F28/BS!F62 -> 0.14120558 | G21: =BS!G28/BS!G62 -> 0.17033661 | H21: =BS!H28/BS!H62 -> 0.16069362 | I21: =BS!I28/BS!I62 -> 0.075010708
B22: Cash Conversion Cycle | C22: 0 | D22: 28.748055 | E22: 27.085612 | F22: 23.904876 | G22: 23.730138 | H22: 25.952472 | I22: 27.451497
B24: Turnover Ratio: | C24: 43921 | D24: =EOMONTH(C24,12) -> 44286 | E24: =EOMONTH(D24,12) -> 44651 | F24: =EOMONTH(E24,12) -> 45016 | G24: =EOMONTH(F24,12) -> 45382 | H24: =EOMONTH(G24,12) -> 45747 | I24: =EOMONTH(H24,12) -> 46112 | J24: Trend
B25: Receivables Turnover Ratio | C25: 0 | D25: 764.86805 | E25: 560.80873 | F25: 663.92189 | G25: 444.48283 | H25: 370.80241 | I25: 454.0675
B26: Inventory Turnover Ratio | C26: 0 | D26: 9.7980208 | E26: 10.578124 | F26: 12.156064 | G26: 12.069672 | H26: 11.269171 | I26: 10.682444
B27: Payables Turnover Ratio | C27: 0 | D27: 40.638763 | E27: 45.226954 | F27: 54.183501 | G27: 49.780904 | H27: 49.183896 | I27: 48.533632
B28: Asset Turnover Ratio | C28: 0 | D28: ='P & L'!D8/AVERAGE(BS!C34:D34) -> 1.8764702 | E28: ='P & L'!E8/AVERAGE(BS!D34:E34) -> 2.1268622 | F28: ='P & L'!F8/AVERAGE(BS!E34:F34) -> 2.5515739 | G28: ='P & L'!G8/AVERAGE(BS!F34:G34) -> 2.5857596 | H28: ='P & L'!H8/AVERAGE(BS!G34:H34) -> 2.609289 | I28: ='P & L'!I8/AVERAGE(BS!H34:I34) -> 2.5562751
B29: Fixed Asset Turnover Ratio | C29: 0 | D29: ='P & L'!D8/AVERAGE(SUM(BS!C10:C13),SUM(BS!D10:D13)) -> 3.4164256 | E29: ='P & L'!E8/AVERAGE(SUM(BS!D10:D13),SUM(BS!E10:E13)) -> 3.3992454 | F29: ='P & L'!F8/AVERAGE(SUM(BS!E10:E13),SUM(BS!F10:F13)) -> 3.8308318 | G29: ='P & L'!G8/AVERAGE(SUM(BS!F10:F13),SUM(BS!G10:G13)) -> 3.8608313 | H29: ='P & L'!H8/AVERAGE(SUM(BS!G10:G13),SUM(BS!H10:H13)) -> 3.7759382 | I29: ='P & L'!I8/AVERAGE(SUM(BS!H10:H13),SUM(BS!I10:I13)) -> 3.5775063
B31: Activity Ratios: | C31: 43921 | D31: =EOMONTH(C31,12) -> 44286 | E31: =EOMONTH(D31,12) -> 44651 | F31: =EOMONTH(E31,12) -> 45016 | G31: =EOMONTH(F31,12) -> 45382 | H31: =EOMONTH(G31,12) -> 45747 | I31: =EOMONTH(H31,12) -> 46112 | J31: Trend
B32: Receivable Days | C32: 0 | D32: 0.47720649 | E32: 0.65084579 | F32: 0.55126967 | G32: 0.82117909 | H32: 0.98435174 | I32: 0.80384525
B33: Inventory Days | C33: 0 | D33: 37.252421 | E33: 34.505175 | F33: 30.10843 | G33: 30.241088 | H33: 32.389249 | I33: 34.16821
B34: Payable days | C34: 0 | D34: 8.9815726 | E34: 8.0704087 | F34: 6.7548238 | G34: 7.3321288 | H34: 7.4211283 | I34: 7.5205582
B36: Solvency Ratios: | C36: 43921 | D36: =EOMONTH(C36,12) -> 44286 | E36: =EOMONTH(D36,12) -> 44651 | F36: =EOMONTH(E36,12) -> 45016 | G36: =EOMONTH(F36,12) -> 45382 | H36: =EOMONTH(G36,12) -> 45747 | I36: =EOMONTH(H36,12) -> 46112 | J36: Trend
B37: Debt To Asset Ratio | C37: 0 | D37: =SUM(AVERAGE(BS!C46:D46),AVERAGE(BS!C47:D47),AVERAGE(BS!C53:D53),AVERAGE(BS!C54:D54))/AVERAGE(BS!C34:D34) -> 0.026923624 | E37: =SUM(AVERAGE(BS!D46:E46),AVERAGE(BS!D47:E47),AVERAGE(BS!D53:E53),AVERAGE(BS!D54:E54))/AVERAGE(BS!D34:E34) -> 0.035720894 | F37: =SUM(AVERAGE(BS!E46:F46),AVERAGE(BS!E47:F47),AVERAGE(BS!E53:F53),AVERAGE(BS!E54:F54))/AVERAGE(BS!E34:F34) -> 0.038440772 | G37: =SUM(AVERAGE(BS!F46:G46),AVERAGE(BS!F47:G47),AVERAGE(BS!F53:G53),AVERAGE(BS!F54:G54))/AVERAGE(BS!F34:G34) -> 0.03146309 | H37: =SUM(AVERAGE(BS!G46:H46),AVERAGE(BS!G47:H47),AVERAGE(BS!G53:H53),AVERAGE(BS!G54:H54))/AVERAGE(BS!G34:H34) -> 0.031048746 | I37: =SUM(AVERAGE(BS!H46:I46),AVERAGE(BS!H47:I47),AVERAGE(BS!H53:I53),AVERAGE(BS!H54:I54))/AVERAGE(BS!H34:I34) -> 0.060277967
B38: Debt To Capital Ratio | C38: 0 | D38: =SUM(AVERAGE(BS!C46:D46),AVERAGE(BS!C47:D47),AVERAGE(BS!C53:D53),AVERAGE(BS!C54:D54))/SUM(AVERAGE(BS!C38:D38),AVERAGE(BS!C46:D46),AVERAGE(BS!C47:D47),AVERAGE(BS!C53:D53),AVERAGE(BS!C54:D54)) -> 0.34843463 | E38: =SUM(AVERAGE(BS!D46:E46),AVERAGE(BS!D47:E47),AVERAGE(BS!D53:E53),AVERAGE(BS!D54:E54))/SUM(AVERAGE(BS!D38:E38),AVERAGE(BS!D46:E46),AVERAGE(BS!D47:E47),AVERAGE(BS!D53:E53),AVERAGE(BS!D54:E54)) -> 0.44541189 | F38: =SUM(AVERAGE(BS!E46:F46),AVERAGE(BS!E47:F47),AVERAGE(BS!E53:F53),AVERAGE(BS!E54:F54))/SUM(AVERAGE(BS!E38:F38),AVERAGE(BS!E46:F46),AVERAGE(BS!E47:F47),AVERAGE(BS!E53:F53),AVERAGE(BS!E54:F54)) -> 0.49898911 | G38: =SUM(AVERAGE(BS!F46:G46),AVERAGE(BS!F47:G47),AVERAGE(BS!F53:G53),AVERAGE(BS!F54:G54))/SUM(AVERAGE(BS!F38:G38),AVERAGE(BS!F46:G46),AVERAGE(BS!F47:G47),AVERAGE(BS!F53:G53),AVERAGE(BS!F54:G54)) -> 0.48757185 | H38: =SUM(AVERAGE(BS!G46:H46),AVERAGE(BS!G47:H47),AVERAGE(BS!G53:H53),AVERAGE(BS!G54:H54))/SUM(AVERAGE(BS!G38:H38),AVERAGE(BS!G46:H46),AVERAGE(BS!G47:H47),AVERAGE(BS!G53:H53),AVERAGE(BS!G54:H54)) -> 0.52048193 | I38: =SUM(AVERAGE(BS!H46:I46),AVERAGE(BS!H47:I47),AVERAGE(BS!H53:I53),AVERAGE(BS!H54:I54))/SUM(AVERAGE(BS!H38:I38),AVERAGE(BS!H46:I46),AVERAGE(BS!H47:I47),AVERAGE(BS!H53:I53),AVERAGE(BS!H54:I54)) -> 0.71358938
B39: Debt To Equity Ratio | C39: 0 | D39: =SUM(AVERAGE(BS!C46:D46),AVERAGE(BS!C47:D47),AVERAGE(BS!C53:D53),AVERAGE(BS!C54:D54))/AVERAGE(BS!C42:D42) -> 0.02977995 | E39: =SUM(AVERAGE(BS!D46:E46),AVERAGE(BS!D47:E47),AVERAGE(BS!D53:E53),AVERAGE(BS!D54:E54))/AVERAGE(BS!D42:E42) -> 0.040232774 | F39: =SUM(AVERAGE(BS!E46:F46),AVERAGE(BS!E47:F47),AVERAGE(BS!E53:F53),AVERAGE(BS!E54:F54))/AVERAGE(BS!E42:F42) -> 0.04337851 | G39: =SUM(AVERAGE(BS!F46:G46),AVERAGE(BS!F47:G47),AVERAGE(BS!F53:G53),AVERAGE(BS!F54:G54))/AVERAGE(BS!F42:G42) -> 0.035541055 | H39: =SUM(AVERAGE(BS!G46:H46),AVERAGE(BS!G47:H47),AVERAGE(BS!G53:H53),AVERAGE(BS!G54:H54))/AVERAGE(BS!G42:H42) -> 0.035206824 | I39: =SUM(AVERAGE(BS!H46:I46),AVERAGE(BS!H47:I47),AVERAGE(BS!H53:I53),AVERAGE(BS!H54:I54))/AVERAGE(BS!H42:I42) -> 0.070727969
B40: Financial Leverage | C40: 0 | D40: =AVERAGE(BS!C34:D34)/AVERAGE(BS!C42:D42) -> 1.10609 | E40: =AVERAGE(BS!D34:E34)/AVERAGE(BS!D42:E42) -> 1.1263093 | F40: =AVERAGE(BS!E34:F34)/AVERAGE(BS!E42:F42) -> 1.1284505 | G40: =AVERAGE(BS!F34:G34)/AVERAGE(BS!F42:G42) -> 1.1296111 | H40: =AVERAGE(BS!G34:H34)/AVERAGE(BS!G42:H42) -> 1.133921 | I40: =AVERAGE(BS!H34:I34)/AVERAGE(BS!H42:I42) -> 1.1733635
B41: Interest Coverage Ratio | C41: ='P & L'!C20/-'P & L'!C22 -> 25.374711 | D41: ='P & L'!D20/-'P & L'!D22 -> 31.906122 | E41: ='P & L'!E20/-'P & L'!E22 -> 37.18944 | F41: ='P & L'!F20/-'P & L'!F22 -> 44.476487 | G41: ='P & L'!G20/-'P & L'!G22 -> 58.025288 | H41: ='P & L'!H20/-'P & L'!H22 -> 52.092297 | I41: ='P & L'!I20/-'P & L'!I22 -> 29.212038
B43: Valuation Ratios: | C43: 43921 | D43: =EOMONTH(C43,12) -> 44286 | E43: =EOMONTH(D43,12) -> 44651 | F43: =EOMONTH(E43,12) -> 45016 | G43: =EOMONTH(F43,12) -> 45382 | H43: =EOMONTH(G43,12) -> 45747 | I43: =EOMONTH(H43,12) -> 46112 | J43: Trend
B44: Basic EPS | C44: 20.71 | D44: 16.97 | E44: 23.04 | F44: 36.72 | G44: 38.99 | H44: 41.61 | I44: 45.65
B45: P/E Ratio | C45: =2218/C44 -> 107.09802 | D45: =2885/D44 -> 170.00589 | E45: =4013/E44 -> 174.17535 | F45: =3413.05/F44 -> 92.947985 | G45: =4570/G44 -> 117.20954 | H45: =4109.75/H44 -> 98.768325 | I45: =4075/I44 -> 89.266156
B46: Price To Cashflow Ratio | C46: =2218/('Cash flow statement'!C34/'P & L'!C35) -> 108.83252 | D46: =2885/('Cash flow statement'!D34/'P & L'!D35) -> 135.90107 | E46: =4013/('Cash flow statement'!E34/'P & L'!E35) -> 189.42105 | F46: =3413.05/('Cash flow statement'!F34/'P & L'!F35) -> 84.056227 | G46: =4570/('Cash flow statement'!G34/'P & L'!G35) -> 108.25468 | H46: =4109.75/('Cash flow statement'!H34/'P & L'!H35) -> 108.58233 | I46: =4075/('Cash flow statement'!I34/'P & L'!I35) -> 76.492777
B47: Price To Sales Ratio | C47: =2218/('P & L'!C8/'P & L'!C35) -> 5.6019197 | D47: =2885/('P & L'!D8/'P & L'!D35) -> 7.7406509 | E47: =4013/('P & L'!E8/'P & L'!E35) -> 8.3919718 | F47: =3413.05/('P & L'!F8/'P & L'!F35) -> 5.1608973 | G47: =4570/('P & L'!G8/'P & L'!G35) -> 5.8526654 | H47: =4109.75/('P & L'!H8/'P & L'!H35) -> 4.505455 | I47: =4075/('P & L'!I8/'P & L'!I35) -> 3.8532072
B48: Price To Book Value Ratio | C48: =2218/(BS!C42/'P & L'!C35) -> 12.573858 | D48: =2885/(BS!D42/'P & L'!D35) -> 15.338256 | E48: =4013/(BS!E42/'P & L'!E35) -> 19.005269 | F48: =3413.05/(BS!F42/'P & L'!F35) -> 13.750457 | G48: =4570/(BS!G42/'P & L'!G35) -> 15.897985 | H48: =4109.75/(BS!H42/'P & L'!H35) -> 12.481391 | I48: =4075/(BS!I42/'P & L'!I35) -> 10.840351
B49: Operating Cash Flow Per Share | C49: ='Cash flow statement'!C34/'P & L'!C35 -> 20.379938 | D49: ='Cash flow statement'!D34/'P & L'!D35 -> 21.228677 | E49: ='Cash flow statement'!E34/'P & L'!E35 -> 21.185607 | F49: ='Cash flow statement'!F34/'P & L'!F35 -> 40.604369 | G49: ='Cash flow statement'!G34/'P & L'!G35 -> 42.215266 | H49: ='Cash flow statement'!H34/'P & L'!H35 -> 37.84916 | I49: ='Cash flow statement'!I34/'P & L'!I35 -> 53.273004
B50: EBITDA / Outstanding Share | C50: ='P & L'!C16/'P & L'!C35 -> 33.882876 | D50: ='P & L'!D16/'P & L'!D35 -> 26.908276 | E50: ='P & L'!E16/'P & L'!E35 -> 38.57051 | F50: ='P & L'!F16/'P & L'!F35 -> 56.146064 | G50: ='P & L'!G16/'P & L'!G35 -> 63.092438 | H50: ='P & L'!H16/'P & L'!H35 -> 68.958075 | I50: ='P & L'!I16/'P & L'!I35 -> 79.701746
B52: Du-pont Anlysis: | C52: 43921 | D52: =EOMONTH(C52,12) -> 44286 | E52: =EOMONTH(D52,12) -> 44651 | F52: =EOMONTH(E52,12) -> 45016 | G52: =EOMONTH(F52,12) -> 45382 | H52: =EOMONTH(G52,12) -> 45747 | I52: =EOMONTH(H52,12) -> 46112 | J52: Trend
B53: Net Profit Margin | C53: 0 | D53: =D10 -> 0.045538138 | E53: =E10 -> 0.048178816 | F53: =F10 -> 0.055517377 | G53: =G10 -> 0.04992456 | H53: =H10 -> 0.045612179 | I53: =I10 -> 0.043164314
B54: Asset Turnover Ratio | C54: 0 | D54: =D28 -> 1.8764702 | E54: =E28 -> 2.1268622 | F54: =F28 -> 2.5515739 | G54: =G28 -> 2.5857596 | H54: =H28 -> 2.609289 | I54: =I28 -> 2.5562751
B55: Financial Leverage | C55: 0 | D55: =D40 -> 1.10609 | E55: =E40 -> 1.1263093 | F55: =F40 -> 1.1284505 | G55: =G40 -> 1.1296111 | H55: =H40 -> 1.133921 | I55: =I40 -> 1.1733635
B56: ROE | C56: 0 | D56: =D53*D54*D55 -> 0.09451645 | E56: =E53*E54*E55 -> 0.11541257 | F56: =F53*F54*F55 -> 0.15985256 | G56: =G53*G54*G55 -> 0.14582478 | H56: =H53*H54*H55 -> 0.13495401 | I56: =I53*I54*I55 -> 0.12946877
B58: Performance & Coverage Ratio: | C58: 43921 | D58: =EOMONTH(C58,12) -> 44286 | E58: =EOMONTH(D58,12) -> 44651 | F58: =EOMONTH(E58,12) -> 45016 | G58: =EOMONTH(F58,12) -> 45382 | H58: =EOMONTH(G58,12) -> 45747 | I58: =EOMONTH(H58,12) -> 46112 | J58: Trend
B59: Cash Flow Return On Revenue | C59: ='Cash flow statement'!C34/'P & L'!C8 -> 0.051472847 | D59: ='Cash flow statement'!D34/'P & L'!D8 -> 0.056957983 | E59: ='Cash flow statement'!E34/'P & L'!E8 -> 0.044303268 | F59: ='Cash flow statement'!F34/'P & L'!F8 -> 0.061398156 | G59: ='Cash flow statement'!G34/'P & L'!G8 -> 0.054063856 | H59: ='Cash flow statement'!H34/'P & L'!H8 -> 0.041493445 | I59: ='Cash flow statement'!I34/'P & L'!I8 -> 0.050373478
B60: Cash Flow Return On Assests | C60: 0 | D60: ='Cash flow statement'!D34/AVERAGE(BS!C34:D34) -> 0.10687996 | E60: ='Cash flow statement'!E34/AVERAGE(BS!D34:E34) -> 0.094226947 | F60: ='Cash flow statement'!F34/AVERAGE(BS!E34:F34) -> 0.15666193 | G60: ='Cash flow statement'!G34/AVERAGE(BS!F34:G34) -> 0.13979613 | H60: ='Cash flow statement'!H34/AVERAGE(BS!G34:H34) -> 0.10826839 | I60: ='Cash flow statement'!I34/AVERAGE(BS!H34:I34) -> 0.12876846
B61: Cash Flow Return On Equity | C61: 0 | D61: ='Cash flow statement'!D34/AVERAGE(BS!C42:D42) -> 0.11821885 | E61: ='Cash flow statement'!E34/AVERAGE(BS!D42:E42) -> 0.10612868 | F61: ='Cash flow statement'!F34/AVERAGE(BS!E42:F42) -> 0.17678524 | G61: ='Cash flow statement'!G34/AVERAGE(BS!F42:G42) -> 0.15791526 | H61: ='Cash flow statement'!H34/AVERAGE(BS!G42:H42) -> 0.1227678 | I61: ='Cash flow statement'!I34/AVERAGE(BS!H42:I42) -> 0.15109222
B62: Cash Flow Return On Profit | C62: ='Cash flow statement'!C34/'P & L'!C32 -> 0.98398131 | D62: ='Cash flow statement'!D34/'P & L'!D32 -> 1.2507754 | E62: ='Cash flow statement'!E34/'P & L'!E32 -> 0.9195591 | F62: ='Cash flow statement'!F34/'P & L'!F32 -> 1.1059268 | G62: ='Cash flow statement'!G34/'P & L'!G32 -> 1.082911 | H62: ='Cash flow statement'!H34/'P & L'!H32 -> 0.90970101 | I62: ='Cash flow statement'!I34/'P & L'!I32 -> 1.1670168
B63: Debt Coverage Ratio | C63: 0 | D63: ='Cash flow statement'!D34/SUM(AVERAGE(BS!C46:D46),AVERAGE(BS!C47:D47),AVERAGE(BS!C53:D53),AVERAGE(BS!C54:D54)) -> 3.9697464 | E63: ='Cash flow statement'!E34/SUM(AVERAGE(BS!D46:E46),AVERAGE(BS!D47:E47),AVERAGE(BS!D53:E53),AVERAGE(BS!D54:E54)) -> 2.6378664 | F63: ='Cash flow statement'!F34/SUM(AVERAGE(BS!E46:F46),AVERAGE(BS!E47:F47),AVERAGE(BS!E53:F53),AVERAGE(BS!E54:F54)) -> 4.0754106 | G63: ='Cash flow statement'!G34/SUM(AVERAGE(BS!F46:G46),AVERAGE(BS!F47:G47),AVERAGE(BS!F53:G53),AVERAGE(BS!F54:G54)) -> 4.4431787 | H63: ='Cash flow statement'!H34/SUM(AVERAGE(BS!G46:H46),AVERAGE(BS!G47:H47),AVERAGE(BS!G53:H53),AVERAGE(BS!G54:H54)) -> 3.4870455 | I63: ='Cash flow statement'!I34/SUM(AVERAGE(BS!H46:I46),AVERAGE(BS!H47:I47),AVERAGE(BS!H53:I53),AVERAGE(BS!H54:I54)) -> 2.1362443
B64: Interest Coverage Ratio | C64: ='Cash flow statement'!C34/-SUM('Cash flow statement'!C60:C61) -> 18.778642 | D64: ='Cash flow statement'!D34/-SUM('Cash flow statement'!D60:D61) -> 31.539908 | E64: ='Cash flow statement'!E34/-SUM('Cash flow statement'!E60:E61) -> 25.513107 | F64: ='Cash flow statement'!F34/-SUM('Cash flow statement'!F60:F61) -> 39.018988 | G64: ='Cash flow statement'!G34/-SUM('Cash flow statement'!G60:G61) -> 47.236195 | H64: ='Cash flow statement'!H34/-SUM('Cash flow statement'!H60:H61) -> 35.463931 | I64: ='Cash flow statement'!I34/-SUM('Cash flow statement'!I60:I61) -> 24.642735
B65: Reinvestment Ratio | C65: =-'Cash flow statement'!C34/'Cash flow statement'!C45 -> 0.27491109 | D65: =-'Cash flow statement'!D34/'Cash flow statement'!D45 -> 1.2388649 | E65: =-'Cash flow statement'!E34/'Cash flow statement'!E45 -> 1.064258 | F65: =-'Cash flow statement'!F34/'Cash flow statement'!F45 -> 1.137119 | G65: =-'Cash flow statement'!G34/'Cash flow statement'!G45 -> 1.1124733 | H65: =-'Cash flow statement'!H34/'Cash flow statement'!H45 -> 1.1270575 | I65: =-'Cash flow statement'!I34/'Cash flow statement'!I45 -> 0.82404872
B66: Debt Payment | C66: =-'Cash flow statement'!C34/SUM('Cash flow statement'!C58:C60) -> 4.2705498 | D66: =-'Cash flow statement'!D34/SUM('Cash flow statement'!D58:D60) -> 10.135918 | E66: =-'Cash flow statement'!E34/SUM('Cash flow statement'!E58:E60) -> 7.7237168 | F66: =-'Cash flow statement'!F34/SUM('Cash flow statement'!F58:F60) -> 11.975369 | G66: =-'Cash flow statement'!G34/SUM('Cash flow statement'!G58:G60) -> 12.408894 | H66: =-'Cash flow statement'!H34/SUM('Cash flow statement'!H58:H60) -> 9.5783231 | I66: =-'Cash flow statement'!I34/SUM('Cash flow statement'!I58:I60) -> 11.031088

Sheet P & L
B2: Income Statement - Avenue Supermarts Limited
B5: Sensitiviy Analysis: | C5: Growth rate: | D5: Base
B7: (In Millions) | C7: 43921 | D7: =EOMONTH(C7,12) -> 44286 | E7: =EOMONTH(D7,12) -> 44651 | F7: =EOMONTH(E7,12) -> 45016 | G7: =EOMONTH(F7,12) -> 45382 | H7: =EOMONTH(G7,12) -> 45747 | I7: =EOMONTH(H7,12) -> 46112 | K7: =EOMONTH(I7,12) -> 46477 | L7: =EOMONTH(K7,12) -> 46843 | M7: =EOMONTH(L7,12) -> 47208 | N7: =EOMONTH(M7,12) -> 47573 | O7: =EOMONTH(N7,12) -> 47938 | P7: =EOMONTH(O7,12) -> 48304 | Q7: =EOMONTH(P7,12) -> 48669 | R7: =EOMONTH(Q7,12) -> 49034 | S7: =EOMONTH(R7,12) -> 49399 | T7: =EOMONTH(S7,12) -> 49765
B8: Revenue from operations | C8: ='Revenue driver'!C6 -> 248702 | D8: ='Revenue driver'!D6 -> 241430.6 | E8: ='Revenue driver'!E6 -> 309762.7 | F8: ='Revenue driver'!F6 -> 428395.6 | G8: ='Revenue driver'!G6 -> 507888.3 | H8: 593580.5 | I8: 688207.4 | K8: ='Revenue driver'!K6 -> 914969.92 | L8: ='Revenue driver'!L6 -> 1167507.9 | M8: ='Revenue driver'!M6 -> 1467607.8 | N8: ='Revenue driver'!N6 -> 1812809.9 | O8: ='Revenue driver'!O6 -> 2203289.8 | P8: ='Revenue driver'!P6 -> 2637618 | Q8: ='Revenue driver'!Q6 -> 3112542.8 | R8: ='Revenue driver'!R6 -> 3639457.9 | ... T8: ='Revenue driver'!T6 -> 4851117.8
B9: Purchase of stock-in-trade | C9: -214416.8 | D9: -208555.6 | E9: -268917.7 | F9: -368847.7 | G9: -439583.1 | H9: -516687.6 | I9: -593159.9 | K9: 0 | L9: 0 | M9: 0 | N9: 0 | O9: 0 | P9: 0 | Q9: 0 | R9: 0 | S9: 0 | T9: 0
B10: Changes in stock-in-trade | C10: 3387.5 | D10: 3008.8 | E10: 4943.8 | F10: 5008.2 | G10: 6837.7 | H10: 11170.6 | I10: 8562.6 | K10: 0 | L10: 0 | M10: 0 | N10: 0 | O10: 0 | P10: 0 | Q10: 0 | R10: 0 | S10: 0 | T10: 0
B11: Total COGS | C11: =C10+C9 -> -211029.3 | D11: =D10+D9 -> -205546.8 | E11: =E10+E9 -> -263973.9 | F11: =F10+F9 -> -363839.5 | G11: =G10+G9 -> -432745.4 | H11: =H10+H9 -> -505517 | I11: =I10+I9 -> -584597.3 | K11: =-(K8-K12) -> -777724.43 | L11: =-(L8-L12) -> -992381.71 | M11: =-(M8-M12) -> -1247466.6 | N11: =-(N8-N12) -> -1540888.4 | O11: =-(O8-O12) -> -1872796.3 | P11: =-(P8-P12) -> -2241975.3 | Q11: =-(Q8-Q12) -> -2645661.4 | R11: =-(R8-R12) -> -3093539.2 | ... T11: =-(T8-T12) -> -4123450.1
B12: Gross profit | C12: =C11+C8 -> 37672.7 | D12: =D11+D8 -> 35883.8 | E12: =E11+E8 -> 45788.8 | F12: =F11+F8 -> 64556.1 | G12: =G11+G8 -> 75142.9 | H12: =H11+H8 -> 88063.5 | I12: =I11+I8 -> 103610.1 | K12: =K13*K8 -> 137245.49 | L12: =L13*L8 -> 175126.18 | M12: =M13*M8 -> 220141.17 | N12: =N13*N8 -> 271921.48 | O12: =O13*O8 -> 330493.46 | P12: =P13*P8 -> 395642.7 | Q12: =Q13*Q8 -> 466881.42 | R12: =R13*R8 -> 545918.68 | ... T12: =T13*T8 -> 727667.67
B13: Gross profit margin | C13: =C12/C$8 -> 0.15147727 | D13: =D12/D$8 -> 0.14862988 | E13: =E12/E$8 -> 0.14781896 | F13: =F12/F$8 -> 0.15069272 | G13: =G12/G$8 -> 0.14795163 | H13: =H12/H$8 -> 0.14835983 | I13: =I12/I$8 -> 0.15055069 | K13: 0.15 | L13: 0.15 | M13: 0.15 | N13: 0.15 | O13: 0.15 | P13: 0.15 | Q13: 0.15 | R13: 0.15 | S13: 0.15 | T13: 0.15
B14: Employee benefits expenses | C14: -4561 | D14: -5365.7 | E14: -6162.1 | F14: -7469.7 | G14: -9061.2 | H14: -11659 | I14: -15414.8 | K14: =-K17*K8 -> -18008.5 | L14: =-L17*L8 -> -22978.97 | M14: =-M17*M8 -> -28885.556 | N14: =-N17*N8 -> -35679.847 | O14: =-O17*O8 -> -43365.299 | P14: =-P17*P8 -> -51913.777 | Q14: =-Q17*Q8 -> -61261.279 | R14: =-R17*R8 -> -71632.057 | ... T14: =-T17*T8 -> -95480.03
B15: Other expenses | C15: -11828.6 | D15: -13087.6 | E15: -14641.7 | F15: -20716.1 | G15: -25044 | H15: -31531.2 | I15: -36329.4 | K15: =-(K12+K14-K16) -> -41464.545 | L15: =-(L12+L14-L16) -> -52909.044 | M15: =-(M12+M14-M16) -> -66508.949 | N15: =-(N12+N14-N16) -> -82152.795 | O15: =-(O12+O14-O16) -> -99848.535 | P15: =-(P12+P14-P16) -> -119531.39 | Q15: =-(Q12+Q14-Q16) -> -141054 | R15: =-(R12+R14-R16) -> -164932.71 | ... T15: =-(T12+T14-T16) -> -219842.63
B16: EBITDA | C16: =C12+C14+C15 -> 21283.1 | D16: =D12+D14+D15 -> 17430.5 | E16: =E12+E14+E15 -> 24985 | F16: =F12+F14+F15 -> 36370.3 | G16: =G12+G14+G15 -> 41037.7 | H16: =H12+H14+H15 -> 44873.3 | I16: =I12+I14+I15 -> 51865.9 | K16: =K18*K8 -> 77772.443 | L16: =L18*L8 -> 99238.171 | M16: =M18*M8 -> 124746.66 | N16: =N18*N8 -> 154088.84 | O16: =O18*O8 -> 187279.63 | P16: =P18*P8 -> 224197.53 | Q16: =Q18*Q8 -> 264566.14 | R16: =R18*R8 -> 309353.92 | ... T16: =T18*T8 -> 412345.01
B17: Employee benefits expenses % | C17: =-C14/C8 -> 0.018339217 | D17: =-D14/D8 -> 0.022224606 | E17: =-E14/E8 -> 0.01989297 | F17: =-F14/F8 -> 0.017436454 | G17: =-G14/G8 -> 0.017840931 | H17: =-H14/H8 -> 0.019641818 | I17: =-I14/I8 -> 0.02239848 | K17: =AVERAGE($C$17:$I$17) -> 0.019682068 | L17: =AVERAGE($C$17:$I$17) -> 0.019682068 | M17: =AVERAGE($C$17:$I$17) -> 0.019682068 | N17: =AVERAGE($C$17:$I$17) -> 0.019682068 | O17: =AVERAGE($C$17:$I$17) -> 0.019682068 | P17: =AVERAGE($C$17:$I$17) -> 0.019682068 | Q17: =AVERAGE($C$17:$I$17) -> 0.019682068 | R17: =AVERAGE($C$17:$I$17) -> 0.019682068 | ... T17: =AVERAGE($C$17:$I$17) -> 0.019682068
B18: EBITDA margin | C18: =C16/C$8 -> 0.085576714 | D18: =D16/D$8 -> 0.072196731 | E18: =E16/E$8 -> 0.080658517 | F18: =F16/F$8 -> 0.084898865 | G18: =G16/G$8 -> 0.080800641 | H18: =H16/H$8 -> 0.075597665 | I18: =I16/I$8 -> 0.075363764 | K18: 0.085 | L18: 0.085 | M18: 0.085 | N18: 0.085 | O18: 0.085 | P18: 0.085 | Q18: 0.085 | R18: 0.085 | S18: 0.085 | T18: 0.085
B19: Depreciation and Amortization | C19: -3744.1 | D19: -4141.6 | E19: -4980.8 | F19: -6388.7 | G19: -7307.6 | H19: -8695.2 | I19: -10370.2 | K19: =Schedules!K9+Schedules!K20 -> -12200.967 | L19: =Schedules!L9+Schedules!L20 -> -13155.015 | M19: =Schedules!M9+Schedules!M20 -> -14580.023 | N19: =Schedules!N9+Schedules!N20 -> -16109.765 | O19: =Schedules!O9+Schedules!O20 -> -17710.104 | P19: =Schedules!P9+Schedules!P20 -> -19381.443 | Q19: =Schedules!Q9+Schedules!Q20 -> -21124.15 | R19: =Schedules!R9+Schedules!R20 -> -22938.512 | ... T19: =Schedules!T9+Schedules!T20 -> -26782.808
B20: EBIT | C20: =C19+C16 -> 17539 | D20: =D19+D16 -> 13288.9 | E20: =E19+E16 -> 20004.2 | F20: =F19+F16 -> 29981.6 | G20: =G19+G16 -> 33730.1 | H20: =H19+H16 -> 36178.1 | I20: =I19+I16 -> 41495.7 | K20: =K19+K16 -> 65571.476 | L20: =L19+L16 -> 86083.156 | M20: =M19+M16 -> 110166.64 | N20: =N19+N16 -> 137979.08 | O20: =O19+O16 -> 169569.53 | P20: =P19+P16 -> 204816.09 | Q20: =Q19+Q16 -> 243441.99 | R20: =R19+R16 -> 286415.41 | ... T20: =T19+T16 -> 385562.21
B21: EBIT margin | C21: =C20/C$8 -> 0.070522151 | D21: =D20/D$8 -> 0.055042319 | E21: =E20/E$8 -> 0.064579112 | F21: =F20/F$8 -> 0.069985779 | G21: =G20/G$8 -> 0.066412438 | H21: =H20/H$8 -> 0.060948936 | I21: =I20/I$8 -> 0.060295341 | K21: =K20/K8 -> 0.071665172 | L21: =L20/L8 -> 0.073732397 | M21: =M20/M8 -> 0.07506545 | N21: =N20/N8 -> 0.076113373 | O21: =O20/O8 -> 0.076961973 | P21: =P20/P8 -> 0.077651914 | Q21: =Q20/Q8 -> 0.078213218 | R21: =R20/R8 -> 0.078697272 | ... T21: =T20/T8 -> 0.079479044
B22: Finance Costs | C22: -691.2 | D22: -416.5 | E22: -537.9 | F22: -674.1 | G22: -581.3 | H22: -694.5 | I22: -1420.5 | K22: =-Schedules!K68 -> -1780.3735 | L22: =-Schedules!L68 -> -1821.2098 | M22: =-Schedules!M68 -> -1851.5637 | N22: =-Schedules!N68 -> -1874.126 | O22: =-Schedules!O68 -> -1890.8966 | P22: =-Schedules!P68 -> -1903.3624 | Q22: =-Schedules!Q68 -> -1912.7273 | R22: =-Schedules!R68 -> -1919.7874 | ... T22: =-Schedules!T68 -> -1929.2079
B23: Other Incomes | C23: 599.9 | D23: 1962.1 | E23: 1174.9 | F23: 1293.4 | G23: 1464.5 | H23: 1243.1 | I23: 741 | K23: =K8*K25 -> 3059.3497 | L23: =L8*L25 -> 3903.7512 | M23: =M8*M25 -> 4907.1836 | N23: =N8*N25 -> 6061.4227 | O23: =O8*O25 -> 7367.0552 | P23: =P8*P25 -> 8819.3018 | Q23: =Q8*Q25 -> 10407.29 | R23: =R8*R25 -> 12169.115 | ... T23: =T8*T25 -> 16220.496
B24: EBT | C24: =C20+C22+C23 -> 17447.7 | D24: =D20+D22+D23 -> 14834.5 | E24: =E20+E22+E23 -> 20641.2 | F24: =F20+F22+F23 -> 30600.9 | G24: =G20+G22+G23 -> 34613.3 | H24: =H20+H22+H23 -> 36726.7 | I24: =I20+I22+I23 -> 40816.2 | K24: =K23+K22+K20 -> 66850.452 | L24: =L23+L22+L20 -> 88165.697 | M24: =M23+M22+M20 -> 113222.26 | N24: =N23+N22+N20 -> 142166.37 | O24: =O23+O22+O20 -> 175045.68 | P24: =P23+P22+P20 -> 211732.03 | Q24: =Q23+Q22+Q20 -> 251936.55 | R24: =R23+R22+R20 -> 296664.74 | ... T24: =T23+T22+T20 -> 399853.49
B25: Other income as a % of revenue | C25: =C23/C8 -> 0.0024121237 | D25: =D23/D8 -> 0.0081269731 | E25: =E23/E8 -> 0.0037929034 | F25: =F23/F8 -> 0.003019172 | G25: =G23/G8 -> 0.002883508 | H25: =H23/H8 -> 0.00209424 | I25: =I23/I8 -> 0.0010767103 | K25: =AVERAGE($C$25:$I$25) -> 0.0033436615 | L25: =AVERAGE($C$25:$I$25) -> 0.0033436615 | M25: =AVERAGE($C$25:$I$25) -> 0.0033436615 | N25: =AVERAGE($C$25:$I$25) -> 0.0033436615 | O25: =AVERAGE($C$25:$I$25) -> 0.0033436615 | P25: =AVERAGE($C$25:$I$25) -> 0.0033436615 | Q25: =AVERAGE($C$25:$I$25) -> 0.0033436615 | R25: =AVERAGE($C$25:$I$25) -> 0.0033436615 | ... T25: =AVERAGE($C$25:$I$25) -> 0.0033436615
B26: EBT margin | C26: =C24/C$8 -> 0.070155045 | D26: =D24/D$8 -> 0.061444158 | E26: =E24/E$8 -> 0.066635525 | F26: =F24/F$8 -> 0.071431406 | G26: =G24/G$8 -> 0.068151403 | H26: =H24/H$8 -> 0.061873158 | I26: =I24/I$8 -> 0.059307993 | K26: =K24/K8 -> 0.073063006 | L26: =L24/L8 -> 0.075516146 | M26: =M24/M8 -> 0.077147491 | N26: =N24/N8 -> 0.078423211 | O26: =O24/O8 -> 0.079447419 | P26: =P24/P8 -> 0.080273954 | Q26: =Q24/Q8 -> 0.080942357 | R26: =R24/R8 -> 0.081513441 | ... T26: =T24/T8 -> 0.082425022
B27: Current tax | C27: -4597.4 | D27: -3946.9 | E27: -5463.3 | F27: -8077 | G27: -9130.9 | H27: -9834.7 | I27: -11012.3 | K27: 0 | L27: 0 | M27: 0 | N27: 0 | O27: 0 | P27: 0 | Q27: 0 | R27: 0 | S27: 0 | T27: 0
B28: Deferred tax charge/(credit) | C28: 159.7 | D28: -31.7 | E28: -121 | F28: -128.2 | G28: -120.2 | H28: -177.6 | I28: -101.6 | K28: 0 | L28: 0 | M28: 0 | N28: 0 | O28: 0 | P28: 0 | Q28: 0 | R28: 0 | S28: 0 | T28: 0
B29: Adjustment of tax related to earlier years | C29: -0.2 | D29: 138.4 | E29: -132.9 | F29: 1387.7 | G29: -6.1 | H29: 360.1 | I29: 3.7 | K29: 0 | L29: 0 | M29: 0 | N29: 0 | O29: 0 | P29: 0 | Q29: 0 | R29: 0 | S29: 0 | T29: 0
B30: Total Tax | C30: =SUM(C27:C29) -> -4437.9 | D30: =SUM(D27:D29) -> -3840.2 | E30: =SUM(E27:E29) -> -5717.2 | F30: =SUM(F27:F29) -> -6817.5 | G30: =SUM(G27:G29) -> -9257.2 | H30: =SUM(H27:H29) -> -9652.2 | I30: =SUM(I27:I29) -> -11110.2 | K30: =K31*K24 -> -18049.622 | L30: =L31*L24 -> -23804.738 | M30: =M31*M24 -> -30570.009 | N30: =N31*N24 -> -38384.92 | O30: =O31*O24 -> -47262.335 | P30: =P31*P24 -> -57167.647 | Q30: =Q31*Q24 -> -68022.869 | R30: =R31*R24 -> -80099.479 | ... T30: =T31*T24 -> -107960.44
B31: Effective Tax rate | C31: =C30/C24 -> -0.25435444 | D31: =D30/D24 -> -0.25886953 | E31: =E30/E24 -> -0.27698002 | F31: =F30/F24 -> -0.22278757 | G31: =G30/G24 -> -0.26744633 | H31: =H30/H24 -> -0.26281152 | I31: =I30/I24 -> -0.27220074 | K31: -0.27 | L31: -0.27 | M31: -0.27 | N31: -0.27 | O31: -0.27 | P31: -0.27 | Q31: -0.27 | R31: -0.27 | S31: -0.27 | T31: -0.27
B32: PAT | C32: =C30+C24 -> 13009.8 | D32: =D30+D24 -> 10994.3 | E32: =E30+E24 -> 14924 | F32: =F30+F24 -> 23783.4 | G32: =G30+G24 -> 25356.1 | H32: =H30+H24 -> 27074.5 | I32: =I30+I24 -> 29706 | K32: =K30+K24 -> 48800.83 | L32: =L30+L24 -> 64360.959 | M32: =M30+M24 -> 82652.248 | N32: =N30+N24 -> 103781.45 | O32: =O30+O24 -> 127783.35 | P32: =P30+P24 -> 154564.38 | Q32: =Q30+Q24 -> 183913.68 | R32: =R30+R24 -> 216565.26 | ... T32: =T30+T24 -> 291893.05
B33: Net profit margin | C33: =C32/C$8 -> 0.052310798 | D33: =D32/D$8 -> 0.045538138 | E33: =E32/E$8 -> 0.048178816 | F33: =F32/F$8 -> 0.055517377 | G33: =G32/G$8 -> 0.04992456 | H33: =H32/H$8 -> 0.045612179 | I33: =I32/I$8 -> 0.043164314 | K33: =K32/K$8 -> 0.053335994 | L33: =L32/L$8 -> 0.055126787 | M33: =M32/M$8 -> 0.056317668 | N33: =N32/N$8 -> 0.057248944 | O33: =O32/O$8 -> 0.057996616 | P33: =P32/P$8 -> 0.058599987 | Q33: =Q32/Q$8 -> 0.059087921 | R33: =R32/R$8 -> 0.059504812 | ... T33: =T32/T$8 -> 0.060170266
B35: Shares outstanding for basic EPS | C35: =628137345/10^6 -> 628.13734 | D35: =647774691/10^6 -> 647.77469 | E35: =647774691/10^6 -> 647.77469 | F35: =647780053/10^6 -> 647.78005 | G35: =650437695/10^6 -> 650.43769 | H35: =650733068/10^6 -> 650.73307 | I35: =650749863/10^6 -> 650.74986 | K35: =I35 -> 650.74986 | L35: =K35 -> 650.74986 | M35: =L35 -> 650.74986 | N35: =M35 -> 650.74986 | O35: =N35 -> 650.74986 | P35: =O35 -> 650.74986 | Q35: =P35 -> 650.74986 | R35: =Q35 -> 650.74986 | S35: =R35 -> 650.74986 | T35: =S35 -> 650.74986
B36: Basic EPS | C36: 20.71 | D36: 16.97 | E36: 23.04 | F36: 36.72 | G36: 38.99 | H36: 41.61 | I36: 45.65 | K36: =K32/K35 -> 74.991687 | L36: =L32/L35 -> 98.902762 | M36: =M32/M35 -> 127.01078 | N36: =N32/N35 -> 159.47979 | O36: =O32/O35 -> 196.36324 | P36: =P32/P35 -> 237.51734 | Q36: =Q32/Q35 -> 282.61809 | R36: =R32/R35 -> 332.7934 | ... T36: =T32/T35 -> 448.54877
B37: Shares outstanding for dilutive EPS | C37: =632984975/10^6 -> 632.98497 | D37: =652593148/10^6 -> 652.59315 | E37: =652893287/10^6 -> 652.89329 | F37: =651758267/10^6 -> 651.75827 | G37: =651536951/10^6 -> 651.53695 | H37: =652318596/10^6 -> 652.3186 | I37: =651005781/10^6 -> 651.00578 | K37: =I37 -> 651.00578 | L37: =K37 -> 651.00578 | M37: =L37 -> 651.00578 | N37: =M37 -> 651.00578 | O37: =N37 -> 651.00578 | P37: =O37 -> 651.00578 | Q37: =P37 -> 651.00578 | R37: =Q37 -> 651.00578 | S37: =R37 -> 651.00578 | T37: =S37 -> 651.00578
B38: Diluted EPS | C38: 20.55 | D38: 16.85 | E38: 22.86 | F38: 36.49 | G38: 38.93 | H38: 41.5 | I38: 45.63 | K38: =K32/K37 -> 74.962207 | L38: =L32/L37 -> 98.863883 | M38: =M32/M37 -> 126.96085 | N38: =N32/N37 -> 159.4171 | O38: =O32/O37 -> 196.28604 | P38: =P32/P37 -> 237.42397 | Q38: =Q32/Q37 -> 282.50699 | R38: =R32/R37 -> 332.66257 | ... T38: =T32/T37 -> 448.37244

Sheet BS
B2: Balance Sheet- Avenue Supermarts Limited
B5: Sensitiviy Analysis: | C5: Transfer: | D5: Average
B7: (In Millions) | C7: 43921 | D7: =EOMONTH(C7,12) -> 44286 | E7: =EOMONTH(D7,12) -> 44651 | F7: =EOMONTH(E7,12) -> 45016 | G7: =EOMONTH(F7,12) -> 45382 | H7: =EOMONTH(G7,12) -> 45747 | I7: =EOMONTH(H7,12) -> 46112 | K7: =EOMONTH(I7,12) -> 46477 | L7: =EOMONTH(K7,12) -> 46843 | M7: =EOMONTH(L7,12) -> 47208 | N7: =EOMONTH(M7,12) -> 47573 | O7: =EOMONTH(N7,12) -> 47938 | P7: =EOMONTH(O7,12) -> 48304 | Q7: =EOMONTH(P7,12) -> 48669 | R7: =EOMONTH(Q7,12) -> 49034 | S7: =EOMONTH(R7,12) -> 49399 | T7: =EOMONTH(S7,12) -> 49765
B8: Assets
B9: Non-current assets
B10: Property, plant and equipment | C10: 51073.6 | D10: 59385 | E10: 77704.6 | F10: 97256.1 | G10: 117591.9 | H10: 143498.3 | I10: 175869.5 | K10: =Schedules!K11 -> 183070.72 | L10: =Schedules!L11 -> 206338.1 | M10: =Schedules!M11 -> 232681.76 | N10: =Schedules!N11 -> 260719.64 | O10: =Schedules!O11 -> 290423.6 | P10: =Schedules!P11 -> 321767.72 | Q10: =Schedules!Q11 -> 354728.22 | R10: =Schedules!R11 -> 389283.37 | ... T10: =Schedules!T11 -> 463100.36
B11: Capital work-in-progress | C11: 3644 | D11: 10195.9 | E11: 11293.4 | F11: 8291.6 | G11: 9352.2 | H11: 10993.5 | I11: 12999.6 | K11: =Schedules!K29 -> 29094.783 | L11: =Schedules!L29 -> 30842.567 | M11: =Schedules!M29 -> 30741.984 | N11: =Schedules!N29 -> 30052.781 | O11: =Schedules!O29 -> 28716.946 | P11: =Schedules!P29 -> 26675.617 | Q11: =Schedules!Q29 -> 23869.065 | R11: =Schedules!R29 -> 20236.692 | ... T11: =Schedules!T29 -> 10247.639
B12: Right-of-use assets | C12: 7173.3 | D12: 9602.4 | E12: 13886.5 | F12: 15048.8 | G12: 15391 | H12: 17417.3 | I12: 23814.1 | K12: =Schedules!K22 -> 25316.728 | L12: =Schedules!L22 -> 26646.555 | M12: =Schedules!M22 -> 27823.451 | N12: =Schedules!N22 -> 28865.004 | O12: =Schedules!O22 -> 29786.779 | P12: =Schedules!P22 -> 30602.549 | Q12: =Schedules!Q22 -> 31325.448 | R12: =Schedules!R22 -> 31966.157 | ... T12: =Schedules!T22 -> 33037.722
B13: Investment properties | C13: 165.3 | D13: 95.7 | E13: 90.3 | F13: 85.4 | G13: 80.9 | H13: 76.5 | I13: 72.6 | K13: =I13 -> 72.6 | L13: =K13 -> 72.6 | M13: =L13 -> 72.6 | N13: =M13 -> 72.6 | O13: =N13 -> 72.6 | P13: =O13 -> 72.6 | Q13: =P13 -> 72.6 | R13: =Q13 -> 72.6 | S13: =R13 -> 72.6 | T13: =S13 -> 72.6
B14: Goodwill | C14: 782.7 | D14: 782.7 | E14: 782.7 | F14: 782.7 | G14: 782.7 | H14: 782.7 | I14: 782.7 | K14: =I14 -> 782.7 | L14: =K14 -> 782.7 | M14: =L14 -> 782.7 | N14: =M14 -> 782.7 | O14: =N14 -> 782.7 | P14: =O14 -> 782.7 | Q14: =P14 -> 782.7 | R14: =Q14 -> 782.7 | S14: =R14 -> 782.7 | T14: =S14 -> 782.7
B15: Intangible asset | C15: 285.4 | D15: 222.2 | E15: 136.1 | F15: 231.8 | G15: 303.5 | H15: 289.8 | I15: 364.2 | K15: =I15 -> 364.2 | L15: =K15 -> 364.2 | M15: =L15 -> 364.2 | N15: =M15 -> 364.2 | O15: =N15 -> 364.2 | P15: =O15 -> 364.2 | Q15: =P15 -> 364.2 | R15: =Q15 -> 364.2 | S15: =R15 -> 364.2 | T15: =S15 -> 364.2
B16: Financial assets:
B17: a) Investments | C17: 0 | D17: 0 | E17: 0.1 | F17: 0.1 | G17: 0.1 | H17: 20.1 | I17: 20.1 | K17: =I17 -> 20.1 | L17: =K17 -> 20.1 | M17: =L17 -> 20.1 | N17: =M17 -> 20.1 | O17: =N17 -> 20.1 | P17: =O17 -> 20.1 | Q17: =P17 -> 20.1 | R17: =Q17 -> 20.1 | S17: =R17 -> 20.1 | T17: =S17 -> 20.1
B18: b) Other non-current financial assets | C18: 31226.7 | D18: 11092.8 | E18: 12627 | F18: 1085.5 | G18: 2347.6 | H18: 1681.2 | I18: 1967.1 | K18: =I18 -> 1967.1 | L18: =K18 -> 1967.1 | M18: =L18 -> 1967.1 | N18: =M18 -> 1967.1 | O18: =N18 -> 1967.1 | P18: =O18 -> 1967.1 | Q18: =P18 -> 1967.1 | R18: =Q18 -> 1967.1 | S18: =R18 -> 1967.1 | T18: =S18 -> 1967.1
B19: Income tax assets (net) | C19: 82.5 | D19: 16.3 | E19: 22.8 | F19: 175 | G19: 175.6 | H19: 181.9 | I19: 168 | K19: =I19 -> 168 | L19: =K19 -> 168 | M19: =L19 -> 168 | N19: =M19 -> 168 | O19: =N19 -> 168 | P19: =O19 -> 168 | Q19: =P19 -> 168 | R19: =Q19 -> 168 | S19: =R19 -> 168 | T19: =S19 -> 168
B20: Deferred tax assets (net) | C20: 2.9 | D20: 9.2 | E20: 16.6 | F20: 17.7 | G20: 47.2 | H20: 75.1 | I20: 67.1 | K20: =I20 -> 67.1 | L20: =K20 -> 67.1 | M20: =L20 -> 67.1 | N20: =M20 -> 67.1 | O20: =N20 -> 67.1 | P20: =O20 -> 67.1 | Q20: =P20 -> 67.1 | R20: =Q20 -> 67.1 | S20: =R20 -> 67.1 | T20: =S20 -> 67.1
B21: Other non-current assets | C21: 2851.4 | D21: 4546.2 | E21: 3737.8 | F21: 3604.3 | G21: 3679 | H21: 4264.5 | I21: 4339.8 | K21: =I21 -> 4339.8 | L21: =K21 -> 4339.8 | M21: =L21 -> 4339.8 | N21: =M21 -> 4339.8 | O21: =N21 -> 4339.8 | P21: =O21 -> 4339.8 | Q21: =P21 -> 4339.8 | R21: =Q21 -> 4339.8 | S21: =R21 -> 4339.8 | T21: =S21 -> 4339.8
B22: Total non-current assets | C22: =(SUM(C10:C21)) -> 97287.8 | D22: =(SUM(D10:D21)) -> 95948.4 | E22: =(SUM(E10:E21)) -> 120297.9 | F22: =(SUM(F10:F21)) -> 126579 | G22: =(SUM(G10:G21)) -> 149751.7 | H22: =(SUM(H10:H21)) -> 179280.9 | I22: =(SUM(I10:I21)) -> 220464.8 | K22: =(SUM(K10:K21)) -> 245263.83 | L22: =(SUM(L10:L21)) -> 271608.82 | M22: =(SUM(M10:M21)) -> 299028.79 | N22: =(SUM(N10:N21)) -> 327419.03 | O22: =(SUM(O10:O21)) -> 356708.93 | P22: =(SUM(P10:P21)) -> 386827.48 | Q22: =(SUM(Q10:Q21)) -> 417704.33 | R22: =(SUM(R10:R21)) -> 449267.82 | ... T22: =(SUM(T10:T21)) -> 514167.32
B23: Current assets
B24: Inventories | C24: 19474 | D24: 22482.8 | E24: 27426.6 | F24: 32434.8 | G24: 39273.1 | H24: 50443.7 | I24: 59006.4 | K24: ='Working Capital'!K7 -> 70358.056 | L24: ='Working Capital'!L7 -> 90023.328 | M24: ='Working Capital'!M7 -> 113163.21 | N24: ='Working Capital'!N7 -> 139780.79 | O24: ='Working Capital'!O7 -> 169425.44 | P24: ='Working Capital'!P7 -> 202823.8 | Q24: ='Working Capital'!Q7 -> 239343.89 | R24: ='Working Capital'!R7 -> 279861.86 | ... T24: ='Working Capital'!T7 -> 373034.36
B25: Financial assets:
B26: a) Investments | C26: 146.8 | D26: 29.5 | E26: 59.3 | F26: 2021.9 | G26: 1066.6 | H26: 12.5 | I26: 20 | K26: =I26 -> 20 | L26: =K26 -> 20 | M26: =L26 -> 20 | N26: =M26 -> 20 | O26: =N26 -> 20 | P26: =O26 -> 20 | Q26: =P26 -> 20 | R26: =Q26 -> 20 | S26: =R26 -> 20 | T26: =S26 -> 20
B27: b) Trade receivables | C27: 195.5 | D27: 435.8 | E27: 668.9 | F27: 621.6 | G27: 1663.7 | H27: 1537.9 | I27: 1493.4 | K27: ='Working Capital'!K13 -> 1786.8988 | L27: ='Working Capital'!L13 -> 2286.3419 | M27: ='Working Capital'!M13 -> 2874.0304 | N27: ='Working Capital'!N13 -> 3550.043 | O27: ='Working Capital'!O13 -> 4302.9346 | P27: ='Working Capital'!P13 -> 5151.1599 | Q27: ='Working Capital'!Q13 -> 6078.6686 | R27: ='Working Capital'!R13 -> 7107.7121 | ... T27: ='Working Capital'!T13 -> 9474.0343
B28: c) Cash and cash equivalents | C28: 1058.7 | D28: 1915 | E28: 951.2 | F28: 2071.5 | G28: 3371.2 | H28: 3554.8 | I28: 2837.1 | K28: ='Cash flow statement'!K66 -> 7058.9061 | L28: ='Cash flow statement'!L66 -> 33433.347 | M28: ='Cash flow statement'!M66 -> 72435.953 | N28: ='Cash flow statement'!N66 -> 128731.64 | O28: ='Cash flow statement'!O66 -> 205842.64 | P28: ='Cash flow statement'!P66 -> 306052.37 | Q28: ='Cash flow statement'!Q66 -> 432501.96 | R28: ='Cash flow statement'!R66 -> 587915.66 | ... T28: ='Cash flow statement'!T66 -> 999207.26
B29: d) Bank balances | C29: 20.1 | D29: 12540.8 | E29: 2034.6 | F29: 12011.8 | G29: 3010.6 | H29: 27.2 | I29: 200.7 | K29: =I29 -> 200.7 | L29: =K29 -> 200.7 | M29: =L29 -> 200.7 | N29: =M29 -> 200.7 | O29: =N29 -> 200.7 | P29: =O29 -> 200.7 | Q29: =P29 -> 200.7 | R29: =Q29 -> 200.7 | S29: =R29 -> 200.7 | T29: =S29 -> 200.7
B30: e) Other current financial assets | C30: 1090.6 | D30: 1679.1 | E30: 1274.6 | F30: 3167.7 | G30: 11284.9 | H30: 5283.6 | I30: 7266 | K30: =I30 -> 7266 | L30: =K30 -> 7266 | M30: =L30 -> 7266 | N30: =M30 -> 7266 | O30: =N30 -> 7266 | P30: =O30 -> 7266 | Q30: =P30 -> 7266 | R30: =Q30 -> 7266 | S30: =R30 -> 7266 | T30: =S30 -> 7266
B31: Other current assets | C31: 1491 | D31: 1528.3 | E31: 2013.3 | F31: 2154.6 | G31: 2350.2 | H31: 3062.3 | I31: 3954.2 | K31: ='Working Capital'!K56 -> 5148.1884 | L31: ='Working Capital'!L56 -> 6569.1237 | M31: ='Working Capital'!M56 -> 8257.6718 | N31: ='Working Capital'!N56 -> 10199.993 | O31: ='Working Capital'!O56 -> 12397.075 | P31: ='Working Capital'!P56 -> 14840.875 | Q31: ='Working Capital'!Q56 -> 17513.097 | R31: ='Working Capital'!R56 -> 20477.848 | ... T31: ='Working Capital'!T56 -> 27295.398
B32: Total current assets | C32: =SUM(C24:C31) -> 23476.7 | D32: =SUM(D24:D31) -> 40611.3 | E32: =SUM(E24:E31) -> 34428.5 | F32: =SUM(F24:F31) -> 54483.9 | G32: =SUM(G24:G31) -> 62020.3 | H32: =SUM(H24:H31) -> 63922 | I32: =SUM(I24:I31) -> 74777.8 | K32: =SUM(K24:K31) -> 91838.75 | L32: =SUM(L24:L31) -> 139798.84 | M32: =SUM(M24:M31) -> 204217.56 | N32: =SUM(N24:N31) -> 289749.17 | O32: =SUM(O24:O31) -> 399454.79 | P32: =SUM(P24:P31) -> 536354.91 | Q32: =SUM(Q24:Q31) -> 702924.32 | R32: =SUM(R24:R31) -> 902849.78 | ... T32: =SUM(T24:T31) -> 1416497.8
B34: Total assets | C34: =SUM(C22,C32) -> 120764.5 | D34: =SUM(D22,D32) -> 136559.7 | E34: =SUM(E22,E32) -> 154726.4 | F34: =SUM(F22,F32) -> 181062.9 | G34: =SUM(G22,G32) -> 211772 | H34: =SUM(H22,H32) -> 243202.9 | I34: =SUM(I22,I32) -> 295242.6 | K34: =SUM(K22,K32) -> 337102.58 | L34: =SUM(L22,L32) -> 411407.66 | M34: =SUM(M22,M32) -> 503246.36 | N34: =SUM(N22,N32) -> 617168.2 | O34: =SUM(O22,O32) -> 756163.72 | P34: =SUM(P22,P32) -> 923182.39 | Q34: =SUM(Q22,Q32) -> 1120628.7 | R34: =SUM(R22,R32) -> 1352117.6 | ... T34: =SUM(T22,T32) -> 1930665.1
B36: Equity and liabilities
B37: Equity:
B38: Equity share capital | C38: 6477.7 | D38: 6477.7 | E38: 6477.7 | F38: 6482.6 | G38: 6507.3 | H38: 6507.3 | I38: 6519.6 | K38: =I38 -> 6519.6 | L38: =K38 -> 6519.6 | M38: =L38 -> 6519.6 | N38: =M38 -> 6519.6 | O38: =N38 -> 6519.6 | P38: =O38 -> 6519.6 | Q38: =P38 -> 6519.6 | R38: =Q38 -> 6519.6 | S38: =R38 -> 6519.6 | T38: =S38 -> 6519.6
B39: Other equity | C39: 104319.7 | D39: 115359.4 | E39: 130298.7 | F39: 154304.4 | G39: 180470.9 | H39: 207770.2 | I39: 238120.8 | K39: =I39+'P & L'!K32 -> 286921.63 | L39: =K39+'P & L'!L32 -> 351282.59 | M39: =L39+'P & L'!M32 -> 433934.84 | N39: =M39+'P & L'!N32 -> 537716.29 | O39: =N39+'P & L'!O32 -> 665499.64 | P39: =O39+'P & L'!P32 -> 820064.02 | Q39: =P39+'P & L'!Q32 -> 1003977.7 | R39: =Q39+'P & L'!R32 -> 1220543 | S39: =R39+'P & L'!S32 -> 1473105.3 | T39: =S39+'P & L'!T32 -> 1764998.4
B40: Equity attributable to equity holders of the Company | C40: =SUM(C38:C39) -> 110797.4 | D40: =SUM(D38:D39) -> 121837.1 | E40: =SUM(E38:E39) -> 136776.4 | F40: =SUM(F38:F39) -> 160787 | G40: =SUM(G38:G39) -> 186978.2 | H40: =SUM(H38:H39) -> 214277.5 | I40: =SUM(I38:I39) -> 244640.4 | K40: =SUM(K38:K39) -> 293441.23 | L40: =SUM(L38:L39) -> 357802.19 | M40: =SUM(M38:M39) -> 440454.44 | N40: =SUM(N38:N39) -> 544235.89 | O40: =SUM(O38:O39) -> 672019.24 | P40: =SUM(P38:P39) -> 826583.62 | Q40: =SUM(Q38:Q39) -> 1010497.3 | R40: =SUM(R38:R39) -> 1227062.6 | ... T40: =SUM(T38:T39) -> 1771518
B41: Non-controlling interest | C41: 4.6 | D41: 4 | E41: 2.5 | F41: 0.8 | G41: -4.8 | H41: -10.5 | I41: -16.8 | K41: =I41 -> -16.8 | L41: =K41 -> -16.8 | M41: =L41 -> -16.8 | N41: =M41 -> -16.8 | O41: =N41 -> -16.8 | P41: =O41 -> -16.8 | Q41: =P41 -> -16.8 | R41: =Q41 -> -16.8 | S41: =R41 -> -16.8 | T41: =S41 -> -16.8
B42: Total equity | C42: =SUM(C40:C41) -> 110802 | D42: =SUM(D40:D41) -> 121841.1 | E42: =SUM(E40:E41) -> 136778.9 | F42: =SUM(F40:F41) -> 160787.8 | G42: =SUM(G40:G41) -> 186973.4 | H42: =SUM(H40:H41) -> 214267 | I42: =SUM(I40:I41) -> 244623.6 | K42: =SUM(K40:K41) -> 293424.43 | L42: =SUM(L40:L41) -> 357785.39 | M42: =SUM(M40:M41) -> 440437.64 | N42: =SUM(N40:N41) -> 544219.09 | O42: =SUM(O40:O41) -> 672002.44 | P42: =SUM(P40:P41) -> 826566.82 | Q42: =SUM(Q40:Q41) -> 1010480.5 | R42: =SUM(R40:R41) -> 1227045.8 | ... T42: =SUM(T40:T41) -> 1771501.2
B43: Liabilities:
B44: Non-current liabilities:
B45: Financial liabilities
B46: a) Lease liabilities | C46: 2211.1 | D46: 3120.1 | E46: 5071.5 | F46: 4766.6 | G46: 3992.4 | H46: 5557.9 | I46: 11425.4 | K46: =Schedules!K34 -> 11837.446 | L46: =Schedules!L34 -> 12143.723 | M46: =Schedules!M34 -> 12371.38 | N46: =Schedules!N34 -> 12540.599 | O46: =Schedules!O34 -> 12666.38 | P46: =Schedules!P34 -> 12759.874 | Q46: =Schedules!Q34 -> 12830.112 | R46: =Schedules!R34 -> 12883.064 | ... T46: =Schedules!T34 -> 12953.718
B47: b) Other financial liabilities | C47: 4.7 | D47: 4.4 | E47: 4.1 | F47: 4.7 | G47: 3.7 | H47: 4.9 | I47: 5.4 | K47: =I47 -> 5.4 | L47: =K47 -> 5.4 | M47: =L47 -> 5.4 | N47: =M47 -> 5.4 | O47: =N47 -> 5.4 | P47: =O47 -> 5.4 | Q47: =P47 -> 5.4 | R47: =Q47 -> 5.4 | S47: =R47 -> 5.4 | T47: =S47 -> 5.4
B48: Provisions | C48: 14.8 | D48: 24.5 | E48: 48.7 | F48: 64.1 | G48: 91.8 | H48: 126.7 | I48: 147 | K48: =I48 -> 147 | L48: =K48 -> 147 | M48: =L48 -> 147 | N48: =M48 -> 147 | O48: =N48 -> 147 | P48: =O48 -> 147 | Q48: =P48 -> 147 | R48: =Q48 -> 147 | S48: =R48 -> 147 | T48: =S48 -> 147
B49: Deferred tax liabilities (net) | C49: 473.9 | D49: 511.9 | E49: 640.3 | F49: 769.6 | G49: 919.3 | H49: 1124.8 | I49: 1218.6 | K49: =Schedules!K56 -> 1391.1412 | L49: =Schedules!L56 -> 1576.0297 | M49: =Schedules!M56 -> 1785.1184 | N49: =Schedules!N56 -> 2003.8613 | O49: =Schedules!O56 -> 2231.7815 | P49: =Schedules!P56 -> 2468.7913 | Q49: =Schedules!Q56 -> 2715.2282 | R49: =Schedules!R56 -> 2968.2853 | ... T49: =Schedules!T56 -> 3492.7035
B50: Total non-current liabilities | C50: =SUM(C46:C49) -> 2704.5 | D50: =SUM(D46:D49) -> 3660.9 | E50: =SUM(E46:E49) -> 5764.6 | F50: =SUM(F46:F49) -> 5605 | G50: =SUM(G46:G49) -> 5007.2 | H50: =SUM(H46:H49) -> 6814.3 | I50: =SUM(I46:I49) -> 12796.4 | K50: =SUM(K46:K49) -> 13380.987 | L50: =SUM(L46:L49) -> 13872.152 | M50: =SUM(M46:M49) -> 14308.898 | N50: =SUM(N46:N49) -> 14696.86 | O50: =SUM(O46:O49) -> 15050.562 | P50: =SUM(P46:P49) -> 15381.066 | Q50: =SUM(Q46:Q49) -> 15697.741 | R50: =SUM(R46:R49) -> 16003.749 | ... T50: =SUM(T46:T49) -> 16598.822
B51: Current liabilities:
B52: Financial liabilities:
B53: a) Borrowings | C53: 37.3 | D53: 0 | E53: 0 | F53: 0 | G53: 0 | H53: 0 | I53: 9652.7 | K53: 0 | L53: 0 | M53: 0 | N53: 0 | O53: 0 | P53: 0 | Q53: 0 | R53: 0 | S53: 0 | T53: 0
B54: b) Lease liabilities | C54: 743.5 | D54: 807 | E54: 1397.9 | F54: 1663.2 | G54: 1929.2 | H54: 2638.3 | I54: 3171.8 | K54: =Schedules!K33 -> 4087.9538 | L54: =Schedules!L33 -> 4193.7236 | M54: =Schedules!M33 -> 4272.3429 | N54: =Schedules!N33 -> 4330.7811 | O54: =Schedules!O33 -> 4374.2186 | P54: =Schedules!P33 -> 4406.5059 | Q54: =Schedules!Q33 -> 4430.762 | R54: =Schedules!R33 -> 4449.0483 | ... T54: =Schedules!T33 -> 4473.4482
B55: c) Trade payables:
B56: Micro and small enterprises | C56: 174.7 | D56: 219.5 | E56: 323.9 | F56: 762.9 | G56: 2306 | H56: 2895.3 | I56: 3934.7 | K56: ='Working Capital'!K19 -> 4344.1019 | L56: ='Working Capital'!L19 -> 5558.2904 | M56: ='Working Capital'!M19 -> 6987.0107 | N56: ='Working Capital'!N19 -> 8630.4545 | O56: ='Working Capital'!O19 -> 10460.798 | P56: ='Working Capital'!P19 -> 12522.905 | Q56: ='Working Capital'!Q19 -> 14777.757 | R56: ='Working Capital'!R19 -> 17279.449 | ... T56: ='Working Capital'!T19 -> 23032.178
B57: Other than micro and small enterprises | C57: 4159.8 | D57: 5561.8 | E57: 5568.1 | F57: 6775 | G57: 7542.1 | H57: 7812.8 | I57: 9447.6 | K57: ='Working Capital'!K20 -> 11975.581 | L57: ='Working Capital'!L20 -> 15322.789 | M57: ='Working Capital'!M20 -> 19261.407 | N57: ='Working Capital'!N20 -> 23791.963 | O57: ='Working Capital'!O20 -> 28837.752 | P57: ='Working Capital'!P20 -> 34522.456 | Q57: ='Working Capital'!Q20 -> 40738.508 | R57: ='Working Capital'!R20 -> 47635.034 | ... T57: ='Working Capital'!T20 -> 63493.842
B58: d) Other financial liabilities | C58: 1779.4 | D58: 2697.8 | E58: 2829.2 | F58: 2894.6 | G58: 3898.5 | H58: 4486.4 | I58: 6371.9 | K58: ='Working Capital'!K36 -> 2475.1087 | L58: ='Working Capital'!L36 -> 5016.993 | M58: ='Working Capital'!M36 -> 5673.0613 | N58: ='Working Capital'!N36 -> 6139.0628 | O58: ='Working Capital'!O36 -> 6613.8169 | P58: ='Working Capital'!P36 -> 7097.4523 | Q58: ='Working Capital'!Q36 -> 7590.099 | R58: ='Working Capital'!R36 -> 8091.8889 | ... T58: ='Working Capital'!T36 -> 9123.4344
B59: Other current liabilities | C59: 4.5 | D59: 1126.6 | E59: 1115.7 | F59: 1211.8 | G59: 957.4 | H59: 1386.2 | I59: 1414.4 | K59: ='Working Capital'!K48 -> 2178.6349 | L59: ='Working Capital'!L48 -> 2804.4601 | M59: ='Working Capital'!M48 -> 3545.8135 | N59: ='Working Capital'!N48 -> 4399.6276 | O59: ='Working Capital'!O48 -> 5366.6183 | P59: ='Working Capital'!P48 -> 6443.1789 | Q59: ='Working Capital'!Q48 -> 7621.1279 | R59: ='Working Capital'!R48 -> 8929.0753 | ... T59: ='Working Capital'!T48 -> 11939.611
B60: Provisions | C60: 207 | D60: 407.3 | E60: 583.7 | F60: 508.7 | G60: 610.4 | H60: 491.4 | I60: 1114.2 | K60: ='Working Capital'!K40 -> 1198.6249 | L60: ='Working Capital'!L40 -> 1529.4536 | M60: ='Working Capital'!M40 -> 1922.5891 | N60: ='Working Capital'!N40 -> 2374.8093 | O60: ='Working Capital'!O40 -> 2886.3441 | P60: ='Working Capital'!P40 -> 3455.3209 | Q60: ='Working Capital'!Q40 -> 4077.4798 | R60: ='Working Capital'!R40 -> 4767.7468 | ... T60: ='Working Capital'!T40 -> 6355.0402
B61: Current Tax Liabilities (Net) | C61: 151.8 | D61: 237.7 | E61: 364.4 | F61: 853.9 | G61: 2547.8 | H61: 2411.2 | I61: 2715.3 | K61: ='Working Capital'!K31 -> 4037.1598 | L61: ='Working Capital'!L31 -> 5324.4069 | M61: ='Working Capital'!M31 -> 6837.5954 | N61: ='Working Capital'!N31 -> 8585.5569 | O61: ='Working Capital'!O31 -> 10571.168 | P61: ='Working Capital'!P31 -> 12786.69 | Q61: ='Working Capital'!Q31 -> 15214.678 | R61: ='Working Capital'!R31 -> 17915.854 | ... T61: ='Working Capital'!T31 -> 24147.517
B62: Total current liabilities | C62: =SUM(C53:C61) -> 7258 | D62: =SUM(D54:D61) -> 11057.7 | E62: =SUM(E54:E61) -> 12182.9 | F62: =SUM(F54:F61) -> 14670.1 | G62: =SUM(G54:G61) -> 19791.4 | H62: =SUM(H54:H61) -> 22121.6 | I62: =SUM(I53:I61) -> 37822.6 | K62: =SUM(K53:K61) -> 30297.165 | L62: =SUM(L53:L61) -> 39750.117 | M62: =SUM(M53:M61) -> 48499.82 | N62: =SUM(N53:N61) -> 58252.255 | O62: =SUM(O53:O61) -> 69110.716 | P62: =SUM(P53:P61) -> 81234.509 | Q62: =SUM(Q53:Q61) -> 94450.412 | R62: =SUM(R53:R61) -> 109068.1 | ... T62: =SUM(T53:T61) -> 142565.07
B64: Total equity and liabilities | C64: =SUM(C42+C50+C62) -> 120764.5 | D64: =SUM(D42+D50+D62) -> 136559.7 | E64: =SUM(E42+E50+E62) -> 154726.4 | F64: =SUM(F42+F50+F62) -> 181062.9 | G64: =SUM(G42+G50+G62) -> 211772 | H64: =SUM(H42+H50+H62) -> 243202.9 | I64: =SUM(I42+I50+I62) -> 295242.6 | K64: =SUM(K42+K50+K62) -> 337102.58 | L64: =SUM(L42+L50+L62) -> 411407.66 | M64: =SUM(M42+M50+M62) -> 503246.36 | N64: =SUM(N42+N50+N62) -> 617168.2 | O64: =SUM(O42+O50+O62) -> 756163.72 | P64: =SUM(P42+P50+P62) -> 923182.39 | Q64: =SUM(Q42+Q50+Q62) -> 1120628.7 | R64: =SUM(R42+R50+R62) -> 1352117.6 | ... T64: =SUM(T42+T50+T62) -> 1930665.1
B65: Check | C65: =IF(ROUND((C64-C34),0)=0,"Balanced","Un-balanced") -> Balanced | D65: =IF(ROUND((D64-D34),0)=0,"Balanced","Un-balanced") -> Balanced | E65: =IF(ROUND((E64-E34),0)=0,"Balanced","Un-balanced") -> Balanced | F65: =IF(ROUND((F64-F34),0)=0,"Balanced","Un-balanced") -> Balanced | G65: =IF(ROUND((G64-G34),0)=0,"Balanced","Un-balanced") -> Balanced | H65: =IF(ROUND((H64-H34),0)=0,"Balanced","Un-balanced") -> Balanced | I65: =IF(ROUND((I64-I34),0)=0,"Balanced","Un-balanced") -> Balanced | K65: =IF(ROUND((K64-K34),0)=0,"Balanced","Un-balanced") -> Balanced | L65: =IF(ROUND((L64-L34),0)=0,"Balanced","Un-balanced") -> Balanced | M65: =IF(ROUND((M64-M34),0)=0,"Balanced","Un-balanced") -> Balanced | N65: =IF(ROUND((N64-N34),0)=0,"Balanced","Un-balanced") -> Balanced | O65: =IF(ROUND((O64-O34),0)=0,"Balanced","Un-balanced") -> Balanced | P65: =IF(ROUND((P64-P34),0)=0,"Balanced","Un-balanced") -> Balanced | Q65: =IF(ROUND((Q64-Q34),0)=0,"Balanced","Un-balanced") -> Balanced | R65: =IF(ROUND((R64-R34),0)=0,"Balanced","Un-balanced") -> Balanced | ... T65: =IF(ROUND((T64-T34),0)=0,"Balanced","Un-balanced") -> Balanced

Sheet Cash flow statement
B2: Cash Flow Statement- Avenue Supermarts Limited
B6: (In Millions) | C6: 43921 | D6: =EOMONTH(C6,12) -> 44286 | E6: =EOMONTH(D6,12) -> 44651 | F6: =EOMONTH(E6,12) -> 45016 | G6: =EOMONTH(F6,12) -> 45382 | H6: =EOMONTH(G6,12) -> 45747 | I6: =EOMONTH(H6,12) -> 46112 | K6: =EOMONTH(I6,12) -> 46477 | L6: =EOMONTH(K6,12) -> 46843 | M6: =EOMONTH(L6,12) -> 47208 | N6: =EOMONTH(M6,12) -> 47573 | O6: =EOMONTH(N6,12) -> 47938 | P6: =EOMONTH(O6,12) -> 48304 | Q6: =EOMONTH(P6,12) -> 48669 | R6: =EOMONTH(Q6,12) -> 49034 | S6: =EOMONTH(R6,12) -> 49399 | T6: =EOMONTH(S6,12) -> 49765
B7: Cash flow from operating activities:
B8: Profit before tax | C8: 17447.7 | D8: 14834.5 | E8: 20641.2 | F8: 30600.9 | G8: 34613.3 | H8: 36726.7 | I8: 40816.2 | K8: ='P & L'!K24 -> 66850.452 | L8: ='P & L'!L24 -> 88165.697 | M8: ='P & L'!M24 -> 113222.26 | N8: ='P & L'!N24 -> 142166.37 | O8: ='P & L'!O24 -> 175045.68 | P8: ='P & L'!P24 -> 211732.03 | Q8: ='P & L'!Q24 -> 251936.55 | R8: ='P & L'!R24 -> 296664.74 | ... T8: ='P & L'!T24 -> 399853.49
B9: Adjustments for:
B10: Depreciation and amortisation expenses | C10: 3744.1 | D10: 4141.6 | E10: 4980.8 | F10: 6388.7 | G10: 7307.6 | H10: 8695.2 | I10: 10370.2 | K10: =-'P & L'!K19 -> 12200.967 | L10: =-'P & L'!L19 -> 13155.015 | M10: =-'P & L'!M19 -> 14580.023 | N10: =-'P & L'!N19 -> 16109.765 | O10: =-'P & L'!O19 -> 17710.104 | P10: =-'P & L'!P19 -> 19381.443 | Q10: =-'P & L'!Q19 -> 21124.15 | R10: =-'P & L'!R19 -> 22938.512 | ... T10: =-'P & L'!T19 -> 26782.808
B11: Finance costs | C11: 691.2 | D11: 416.5 | E11: 537.9 | F11: 674.1 | G11: 581.3 | H11: 694.5 | I11: 1420.5 | K11: =-'P & L'!K22 -> 1780.3735 | L11: =-'P & L'!L22 -> 1821.2098 | M11: =-'P & L'!M22 -> 1851.5637 | N11: =-'P & L'!N22 -> 1874.126 | O11: =-'P & L'!O22 -> 1890.8966 | P11: =-'P & L'!P22 -> 1903.3624 | Q11: =-'P & L'!Q22 -> 1912.7273 | R11: =-'P & L'!R22 -> 1919.7874 | ... T11: =-'P & L'!T22 -> 1929.2079
B12: Interest income | C12: =(-32.49)*10 -> -324.9 | D12: -1781.3 | E12: -1039.6 | F12: -1075.6 | G12: -1074.6 | H12: -878.3 | I12: -539.8 | K12: =-'P & L'!K23 -> -3059.3497 | L12: =-'P & L'!L23 -> -3903.7512 | M12: =-'P & L'!M23 -> -4907.1836 | N12: =-'P & L'!N23 -> -6061.4227 | O12: =-'P & L'!O23 -> -7367.0552 | P12: =-'P & L'!P23 -> -8819.3018 | Q12: =-'P & L'!Q23 -> -10407.29 | R12: =-'P & L'!R23 -> -12169.115 | ... T12: =-'P & L'!T23 -> -16220.496
B13: Gain on sale of investments | C13: -101.6 | D13: -25.6 | E13: -36.6 | F13: -88.3 | G13: -271.1 | H13: -217.6 | I13: -40.7 | K13: 0 | L13: 0 | M13: 0 | N13: 0 | O13: 0 | P13: 0 | Q13: 0 | R13: 0 | S13: 0 | T13: 0
B14: Expense on employee stock option scheme | C14: 84.6 | D14: 63.8 | E14: 64.2 | F14: 120.1 | G14: 188.4 | H14: 307.2 | I14: 338.7 | K14: 0 | L14: 0 | M14: 0 | N14: 0 | O14: 0 | P14: 0 | Q14: 0 | R14: 0 | S14: 0 | T14: 0
B15: Rent income | C15: -28.8 | D15: -28.9 | E15: -35.5 | F15: -46.9 | G15: -49.8 | H15: -50.4 | I15: -53.4 | K15: 0 | L15: 0 | M15: 0 | N15: 0 | O15: 0 | P15: 0 | Q15: 0 | R15: 0 | S15: 0 | T15: 0
B16: Loss on disposal of property, plant and equipment (net) | C16: -24.5 | D16: 17.8 | E16: 38.5 | F16: 17.4 | G16: 18.7 | H16: 71.8 | I16: 22 | K16: 0 | L16: 0 | M16: 0 | N16: 0 | O16: 0 | P16: 0 | Q16: 0 | R16: 0 | S16: 0 | T16: 0
B17: Operating profit before working capital changes | C17: =SUM(C8:C16) -> 21487.8 | D17: =SUM(D8:D16) -> 17638.4 | E17: =SUM(E8:E16) -> 25150.9 | F17: =SUM(F8:F16) -> 36590.4 | G17: =SUM(G8:G16) -> 41313.8 | H17: =SUM(H8:H16) -> 45349.1 | I17: =SUM(I8:I16) -> 52333.7 | K17: =SUM(K8:K16) -> 77772.443 | L17: =SUM(L8:L16) -> 99238.171 | M17: =SUM(M8:M16) -> 124746.66 | N17: =SUM(N8:N16) -> 154088.84 | O17: =SUM(O8:O16) -> 187279.63 | P17: =SUM(P8:P16) -> 224197.53 | Q17: =SUM(Q8:Q16) -> 264566.14 | R17: =SUM(R8:R16) -> 309353.92 | ... T17: =SUM(T8:T16) -> 412345.01
B18: Adjustments for:
B19: Increase in trade payables | C19: -298.2 | D19: 1446.8 | E19: 110.7 | F19: 1645.9 | G19: 2310.2 | H19: 860 | I19: 2674.2 | K19: =SUM(BS!K56:K57)-SUM(BS!I56:I57) -> 2937.3831 | L19: =SUM(BS!L56:L57)-SUM(BS!K56:K57) -> 4561.3967 | M19: =SUM(BS!M56:M57)-SUM(BS!L56:L57) -> 5367.3379 | N19: =SUM(BS!N56:N57)-SUM(BS!M56:M57) -> 6173.9993 | O19: =SUM(BS!O56:O57)-SUM(BS!N56:N57) -> 6876.1324 | P19: =SUM(BS!P56:P57)-SUM(BS!O56:O57) -> 7746.8114 | Q19: =SUM(BS!Q56:Q57)-SUM(BS!P56:P57) -> 8470.9041 | R19: =SUM(BS!R56:R57)-SUM(BS!Q56:Q57) -> 9398.2182 | S19: =SUM(BS!S56:S57)-SUM(BS!R56:R57) -> 10337.652 | T19: =SUM(BS!T56:T57)-SUM(BS!S56:S57) -> 11273.885
B20: Increase/decrease in current provisions | C20: -30.4 | D20: 62.4 | E20: 65.3 | F20: 79.9 | G20: -12.4 | H20: -232.3 | I20: 551.2 | K20: =BS!K60-BS!I60 -> 84.42491 | L20: =BS!L60-BS!K60 -> 330.8287 | M20: =BS!M60-BS!L60 -> 393.13553 | N20: =BS!N60-BS!M60 -> 452.22018 | O20: =BS!O60-BS!N60 -> 511.53474 | P20: =BS!P60-BS!O60 -> 568.9768 | Q20: =BS!Q60-BS!P60 -> 622.15894 | R20: =BS!R60-BS!Q60 -> 690.26698 | S20: =BS!S60-BS!R60 -> 759.26519 | T20: =BS!T60-BS!S60 -> 828.02828
B21: Increase/decrease in other current financial liabilities | C21: 242.8 | D21: 488.7 | E21: -69.1 | F21: -71.1 | G21: 399.2 | H21: 431.7 | I21: 356.3 | K21: =BS!K58-BS!I58 -> -3896.7913 | L21: =BS!L58-BS!K58 -> 2541.8843 | M21: =BS!M58-BS!L58 -> 656.06831 | N21: =BS!N58-BS!M58 -> 466.00146 | O21: =BS!O58-BS!N58 -> 474.75419 | P21: =BS!P58-BS!O58 -> 483.63536 | Q21: =BS!Q58-BS!P58 -> 492.64669 | R21: =BS!R58-BS!Q58 -> 501.78988 | S21: =BS!S58-BS!R58 -> 511.06667 | T21: =BS!T58-BS!S58 -> 520.47881
B22: Increase/decrease in other current liabilities | C22: -22.4 | D22: 200.3 | E22: 176.4 | F22: 628.1 | G22: -254.4 | H22: 428.8 | I22: 28.2 | K22: =BS!K59-BS!I59 -> 764.23491 | L22: =BS!L59-BS!K59 -> 625.82517 | M22: =BS!M59-BS!L59 -> 741.35345 | N22: =BS!N59-BS!M59 -> 853.81412 | O22: =BS!O59-BS!N59 -> 966.99063 | P22: =BS!P59-BS!O59 -> 1076.5606 | Q22: =BS!Q59-BS!P59 -> 1177.949 | R22: =BS!R59-BS!Q59 -> 1307.9475 | S22: =BS!S59-BS!R59 -> 1439.6462 | T22: =BS!T59-BS!S59 -> 1570.8894
B23: Increase/decrease in non-current provisions | C23: 4.3 | D23: 9.7 | E23: 24.2 | F23: 15.4 | G23: 27.7 | H23: 34.9 | I23: 20.3 | K23: =BS!K48-BS!I48 -> 0 | L23: =BS!L48-BS!K48 -> 0 | M23: =BS!M48-BS!L48 -> 0 | N23: =BS!N48-BS!M48 -> 0 | O23: =BS!O48-BS!N48 -> 0 | P23: =BS!P48-BS!O48 -> 0 | Q23: =BS!Q48-BS!P48 -> 0 | R23: =BS!R48-BS!Q48 -> 0 | S23: =BS!S48-BS!R48 -> 0 | T23: =BS!T48-BS!S48 -> 0
B24: Increase/decrease in other non-current financial liabilities | C24: -3.1 | D24: -0.3 | E24: -0.3 | F24: 0.6 | G24: -1 | H24: 1.2 | I24: 0.5 | K24: =BS!K47-BS!I47 -> 0 | L24: =BS!L47-BS!K47 -> 0 | M24: =BS!M47-BS!L47 -> 0 | N24: =BS!N47-BS!M47 -> 0 | O24: =BS!O47-BS!N47 -> 0 | P24: =BS!P47-BS!O47 -> 0 | Q24: =BS!Q47-BS!P47 -> 0 | R24: =BS!R47-BS!Q47 -> 0 | S24: =BS!S47-BS!R47 -> 0 | T24: =BS!T47-BS!S47 -> 0
B25: Increase/decrease in trade receivables | C25: 448.2 | D25: -240.3 | E25: -233.1 | F25: 47.3 | G25: -1042.1 | H25: 125.8 | I25: 44.5 | K25: =BS!I27-BS!K27 -> -293.49876 | L25: =BS!K27-BS!L27 -> -499.44316 | M25: =BS!L27-BS!M27 -> -587.68846 | N25: =BS!M27-BS!N27 -> -676.01262 | O25: =BS!N27-BS!O27 -> -752.89161 | P25: =BS!O27-BS!P27 -> -848.22528 | Q25: =BS!P27-BS!Q27 -> -927.5087 | R25: =BS!Q27-BS!R27 -> -1029.0435 | S25: =BS!R27-BS!S27 -> -1131.9054 | T25: =BS!S27-BS!T27 -> -1234.4168
B26: Increase/decrease in inventories | C26: -3387.5 | D26: -3008.8 | E26: -4943.8 | F26: -5008.2 | G26: -6838.3 | H26: -11170.6 | I26: -8562.7 | K26: =BS!I24-BS!K24 -> -11351.656 | L26: =BS!K24-BS!L24 -> -19665.272 | M26: =BS!L24-BS!M24 -> -23139.877 | N26: =BS!M24-BS!N24 -> -26617.588 | O26: =BS!N24-BS!O24 -> -29644.651 | P26: =BS!O24-BS!P24 -> -33398.356 | Q26: =BS!P24-BS!Q24 -> -36520.093 | R26: =BS!Q24-BS!R24 -> -40517.966 | S26: =BS!R24-BS!S24 -> -44568.09 | T26: =BS!S24-BS!T24 -> -48604.413
B27: Increase/decrease in other non-current assets | C27: 18.5 | D27: 117.3 | E27: -29.8 | F27: 0 | G27: 0 | H27: -249.7 | I27: -94.4 | K27: =BS!I21-BS!K21 -> 0 | L27: =BS!K21-BS!L21 -> 0 | M27: =BS!L21-BS!M21 -> 0 | N27: =BS!M21-BS!N21 -> 0 | O27: =BS!N21-BS!O21 -> 0 | P27: =BS!O21-BS!P21 -> 0 | Q27: =BS!P21-BS!Q21 -> 0 | R27: =BS!Q21-BS!R21 -> 0 | S27: =BS!R21-BS!S21 -> 0 | T27: =BS!S21-BS!T21 -> 0
B28: Increase/decrease in other non-current financial assets | C28: -113.3 | D28: -152.6 | E28: -67.9 | F28: -189.9 | G28: -282.3 | H28: -509.2 | I28: -439.2 | K28: =BS!I18-BS!K18 -> 0 | L28: =BS!K18-BS!L18 -> 0 | M28: =BS!L18-BS!M18 -> 0 | N28: =BS!M18-BS!N18 -> 0 | O28: =BS!N18-BS!O18 -> 0 | P28: =BS!O18-BS!P18 -> 0 | Q28: =BS!P18-BS!Q18 -> 0 | R28: =BS!Q18-BS!R18 -> 0 | S28: =BS!R18-BS!S18 -> 0 | T28: =BS!S18-BS!T18 -> 0
B29: Increase/decrease in bank balances other than cash and cash equivalents | C29: -5 | D29: -20.7 | E29: 6.2 | F29: -487.1 | G29: -0.4 | H29: -1.5 | I29: -189.8 | K29: =BS!I29-BS!K29 -> 0 | L29: =BS!K29-BS!L29 -> 0 | M29: =BS!L29-BS!M29 -> 0 | N29: =BS!M29-BS!N29 -> 0 | O29: =BS!N29-BS!O29 -> 0 | P29: =BS!O29-BS!P29 -> 0 | Q29: =BS!P29-BS!Q29 -> 0 | R29: =BS!Q29-BS!R29 -> 0 | S29: =BS!R29-BS!S29 -> 0 | T29: =BS!S29-BS!T29 -> 0
B30: Increase/decrease in other current assets | C30: -424.3 | D30: -47.9 | E30: -489.6 | F30: 139.1 | G30: -389.6 | H30: -712.1 | I30: -891.9 | K30: =BS!I31-BS!K31 -> -1193.9884 | L30: =BS!K31-BS!L31 -> -1420.9353 | M30: =BS!L31-BS!M31 -> -1688.5481 | N30: =BS!M31-BS!N31 -> -1942.3213 | O30: =BS!N31-BS!O31 -> -2197.082 | P30: =BS!O31-BS!P31 -> -2443.8002 | Q30: =BS!P31-BS!Q31 -> -2672.2216 | R30: =BS!Q31-BS!R31 -> -2964.7511 | S30: =BS!R31-BS!S31 -> -3261.1038 | T30: =BS!S31-BS!T31 -> -3556.4467
B31: Increase/decrease in other current financial assets | C31: -192 | D31: -125.9 | E31: -374.1 | F31: 1.2 | G31: -354.3 | H31: -134.1 | I31: -482.3 | K31: =BS!I30-BS!K30 -> 0 | L31: =BS!K30-BS!L30 -> 0 | M31: =BS!L30-BS!M30 -> 0 | N31: =BS!M30-BS!N30 -> 0 | O31: =BS!N30-BS!O30 -> 0 | P31: =BS!O30-BS!P30 -> 0 | Q31: =BS!P30-BS!Q30 -> 0 | R31: =BS!Q30-BS!R30 -> 0 | S31: =BS!R30-BS!S30 -> 0 | T31: =BS!S30-BS!T30 -> 0
B32: Cash flow from operating activities | C32: =SUM(C17:C31) -> 17725.4 | D32: =SUM(D17:D31) -> 16367.1 | E32: =SUM(E17:E31) -> 19326 | F32: =SUM(F17:F31) -> 33391.6 | G32: =SUM(G17:G31) -> 34876.1 | H32: =SUM(H17:H31) -> 34222 | I32: =SUM(I17:I31) -> 45348.6 | K32: =SUM(K17:K31) -> 64822.551 | L32: =SUM(L17:L31) -> 85712.456 | M32: =SUM(M17:M31) -> 106488.44 | N32: =SUM(N17:N31) -> 132798.95 | O32: =SUM(O17:O31) -> 163514.42 | P32: =SUM(P17:P31) -> 197383.13 | Q32: =SUM(Q17:Q31) -> 235209.97 | R32: =SUM(R17:R31) -> 276740.38 | ... T32: =SUM(T17:T31) -> 373143.02
B33: Direct taxes paid (net of refunds) | C33: -4924 | D33: -2615.7 | E33: -5602.5 | F33: -7088.9 | G33: -7417.7 | H33: -9592.3 | I33: -10681.2 | K33: ='P & L'!K30+(BS!K61-BS!I61)+(BS!K49-BS!I49) -> -16555.221 | L33: ='P & L'!L30+(BS!L61-BS!K61)+(BS!L49-BS!K49) -> -22332.603 | M33: ='P & L'!M30+(BS!M61-BS!L61)+(BS!M49-BS!L49) -> -28847.732 | N33: ='P & L'!N30+(BS!N61-BS!M61)+(BS!N49-BS!M49) -> -36418.216 | O33: ='P & L'!O30+(BS!O61-BS!N61)+(BS!O49-BS!N49) -> -45048.803 | P33: ='P & L'!P30+(BS!P61-BS!O61)+(BS!P49-BS!O49) -> -54715.116 | Q33: ='P & L'!Q30+(BS!Q61-BS!P61)+(BS!Q49-BS!P49) -> -65348.444 | R33: ='P & L'!R30+(BS!R61-BS!Q61)+(BS!R49-BS!Q49) -> -77145.246 | S33: ='P & L'!S30+(BS!S61-BS!R61)+(BS!S49-BS!R49) -> -90176.304 | T33: ='P & L'!T30+(BS!T61-BS!S61)+(BS!T49-BS!S49) -> -104441.54
B34: Net cash flow from operating activities | C34: =SUM(C32:C33) -> 12801.4 | D34: =SUM(D32:D33) -> 13751.4 | E34: =SUM(E32:E33) -> 13723.5 | F34: =SUM(F32:F33) -> 26302.7 | G34: =SUM(G32:G33) -> 27458.4 | H34: =SUM(H32:H33) -> 24629.7 | I34: =SUM(I32:I33) -> 34667.4 | K34: =SUM(K32:K33) -> 48267.33 | L34: =SUM(L32:L33) -> 63379.853 | M34: =SUM(M32:M33) -> 77640.71 | N34: =SUM(N32:N33) -> 96380.738 | O34: =SUM(O32:O33) -> 118465.61 | P34: =SUM(P32:P33) -> 142668.02 | Q34: =SUM(Q32:Q33) -> 169861.53 | R34: =SUM(R32:R33) -> 199595.14 | ... T34: =SUM(T32:T33) -> 268701.48
B36: Cash flow from investing activities:
B37: Proceeds from disposal of property, plant and equipment | C37: 61.5 | D37: 18.8 | E37: 209.2 | F37: 54.6 | G37: 94.5 | H37: 58.3 | I37: 4.4 | K37: 0 | L37: 0 | M37: 0 | N37: 0 | O37: 0 | P37: 0 | Q37: 0 | R37: 0 | S37: 0 | T37: 0
B38: Realisation from Bank Deposits/(Purchase of Bank Deposits) | C38: 2215.8 | D38: 7830 | E38: 10500 | F38: 374 | G38: -1362.6 | H38: 9984.4 | I38: -1464.6 | K38: 0 | L38: 0 | M38: 0 | N38: 0 | O38: 0 | P38: 0 | Q38: 0 | R38: 0 | S38: 0 | T38: 0
B39: Interest received | C39: 118.4 | D39: 1290.9 | E39: 428 | F39: 387.2 | G39: 2622.9 | H39: 1031 | I39: 437.3 | K39: =-K12 -> 3059.3497 | L39: =-L12 -> 3903.7512 | M39: =-M12 -> 4907.1836 | N39: =-N12 -> 6061.4227 | O39: =-O12 -> 7367.0552 | P39: =-P12 -> 8819.3018 | Q39: =-Q12 -> 10407.29 | R39: =-R12 -> 12169.115 | ... T39: =-T12 -> 16220.496
B40: Rent income received | C40: 28.8 | D40: 28.9 | E40: 35.5 | F40: 46.9 | G40: 49 | H40: 52 | I40: 53.6 | K40: 0 | L40: 0 | M40: 0 | N40: 0 | O40: 0 | P40: 0 | Q40: 0 | R40: 0 | S40: 0 | T40: 0
B41: Purchase of property, plant and equipment, intangible assets, capital work in progress, capital advances and capital creditors (net) | C41: -17121.7 | D41: -20294.2 | E41: -24104.2 | F41: -22119.5 | G41: -27312.5 | H41: -34230.4 | I41: -41133.5 | K41: =-(Schedules!K27) -> -32500 | L41: =-(Schedules!L27) -> -35000 | M41: =-(Schedules!M27) -> -37500 | N41: =-(Schedules!N27) -> -40000 | O41: =-(Schedules!O27) -> -42500 | P41: =-(Schedules!P27) -> -45000 | Q41: =-(Schedules!Q27) -> -47500 | R41: =-(Schedules!R27) -> -50000 | ... T41: =-(Schedules!T27) -> -55000
B42: Purchase of non current investment | C42: -31970 | D42: 0 | E42: 0 | F42: -1930.8 | G42: 927.3 | H42: -20 | I42: 0 | K42: 0 | L42: 0 | M42: 0 | N42: 0 | O42: 0 | P42: 0 | Q42: 0 | R42: 0 | S42: 0 | T42: 0
B43: Proceeds from sale of current investments | C43: 101.6 | D43: 25.6 | E43: 36.6 | F43: 56.6 | G43: 299.1 | H43: 50735.1 | I43: 31226.6 | K43: 0 | M43: 0 | N43: 0 | O43: 0 | P43: 0 | Q43: 0 | R43: 0 | S43: 0 | T43: 0
B44: Purchase of current investments | C44: 0 | D44: 0 | E44: 0 | F44: 0 | G44: 0 | H44: -49463.5 | I44: -31193.4 | K44: 0 | L44: 0 | M44: 0 | N44: 0 | O44: 0 | P44: 0 | Q44: 0 | R44: 0 | S44: 0 | T44: 0
B45: Net cash flow used in investing activities | C45: =SUM(C37:C44) -> -46565.6 | D45: =SUM(D37:D44) -> -11100 | E45: =SUM(E37:E44) -> -12894.9 | F45: =SUM(F37:F44) -> -23131 | G45: =SUM(G37:G44) -> -24682.3 | H45: =SUM(H37:H44) -> -21853.1 | I45: =SUM(I37:I44) -> -42069.6 | K45: =SUM(K37:K44) -> -29440.65 | L45: =SUM(L37:L44) -> -31096.249 | M45: =SUM(M37:M44) -> -32592.816 | N45: =SUM(N37:N44) -> -33938.577 | O45: =SUM(O37:O44) -> -35132.945 | P45: =SUM(P37:P44) -> -36180.698 | Q45: =SUM(Q37:Q44) -> -37092.71 | R45: =SUM(R37:R44) -> -37830.885 | ... T45: =SUM(T37:T44) -> -38779.504
B47: Cash flow from financing activities:
B48: Proceeds from issue of QIP (net of expenses) | C48: 40765.1 | D48: 0 | E48: 0 | F48: 0 | G48: 0 | H48: 0 | I48: 0 | K48: 0 | L48: 0 | M48: 0 | N48: 0 | O48: 0 | P48: 0 | Q48: 0 | R48: 0 | S48: 0 | T48: 0
B49: Proceeds from exercise of share options | C49: 1103.4 | D49: 0 | E49: 0 | F49: 146.3 | G49: 748.1 | H49: 0 | I49: 366.5 | K49: 0 | L49: 0 | M49: 0 | N49: 0 | O49: 0 | P49: 0 | Q49: 0 | R49: 0 | S49: 0 | T49: 0
B50: Proceeds from share application money pending allotment | C50: 0 | D50: 0 | E50: 0 | F50: 9.1 | G50: 0 | H50: 0 | I50: 7.2 | K50: 0 | L50: 0 | M50: 0 | N50: 0 | O50: 0 | P50: 0 | Q50: 0 | R50: 0 | S50: 0 | T50: 0
B51: Proceeds from short term borrowings | C51: 2610.3 | D51: 2000 | E51: 2480 | F51: 0 | G51: 0 | H51: 0 | I51: 9876.1 | K51: 0 | L51: 0 | M51: 0 | N51: 0 | O51: 0 | P51: 0 | Q51: 0 | R51: 0 | S51: 0 | T51: 0
B52: Proceeds from commercial papers | C52: 7894.6 | D52: 0 | E52: 0 | F52: 0 | G52: 0 | H52: 0 | I52: 6000 | K52: 0 | L52: 0 | M52: 0 | N52: 0 | O52: 0 | P52: 0 | Q52: 0 | R52: 0 | S52: 0 | T52: 0
B53: Proceeds of non convertible debentures | C53: 3000 | D53: 0 | E53: 0 | F53: 0 | G53: 0 | H53: 0 | I53: 0 | K53: 0 | L53: 0 | M53: 0 | N53: 0 | O53: 0 | P53: 0 | Q53: 0 | R53: 0 | S53: 0 | T53: 0
B54: Proceeds from long term borrowings | C54: 500 | D54: 0 | E54: 0 | F54: 0 | G54: 0 | H54: 0 | I54: 0 | K54: 0 | L54: 0 | M54: 0 | N54: 0 | O54: 0 | P54: 0 | Q54: 0 | R54: 0 | S54: 0 | T54: 0
B55: Repayment of short term borrowings | C55: -3150 | D55: -2037.3 | E55: 0 | F55: 0 | G55: 0 | H55: 0 | I55: -4026.1 | K55: =BS!K53-BS!I53 -> -9652.7 | L55: =BS!L53-BS!K53 -> 0 | M55: =BS!M53-BS!L53 -> 0 | N55: =BS!N53-BS!M53 -> 0 | O55: =BS!O53-BS!N53 -> 0 | P55: =BS!P53-BS!O53 -> 0 | Q55: =BS!Q53-BS!P53 -> 0 | R55: =BS!R53-BS!Q53 -> 0 | S55: =BS!S53-BS!R53 -> 0 | T55: =BS!T53-BS!S53 -> 0
B56: Repayment of commercial papers | C56: -10349.9 | D56: 0 | E56: 0 | F56: 0 | G56: 0 | H56: 0 | I56: -6000 | K56: 0 | L56: 0 | M56: 0 | N56: 0 | O56: 0 | P56: 0 | Q56: 0 | R56: 0 | S56: 0 | T56: 0
B57: Repayment of non convertible debentures | C57: -5120 | D57: -340 | E57: -2480 | F57: 0 | G57: 0 | H57: 0 | I57: 0 | K57: 0 | L57: 0 | M57: 0 | N57: 0 | O57: 0 | P57: 0 | Q57: 0 | R57: 0 | S57: 0 | T57: 0
B58: Repayment of long term borrowings | C58: -2000 | D58: 0 | E58: 0 | F58: 0 | G58: 0 | H58: 0 | I58: 0 | K58: 0 | L58: 0 | M58: 0 | N58: 0 | O58: 0 | P58: 0 | Q58: 0 | R58: 0 | S58: 0 | T58: 0
B59: Payment of lease liabilities | C59: -997.6 | D59: -981.7 | E59: -1254.5 | F59: -1532.7 | G59: -1643.2 | H59: -1898.5 | I59: -1935.1 | K59: =Schedules!K40 -> -3171.8 | L59: =Schedules!L40 -> -4087.9538 | M59: =Schedules!M40 -> -4193.7236 | N59: =Schedules!N40 -> -4272.3429 | O59: =Schedules!O40 -> -4330.7811 | P59: =Schedules!P40 -> -4374.2186 | Q59: =Schedules!Q40 -> -4406.5059 | R59: =Schedules!R40 -> -4430.762 | ... T59: =Schedules!T40 -> -4462.8974
B60: Interest paid on lease liabilities | C60: 0 | D60: -375 | E60: -522.3 | F60: -663.7 | G60: -569.6 | H60: -672.9 | I60: -1207.6 | K60: =-Schedules!K65 -> -1578.3068 | L60: =-Schedules!L65 -> -1619.1432 | M60: =-Schedules!M65 -> -1649.4971 | N60: =-Schedules!N65 -> -1672.0593 | O60: =-Schedules!O65 -> -1688.83 | P60: =-Schedules!P65 -> -1701.2957 | Q60: =-Schedules!Q65 -> -1710.6606 | R60: =-Schedules!R65 -> -1717.7208 | ... T60: =-Schedules!T65 -> -1727.1413
B61: Interest paid | C61: -681.7 | D61: -61 | E61: -15.6 | F61: -10.4 | G61: -11.7 | H61: -21.6 | I61: -199.2 | K61: =-(SUM(Schedules!K66:K67)) -> -202.06667 | L61: =-(SUM(Schedules!L66:L67)) -> -202.06667 | M61: =-(SUM(Schedules!M66:M67)) -> -202.06667 | N61: =-(SUM(Schedules!N66:N67)) -> -202.06667 | O61: =-(SUM(Schedules!O66:O67)) -> -202.06667 | P61: =-(SUM(Schedules!P66:P67)) -> -202.06667 | Q61: =-(SUM(Schedules!Q66:Q67)) -> -202.06667 | R61: =-(SUM(Schedules!R66:R67)) -> -202.06667 | ... T61: =-(SUM(Schedules!T66:T67)) -> -202.06667
B62: Cash flow from/(used in) financing activities | C62: =SUM(C48:C61) -> 33574.2 | D62: =SUM(D48:D61) -> -1795 | E62: =SUM(E48:E61) -> -1792.4 | F62: =SUM(F48:F61) -> -2051.4 | G62: =SUM(G48:G61) -> -1476.4 | H62: =SUM(H48:H61) -> -2593 | I62: =SUM(I48:I61) -> 2881.8 | K62: =SUM(K48:K61) -> -14604.873 | L62: =SUM(L48:L61) -> -5909.1636 | M62: =SUM(M48:M61) -> -6045.2873 | N62: =SUM(N48:N61) -> -6146.4689 | O62: =SUM(O48:O61) -> -6221.6777 | P62: =SUM(P48:P61) -> -6277.5809 | Q62: =SUM(Q48:Q61) -> -6319.2332 | R62: =SUM(R48:R61) -> -6350.5494 | ... T62: =SUM(T48:T61) -> -6392.1053
B64: Net Increase/(decrease) in cash and cash equivalent | C64: -190 | D64: 856.4 | E64: -963.8 | F64: 1120.3 | G64: 1299.7 | H64: 183.6 | I64: 4520.4 | K64: =K34+K45+K62 -> 4221.8061 | L64: =L34+L45+L62 -> 26374.44 | M64: =M34+M45+M62 -> 39002.606 | N64: =N34+N45+N62 -> 56295.692 | O64: =O34+O45+O62 -> 77110.991 | P64: =P34+P45+P62 -> 100209.74 | Q64: =Q34+Q45+Q62 -> 126449.59 | R64: =R34+R45+R62 -> 155413.7 | ... T64: =T34+T45+T62 -> 223529.87
B65: Cash and cash equivalents at beginning of the year | C65: 1248.6 | D65: 1058.6 | E65: 1915 | F65: 951.2 | G65: 2071.5 | H65: 3371.2 | I65: 3554.8 | K65: =I69 -> 2837.1 | L65: =K69 -> 7058.9061 | M65: =L69 -> 33433.347 | N65: =M69 -> 72435.953 | O65: =N69 -> 128731.64 | P65: =O69 -> 205842.64 | Q65: =P69 -> 306052.37 | R65: =Q69 -> 432501.96 | S65: =R69 -> 587915.66 | T65: =S69 -> 775677.39
B66: Cash and cash equivalents at end of the year (net of bank overdrawn balances) | C66: 1058.6 | D66: 1915 | E66: 951.2 | F66: 2071.5 | G66: 3371.2 | H66: 3554.8 | I66: -965.6 | K66: =K64+K65 -> 7058.9061 | L66: =L64+L65 -> 33433.347 | M66: =M64+M65 -> 72435.953 | N66: =N64+N65 -> 128731.64 | O66: =O64+O65 -> 205842.64 | P66: =P64+P65 -> 306052.37 | Q66: =Q64+Q65 -> 432501.96 | R66: =R64+R65 -> 587915.66 | ... T66: =T64+T65 -> 999207.26
C67: 0 | D67: 0 | E67: 0 | F67: 0 | G67: 0 | H67: 0 | I67: 0
B68: Cash and cash equivalents as per above comprises of the following:
B69: Cash and cash equivalents | C69: 1058.7 | D69: 1915 | E69: 951.2 | F69: 2071.5 | G69: 3371.2 | H69: 3554.8 | I69: 2837.1 | K69: =K66 -> 7058.9061 | L69: =L66 -> 33433.347 | M69: =M66 -> 72435.953 | N69: =N66 -> 128731.64 | O69: =O66 -> 205842.64 | P69: =P66 -> 306052.37 | Q69: =Q66 -> 432501.96 | R69: =R66 -> 587915.66 | ... T69: =T66 -> 999207.26
B70: Bank overdrawn | C70: -0.1 | D70: 0 | E70: 0 | F70: 0 | G70: 0 | H70: 0 | I70: -3802.7 | K70: 0 | L70: 0 | M70: 0 | N70: 0 | O70: 0 | P70: 0 | Q70: 0 | R70: 0 | S70: 0 | T70: 0
B71: Balance as per statement of cash flows | C71: 1058.6 | D71: 1915 | E71: 951.2 | F71: 2071.5 | G71: 3371.2 | H71: 3554.8 | I71: -965.6 | K71: =SUM(K69:K70) -> 7058.9061 | L71: =SUM(L64:L70) -> 100300.04 | M71: =SUM(M64:M70) -> 217307.86 | N71: =SUM(N64:N70) -> 386194.93 | O71: =SUM(O64:O70) -> 617527.91 | P71: =SUM(P64:P70) -> 918157.12 | Q71: =SUM(Q64:Q70) -> 1297505.9 | R71: =SUM(R64:R70) -> 1763747 | S71: =SUM(S64:S70) -> 2327032.2 | T71: =SUM(T64:T70) -> 2997621.8

Sheet DCF Valuation
B2: DCF Valuation- Avenue Supermarts Limited
B5: (In Millions) | C5: 46112 | E5: =EOMONTH(C5,12) -> 46477 | F5: =EOMONTH(E5,12) -> 46843 | G5: =EOMONTH(F5,12) -> 47208 | H5: =EOMONTH(G5,12) -> 47573 | I5: =EOMONTH(H5,12) -> 47938 | J5: =EOMONTH(I5,12) -> 48304 | K5: =EOMONTH(J5,12) -> 48669 | L5: =EOMONTH(K5,12) -> 49034 | M5: =EOMONTH(L5,12) -> 49399 | N5: =EOMONTH(M5,12) -> 49765 | P5: WAAC | Q5: Terminal rate
B6: EBIT (1-Tax rate) | C6: ='P & L'!I20*(1-'DCF Valuation'!$C$28) -> 30200.54 | E6: ='P & L'!K20*(1-'DCF Valuation'!$C$28) -> 47722.872 | F6: ='P & L'!L20*(1-'DCF Valuation'!$C$28) -> 62651.257 | G6: ='P & L'!M20*(1-'DCF Valuation'!$C$28) -> 80179.197 | H6: ='P & L'!N20*(1-'DCF Valuation'!$C$28) -> 100421.07 | I6: ='P & L'!O20*(1-'DCF Valuation'!$C$28) -> 123412.57 | J6: ='P & L'!P20*(1-'DCF Valuation'!$C$28) -> 149065 | K6: ='P & L'!Q20*(1-'DCF Valuation'!$C$28) -> 177176.9 | L6: ='P & L'!R20*(1-'DCF Valuation'!$C$28) -> 208452.92 | ... N6: ='P & L'!T20*(1-'DCF Valuation'!$C$28) -> 280611.89
B7: Add: Depreciation and Amortization | C7: =-'P & L'!I19 -> 10370.2 | E7: =-'P & L'!K19 -> 12200.967 | F7: =-'P & L'!L19 -> 13155.015 | G7: =-'P & L'!M19 -> 14580.023 | H7: =-'P & L'!N19 -> 16109.765 | I7: =-'P & L'!O19 -> 17710.104 | J7: =-'P & L'!P19 -> 19381.443 | K7: =-'P & L'!Q19 -> 21124.15 | L7: =-'P & L'!R19 -> 22938.512 | ... N7: =-'P & L'!T19 -> 26782.808 | P7: =C21 -> 3140.5221 | Q7: 0.03 | R7: 0.04 | S7: 0.045 | T7: 0.06 | U7: 0.07
B8: Less: Capex | C8: ='Cash flow statement'!I41 -> -41133.5 | E8: ='Cash flow statement'!K41 -> -32500 | F8: ='Cash flow statement'!L41 -> -35000 | G8: ='Cash flow statement'!M41 -> -37500 | H8: ='Cash flow statement'!N41 -> -40000 | I8: ='Cash flow statement'!O41 -> -42500 | J8: ='Cash flow statement'!P41 -> -45000 | K8: ='Cash flow statement'!Q41 -> -47500 | L8: ='Cash flow statement'!R41 -> -50000 | ... N8: ='Cash flow statement'!T41 -> -55000 | P8: 0.09 | Q8: 3241.6717 | R8: 3756.9477 | S8: 4100.4649 | T8: 5818.0513 | U8: 8394.4309
B9: (+/-) Changes in working capital | C9: =SUM('Cash flow statement'!I19:I31) -> -6985.1 | E9: =SUM('Cash flow statement'!K19:K31) -> -12949.892 | F9: =SUM('Cash flow statement'!L19:L31) -> -13525.716 | G9: =SUM('Cash flow statement'!M19:M31) -> -18258.219 | H9: =SUM('Cash flow statement'!N19:N31) -> -21289.886 | I9: =SUM('Cash flow statement'!O19:O31) -> -23765.213 | J9: =SUM('Cash flow statement'!P19:P31) -> -26814.398 | K9: =SUM('Cash flow statement'!Q19:Q31) -> -29356.165 | L9: =SUM('Cash flow statement'!R19:R31) -> -32613.538 | ... N9: =SUM('Cash flow statement'!T19:T31) -> -39201.995 | P9: 0.1 | Q9: 2669.041 | R9: 3008.9494 | S9: 3225.2548 | T9: 4198.6289 | U9: 5388.3083
B10: FCFF | C10: =SUM(C6:C9) -> -7547.8604 | E10: =SUM(E6:E9) -> 14473.946 | F10: =SUM(F6:F9) -> 27280.557 | G10: =SUM(G6:G9) -> 39001.001 | H10: =SUM(H6:H9) -> 55240.947 | I10: =SUM(I6:I9) -> 74857.465 | J10: =SUM(J6:J9) -> 96632.041 | K10: =SUM(K6:K9) -> 121444.88 | L10: =SUM(L6:L9) -> 148777.89 | ... N10: =SUM(N6:N9) -> 213192.7 | P10: 0.10866338 | Q10: 2295.5892 | R10: 2542.44 | S10: 2694.9462 | T10: 3340.4987 | U10: 4049.1462
B11: Terminal Value | E11: 0 | F11: 0 | G11: 0 | H11: 0 | I11: 0 | J11: 0 | K11: 0 | L11: 0 | M11: 0 | N11: =N10*(1+$C$31)/($C$29-$C$31) -> 3962948.6 | P11: 0.12 | Q11: 1921.0861 | R11: 2090.5633 | S11: 2192.2497 | T11: 2598.995 | U11: 3005.7403
B12: Toatal FCFF | E12: =SUM(E10:E11) -> 14473.946 | F12: =SUM(F10:F11) -> 27280.557 | G12: =SUM(G10:G11) -> 39001.001 | H12: =SUM(H10:H11) -> 55240.947 | I12: =SUM(I10:I11) -> 74857.465 | J12: =SUM(J10:J11) -> 96632.041 | K12: =SUM(K10:K11) -> 121444.88 | L12: =SUM(L10:L11) -> 148777.89 | ... N12: =SUM(N10:N11) -> 4176141.3 | P12: 0.13 | Q12: 1665.5944 | R12: 1791.0739 | S12: 1864.8853 | T12: 2149.5867 | U12: 2418.4713
B14: Discounted FCFF | E14: =E12/(1+$C$29)^E53 -> 13689.691 | F14: =F12/(1+$C$29)^F53 -> 23393.166 | G14: =G12/(1+$C$29)^G53 -> 30328.918 | H14: =H12/(1+$C$29)^H53 -> 38957.195 | I14: =I12/(1+$C$29)^I53 -> 47874.811 | J14: =J12/(1+$C$29)^J53 -> 56030.202 | K14: =K12/(1+$C$29)^K53 -> 63859.521 | L14: =L12/(1+$C$29)^L53 -> 70946.379 | ... N14: =N12/(1+$C$29)^N53 -> 1637349.8
B16: Enterprise Value | C16: =SUM(E14:N14) -> 2059988.2 | Q16: Very low | R16: Low | S16: Actual | T16: High | U16: Very high
B17: Less: Net debt | C17: =-C46 -> -15562.8 | P17: WAAC | Q17: 0.09 | R17: 0.1 | S17: =(C24*C25)+(C26*(C27*(1-C28))) -> 0.10121733 | T17: 0.12 | U17: 0.13
B18: Add: Non-operational assets | C18: =BS!I13 -> 72.6 | P18: Terminal rate | Q18: 0.03 | R18: 0.04 | S18: 0.045 | T18: 0.06 | U18: 0.07
B19: Equity value | C19: =SUM(C16:C18) -> 2044498
B21: Target price | C21: =C19/C41 -> 3140.5221
B23: Calculations: | P23: Sensitivity Analysis | Q23: WAAC | R23: Actual
B24: Equity weightage % | C24: =C42/$C$48 -> 0.99371712 | Q24: Terminal rate | R24: Actual
B25: Cost of equity | C25: =C37 -> 0.10150066
B26: Debt weightage % | C26: =C46/$C$48 -> 0.0062828832
B27: Cost of debt | C27: 0.0775
B28: Tax rate | C28: =-'P & L'!I31 -> 0.27220074
B29: WAAC | C29: =INDEX($Q$17:$U$18,MATCH($Q$23,$P$17:$P$18,0),MATCH($R$23,$Q$16:$U$16,0)) -> 0.10121733
B31: Terminal growth rate | C31: =INDEX($Q$17:$U$18,MATCH($Q$24,$P$17:$P$18,0), MATCH($R$24,$Q$16:$U$16,0)) -> 0.045
B33: CAPM calculation:
B34: Risk free rate | C34: 0.06942
B35: Beta | C35: 0.877
B36: Market rate | C36: 0.106
B37: Cost of equity | C37: =C34+(C35*(C36-C34)) -> 0.10150066
B39: Calculation of capital invested:
B40: Share price | C40: 3781
B41: Outstanding shares | C41: =651005781/10^6 -> 651.00578
B42: Market capitalization | C42: =C40*C41 -> 2461452.9
B44: Debt | C44: =BS!I46+BS!I54 -> 14597.2
B45: Cash | C45: ='Cash flow statement'!I71 -> -965.6
B46: Net debt | C46: =C44-C45 -> 15562.8
B48: Total capital | C48: =C42+C46 -> 2477015.7
B50: Date of calculation | C50: =TODAY() -> 46269
B51: Days per year | C51: 360
B52: Days count till the present day | C52: 0 | E52: =E5-$C$50 -> 208 | F52: =F5-$C$50 -> 574 | G52: =G5-$C$50 -> 939 | H52: =H5-$C$50 -> 1304 | I52: =I5-$C$50 -> 1669 | J52: =J5-$C$50 -> 2035 | K52: =K5-$C$50 -> 2400 | L52: =L5-$C$50 -> 2765 | ... N52: =N5-$C$50 -> 3496
B53: Number of years calculation | C53: 0 | E53: =E52/$C$51 -> 0.57777778 | F53: =F52/$C$51 -> 1.5944444 | G53: =G52/$C$51 -> 2.6083333 | H53: =H52/$C$51 -> 3.6222222 | I53: =I52/$C$51 -> 4.6361111 | J53: =J52/$C$51 -> 5.6527778 | K53: =K52/$C$51 -> 6.6666667 | L53: =L52/$C$51 -> 7.6805556 | ... N53: =N52/$C$51 -> 9.7111111
